[
  {
    "address": "EQDvonw3GaGFdLleBu0YN34w2ujKgXVm7I9m5Bsfq_V3pb4b",
    "is_active": true,
    "node_registry": "EQDbPc6xGV6-nCmDH8bVXUdQCQ1tXMM062Xah-63HAMAkpq8",
    "owner": "EQA0ltvrkBHmBa0QSTNHcZSUNIvha1F6hTwCCMGPbyVPNpTq",
    "total_ratings": 0,
    "rating_count": 0,
    "average_rating": 0,
    "plan": "time",
    "hostname": "kr.cdn-vk.run",
    "country": "RU",
    "region": "Krasnodarskiy kray",
    "city": "Krasnodar",
    "ip": "193.124.121.148",
    "exit_ip": null,
    "ssl": true,
    "check_port": 443,
    "api_port": 443,
    "api_path": "/api/v1",
    "public_key": "ac4f0bf9cf736c651523c52b3175ba0b9c1b43568213ada1a18878c661872e00",
    "node_id": 192812381208148,
    "scanned": "2026-03-19T03:34:23.726848Z",
    "heartbeat": "2026-03-19T03:34:05.598724Z",
    "health_check": "2026-03-19T03:34:07.716290Z",
    "version": "1.1.5",
    "uptime": 99,
    "limit": 100,
    "upload": 0,
    "download": 0,
    "disk": 81.3,
    "mem": 47.63,
    "cpu": 1.0101010110512423,
    "uptime_sec": 576559,
    "net_download": 175583,
    "net_upload": 175409,
    "traffic_users": 2220932098330,
    "traffic_node": 10588123698022,
    "users": 2
  },
  {
    "address": "EQDcR5e-MXXPrC3HaF2PPwBjMR-0Bui6hsqmUU40mqkcnF9F",
    "is_active": true,
    "node_registry": "EQDbPc6xGV6-nCmDH8bVXUdQCQ1tXMM062Xah-63HAMAkpq8",
    "owner": "EQA0ltvrkBHmBa0QSTNHcZSUNIvha1F6hTwCCMGPbyVPNpTq",
    "total_ratings": 0,
    "rating_count": 0,
    "average_rating": 0,
    "plan": "time",
    "hostname": "fr.cdn-vk.run",
    "country": "FR",
    "region": "\u00cele-de-France",
    "city": "Paris",
    "ip": "82.22.50.7",
    "exit_ip": null,
    "ssl": true,
    "check_port": 443,
    "api_port": 443,
    "api_path": "/api/v1",
    "public_key": "115b6e95aa7ed4fe1221822b148a6be6b7e466bccc1f8bddc265066b2d6da9d2",
    "node_id": 8182184987,
    "scanned": "2026-03-19T03:34:23.485597Z",
    "heartbeat": "2026-03-19T03:33:53.002662Z",
    "health_check": "2026-03-19T03:34:07.338873Z",
    "version": "1.1.5",
    "uptime": 99,
    "limit": 100,
    "upload": 0,
    "download": 0,
    "disk": 24.87,
    "mem": 49.96,
    "cpu": 37.11340206457768,
    "uptime_sec": 612456,
    "net_download": 1247120,
    "net_upload": 1276624,
    "traffic_users": 2520278727832,
    "traffic_node": 6705704627796,
    "users": 13
  },
  {
    "address": "EQDY_NQTaVHG9oPwKmWzD8AG-jyF8bkJnYEcay9HU-N7MUC6",
    "is_active": true,
    "node_registry": "EQDbPc6xGV6-nCmDH8bVXUdQCQ1tXMM062Xah-63HAMAkpq8",
    "owner": "EQA0ltvrkBHmBa0QSTNHcZSUNIvha1F6hTwCCMGPbyVPNpTq",
    "total_ratings": 0,
    "rating_count": 0,
    "average_rating": 0,
    "plan": "time",
    "hostname": "kz.yastatic.site",
    "country": "KZ",
    "region": "Astana",
    "city": "Astana",
    "ip": "5.180.46.29",
    "exit_ip": null,
    "ssl": true,
    "check_port": 443,
    "api_port": 443,
    "api_path": "/api/v1",
    "public_key": "38ee30de71a8452ac39f863f06fa3351af319836f81b4aa90b0482835ba9f1ce",
    "node_id": 48179845829,
    "scanned": "2026-03-19T03:34:23.224154Z",
    "heartbeat": "2026-03-19T03:33:56.776006Z",
    "health_check": "2026-03-19T03:34:07.682878Z",
    "version": "1.1.5",
    "uptime": 100,
    "limit": 100,
    "upload": 342,
    "download": 1327,
    "disk": 28.55,
    "mem": 62.5,
    "cpu": 24.352331606274262,
    "uptime_sec": 32889,
    "net_download": 108897,
    "net_upload": 96744,
    "traffic_users": 6637887922207,
    "traffic_node": 16673753410133,
    "users": 20
  },
  {
    "address": "EQDYWBXU-nPoWt4FUJNsdQ2Rjfyi8Lf3ufzZcqoA47S1oJob",
    "is_active": true,
    "node_registry": "EQDbPc6xGV6-nCmDH8bVXUdQCQ1tXMM062Xah-63HAMAkpq8",
    "owner": "EQA0ltvrkBHmBa0QSTNHcZSUNIvha1F6hTwCCMGPbyVPNpTq",
    "total_ratings": 0,
    "rating_count": 0,
    "average_rating": 0,
    "plan": "time",
    "hostname": "is.edge-apple.online",
    "country": "IS",
    "region": "Reykjanesb\u00e6r",
    "city": "Keflav\u00edk",
    "ip": "82.22.53.38",
    "exit_ip": null,
    "ssl": true,
    "check_port": 443,
    "api_port": 443,
    "api_path": "/api/v1",
    "public_key": "8082620a175c8d4e707848125085696e7703e14d7530368bf4ec8ff6cf9141b2",
    "node_id": 81821852838,
    "scanned": "2026-03-19T03:34:22.652356Z",
    "heartbeat": "2026-03-19T03:34:17.431031Z",
    "health_check": "2026-03-19T03:34:07.532116Z",
    "version": "1.1.5",
    "uptime": 100,
    "limit": 100,
    "upload": 64,
    "download": 258,
    "disk": 33.63,
    "mem": 36.7,
    "cpu": 1.0101010804181925,
    "uptime_sec": 601193,
    "net_download": 588,
    "net_upload": 594,
    "traffic_users": 400844758987,
    "traffic_node": 1216136095302,
    "users": 3
  },
  {
    "address": "EQDWdWtcCwGNNVND8C00IAM1xPpQDp3m1IdM67D1-chLoiVe",
    "is_active": true,
    "node_registry": "EQDbPc6xGV6-nCmDH8bVXUdQCQ1tXMM062Xah-63HAMAkpq8",
    "owner": "EQA0ltvrkBHmBa0QSTNHcZSUNIvha1F6hTwCCMGPbyVPNpTq",
    "total_ratings": 0,
    "rating_count": 0,
    "average_rating": 0,
    "plan": "time",
    "hostname": "k.cdn-vk.run",
    "country": "RU",
    "region": "Kuzbass",
    "city": "Kemerovo",
    "ip": "77.110.112.64",
    "exit_ip": null,
    "ssl": true,
    "check_port": 443,
    "api_port": 443,
    "api_path": "/api/v1",
    "public_key": "3da82636c5cfa428209f58465ea7daf1b2ed10ffdeba2c27c5f031f7168cc047",
    "node_id": 7681098111864,
    "scanned": "2026-03-19T03:34:22.032629Z",
    "heartbeat": "2026-03-19T03:34:13.525497Z",
    "health_check": "2026-03-19T03:34:09.862992Z",
    "version": "1.1.6",
    "uptime": 99,
    "limit": 100,
    "upload": 0,
    "download": 0,
    "disk": 71.11,
    "mem": 37.27,
    "cpu": 2.00000000174623,
    "uptime_sec": 322294,
    "net_download": 4751,
    "net_upload": 171,
    "traffic_users": 63322121947,
    "traffic_node": 380338692435,
    "users": 2
  },
  {
    "address": "EQDW1FDkKA2rNDJco73gfyhzg-OT4_zd18SJJ-kSUttk2iw2",
    "is_active": true,
    "node_registry": "EQDbPc6xGV6-nCmDH8bVXUdQCQ1tXMM062Xah-63HAMAkpq8",
    "owner": "EQA0ltvrkBHmBa0QSTNHcZSUNIvha1F6hTwCCMGPbyVPNpTq",
    "total_ratings": 0,
    "rating_count": 0,
    "average_rating": 0,
    "plan": "time",
    "hostname": "rude.cdn-vk.run",
    "country": "RU",
    "region": "Moscow",
    "city": "Moscow",
    "ip": "193.247.73.42",
    "exit_ip": null,
    "ssl": true,
    "check_port": 443,
    "api_port": 443,
    "api_path": "/api/v1",
    "public_key": "8fdfadb3e23aa382f4c98127833e4978f8ba7ac3ab839c9f52d4890a68943322",
    "node_id": 1928246872842,
    "scanned": "2026-03-19T03:34:21.510056Z",
    "heartbeat": "2026-03-19T03:34:12.758852Z",
    "health_check": "2026-03-19T03:34:08.669933Z",
    "version": "1.1.6",
    "uptime": 100,
    "limit": 100,
    "upload": 0,
    "download": 0,
    "disk": 47.64,
    "mem": 52.15,
    "cpu": 3.9603960441688195,
    "uptime_sec": 332892,
    "net_download": 17142,
    "net_upload": 17255,
    "traffic_users": 455714294253,
    "traffic_node": 2112209168419,
    "users": 4
  },
  {
    "address": "EQDF6UK5d3F9hMcPBdqxgHwnpDyFi8FjZpV2dKGMQeCCqsTd",
    "is_active": true,
    "node_registry": "EQDbPc6xGV6-nCmDH8bVXUdQCQ1tXMM062Xah-63HAMAkpq8",
    "owner": "EQA0ltvrkBHmBa0QSTNHcZSUNIvha1F6hTwCCMGPbyVPNpTq",
    "total_ratings": 0,
    "rating_count": 0,
    "average_rating": 0,
    "plan": "time",
    "hostname": "web.cdn-vk.rest",
    "country": "BH",
    "region": "Al \u2018\u0100\u015fimah",
    "city": "Manama",
    "ip": "185.253.117.69",
    "exit_ip": null,
    "ssl": true,
    "check_port": 443,
    "api_port": 443,
    "api_path": "/api/v1",
    "public_key": "30ae5c52e4b2969502dd80e79e8b14e6c7199b2e9752935d262facaca3b21cf5",
    "node_id": 18482528116869,
    "scanned": "2026-03-19T03:34:21.084440Z",
    "heartbeat": "2026-03-19T03:33:16.630564Z",
    "health_check": "2026-03-19T03:34:08.057980Z",
    "version": "1.1.5",
    "uptime": 100,
    "limit": 100,
    "upload": 243,
    "download": 325,
    "disk": 26.29,
    "mem": 29.36,
    "cpu": 2.03389830685054,
    "uptime_sec": 614236,
    "net_download": 118106,
    "net_upload": 103438,
    "traffic_users": 881162266378,
    "traffic_node": 2941295445255,
    "users": 2
  },
  {
    "address": "EQDCu-7klU0X0BJ09Atn3zT2WEgzYMYGJ49wTJUY1YEGpJsz",
    "is_active": true,
    "node_registry": "EQDbPc6xGV6-nCmDH8bVXUdQCQ1tXMM062Xah-63HAMAkpq8",
    "owner": "EQA0ltvrkBHmBa0QSTNHcZSUNIvha1F6hTwCCMGPbyVPNpTq",
    "total_ratings": 0,
    "rating_count": 0,
    "average_rating": 0,
    "plan": "time",
    "hostname": "get.cdn-vk.rest",
    "country": "SA",
    "region": "Ar Riy\u0101\u1e11",
    "city": "Riyadh",
    "ip": "185.253.118.233",
    "exit_ip": null,
    "ssl": true,
    "check_port": 443,
    "api_port": 443,
    "api_path": "/api/v1",
    "public_key": "3548eaf740c60c7e277a75abd085c409f112d70dcfb972735977ab8bbeb4cbb2",
    "node_id": 184825281178233,
    "scanned": "2026-03-19T03:34:20.718344Z",
    "heartbeat": "2026-03-19T03:33:33.462429Z",
    "health_check": "2026-03-19T03:34:07.849192Z",
    "version": "1.1.5",
    "uptime": 100,
    "limit": 100,
    "upload": 249,
    "download": 422,
    "disk": 26.25,
    "mem": 25.52,
    "cpu": 0.33333334135305553,
    "uptime_sec": 618383,
    "net_download": 10825,
    "net_upload": 10076,
    "traffic_users": 1366217215578,
    "traffic_node": 3461949089625,
    "users": 2
  },
  {
    "address": "EQD6wzIFOah2NMwBM7VBAQQcEwSu1VteLgLLy9-4RmzuJ4M3",
    "is_active": true,
    "node_registry": "EQDbPc6xGV6-nCmDH8bVXUdQCQ1tXMM062Xah-63HAMAkpq8",
    "owner": "EQA0ltvrkBHmBa0QSTNHcZSUNIvha1F6hTwCCMGPbyVPNpTq",
    "total_ratings": 0,
    "rating_count": 0,
    "average_rating": 0,
    "plan": "time",
    "hostname": "nov.cdn-vk.run",
    "country": "RU",
    "region": "Novosibirsk Oblast",
    "city": "Novosibirsk",
    "ip": "185.21.142.233",
    "exit_ip": null,
    "ssl": true,
    "check_port": 443,
    "api_port": 443,
    "api_path": "/api/v1",
    "public_key": "9615af1c7a5bcf66ffd8e78521d8b5cd4820948edeb42c88c090092d176f5e06",
    "node_id": 18482081418233,
    "scanned": "2026-03-19T03:34:20.142159Z",
    "heartbeat": "2026-03-19T03:33:35.129542Z",
    "health_check": "2026-03-19T03:34:08.532926Z",
    "version": "1.1.6",
    "uptime": 99,
    "limit": 100,
    "upload": 0,
    "download": 0,
    "disk": 41.9,
    "mem": 50.85,
    "cpu": 1.0204081700533714,
    "uptime_sec": 327791,
    "net_download": 2697,
    "net_upload": 4821,
    "traffic_users": 261946970777,
    "traffic_node": 1249301708938,
    "users": 1
  },
  {
    "address": "EQD6uRTOE2HhfvSuonStLzqdStM5Sdhimb4Mj_9wboKv7z12",
    "is_active": true,
    "node_registry": "EQDbPc6xGV6-nCmDH8bVXUdQCQ1tXMM062Xah-63HAMAkpq8",
    "owner": "EQA0ltvrkBHmBa0QSTNHcZSUNIvha1F6hTwCCMGPbyVPNpTq",
    "total_ratings": 0,
    "rating_count": 0,
    "average_rating": 0,
    "plan": "time",
    "hostname": "ae.cdn-vk.run",
    "country": "RU",
    "region": "Moscow",
    "city": "Moscow",
    "ip": "85.192.56.94",
    "exit_ip": null,
    "ssl": true,
    "check_port": 443,
    "api_port": 443,
    "api_path": "/api/v1",
    "public_key": "b1c0baa4c8ace3f074c776ddaab01f8b1ca90ff3ef786a5a98c2c5bece2b7ec3",
    "node_id": 848191855894,
    "scanned": "2026-03-19T03:34:19.803219Z",
    "heartbeat": "2026-03-19T03:34:18.106077Z",
    "health_check": "2026-03-19T03:34:07.976619Z",
    "version": "1.1.6",
    "uptime": 99,
    "limit": 100,
    "upload": 0,
    "download": 0,
    "disk": 25.45,
    "mem": 20.29,
    "cpu": 7.92079208074856,
    "uptime_sec": 323085,
    "net_download": 466545,
    "net_upload": 490512,
    "traffic_users": 887319743616,
    "traffic_node": 4225673355928,
    "users": 5
  },
  {
    "address": "EQD6TxPPibaYdZhY4SKxnaw5U0AM414S9iN4SNpcpzpZhOAw",
    "is_active": true,
    "node_registry": "EQDbPc6xGV6-nCmDH8bVXUdQCQ1tXMM062Xah-63HAMAkpq8",
    "owner": "EQA0ltvrkBHmBa0QSTNHcZSUNIvha1F6hTwCCMGPbyVPNpTq",
    "total_ratings": 0,
    "rating_count": 0,
    "average_rating": 0,
    "plan": "time",
    "hostname": "ua.media-cdn.online",
    "country": "UA",
    "region": "Kyiv City",
    "city": "Kyiv",
    "ip": "5.34.182.90",
    "exit_ip": null,
    "ssl": true,
    "check_port": 443,
    "api_port": 443,
    "api_path": "/api/v1",
    "public_key": "b355ec1119586a4a389e390e169cc964a9c645d229838df16e0c7c03cff9d7af",
    "node_id": 48338181890,
    "scanned": "2026-03-19T03:34:19.540878Z",
    "heartbeat": "2026-03-19T03:33:36.565439Z",
    "health_check": "2026-03-19T03:34:07.439995Z",
    "version": "1.1.6",
    "uptime": 99,
    "limit": 100,
    "upload": 0,
    "download": 0,
    "disk": 67.35,
    "mem": 29.5,
    "cpu": 2.9999999942374416,
    "uptime_sec": 265827,
    "net_download": 67288,
    "net_upload": 1488,
    "traffic_users": 43397176461,
    "traffic_node": 155541949523,
    "users": 2
  },
  {
    "address": "EQD3LT4bTCmjjN7ZRXI5qck7hgMR5iKDWUUGQWd54R2u_M5V",
    "is_active": true,
    "node_registry": "EQDbPc6xGV6-nCmDH8bVXUdQCQ1tXMM062Xah-63HAMAkpq8",
    "owner": "EQA0ltvrkBHmBa0QSTNHcZSUNIvha1F6hTwCCMGPbyVPNpTq",
    "total_ratings": 0,
    "rating_count": 0,
    "average_rating": 0,
    "plan": "time",
    "hostname": "ru.cdn-vk.run",
    "country": "RU",
    "region": "Primorye",
    "city": "Vladivostok",
    "ip": "193.124.9.226",
    "exit_ip": null,
    "ssl": true,
    "check_port": 443,
    "api_port": 443,
    "api_path": "/api/v1",
    "public_key": "fd7e2f846288e7a1aee506adbd281d3ee5682bcf15b03687c01625fc2646eb3d",
    "node_id": 1928123888226,
    "scanned": "2026-03-19T03:34:18.480387Z",
    "heartbeat": "2026-03-19T03:34:09.501649Z",
    "health_check": "2026-03-19T03:34:09.185169Z",
    "version": "1.1.6",
    "uptime": 99,
    "limit": 100,
    "upload": 0,
    "download": 0,
    "disk": 39.84,
    "mem": 62.86,
    "cpu": 12.745098039439476,
    "uptime_sec": 330931,
    "net_download": 1059281,
    "net_upload": 2080528,
    "traffic_users": 145712971054,
    "traffic_node": 763106108540,
    "users": 8
  },
  {
    "address": "EQD1vwDcZN_Q_mPxtHIoLkPW2RoqxmA1ltd1mVSWWjkfrR-S",
    "is_active": true,
    "node_registry": "EQDbPc6xGV6-nCmDH8bVXUdQCQ1tXMM062Xah-63HAMAkpq8",
    "owner": "EQA0ltvrkBHmBa0QSTNHcZSUNIvha1F6hTwCCMGPbyVPNpTq",
    "total_ratings": 0,
    "rating_count": 0,
    "average_rating": 0,
    "plan": "time",
    "hostname": "ph.edge-apple.online",
    "country": "PH",
    "region": "National Capital Region",
    "city": "Makati",
    "ip": "206.237.107.68",
    "exit_ip": null,
    "ssl": true,
    "check_port": 443,
    "api_port": 443,
    "api_path": "/api/v1",
    "public_key": "b3cb2c6b7d9f82c4803570d273d79e65539c807df03594ce2dd1cbcd0ab7e074",
    "node_id": 20582368106868,
    "scanned": "2026-03-19T03:34:17.265511Z",
    "heartbeat": "2026-03-19T03:34:10.334433Z",
    "health_check": "2026-03-19T03:34:10.427641Z",
    "version": "1.1.5",
    "uptime": 100,
    "limit": 100,
    "upload": 0,
    "download": 0,
    "disk": 37.86,
    "mem": 25.85,
    "cpu": 0.0,
    "uptime_sec": 597705,
    "net_download": 2125320,
    "net_upload": 2331959,
    "traffic_users": 29850760979,
    "traffic_node": 176215180646,
    "users": 1
  },
  {
    "address": "EQCwbNWT6x5mWBaajKOd5H5qgYbMgL1o3yhEtWUUqcURUHpT",
    "is_active": true,
    "node_registry": "EQDbPc6xGV6-nCmDH8bVXUdQCQ1tXMM062Xah-63HAMAkpq8",
    "owner": "EQA0ltvrkBHmBa0QSTNHcZSUNIvha1F6hTwCCMGPbyVPNpTq",
    "total_ratings": 0,
    "rating_count": 0,
    "average_rating": 0,
    "plan": "time",
    "hostname": "uk.yastatic.site",
    "country": "GB",
    "region": "England",
    "city": "London",
    "ip": "173.208.51.125",
    "exit_ip": null,
    "ssl": true,
    "check_port": 443,
    "api_port": 443,
    "api_path": "/api/v1",
    "public_key": "27fc7ff150dd726129385d842989efc775b12a38817fc9dd90fb1ed403419aae",
    "node_id": 17282078508125,
    "scanned": "2026-03-19T03:34:17.024092Z",
    "heartbeat": "2026-03-19T03:33:34.876802Z",
    "health_check": "2026-03-19T03:34:07.704798Z",
    "version": "1.1.5",
    "uptime": 99,
    "limit": 100,
    "upload": 0,
    "download": 0,
    "disk": 5.16,
    "mem": 8.99,
    "cpu": 6.4999999944120646,
    "uptime_sec": 612440,
    "net_download": 763299,
    "net_upload": 768516,
    "traffic_users": 3077332348633,
    "traffic_node": 8553625284884,
    "users": 21
  },
  {
    "address": "EQCu8Ot-tqwpEsCoyZ9ETio7IdajO6N9RleQQI0gYlfE32iU",
    "is_active": true,
    "node_registry": "EQDbPc6xGV6-nCmDH8bVXUdQCQ1tXMM062Xah-63HAMAkpq8",
    "owner": "EQA0ltvrkBHmBa0QSTNHcZSUNIvha1F6hTwCCMGPbyVPNpTq",
    "total_ratings": 0,
    "rating_count": 0,
    "average_rating": 0,
    "plan": "time",
    "hostname": "ph.yastatic.site",
    "country": "PH",
    "region": "National Capital Region",
    "city": "Manila",
    "ip": "118.194.239.60",
    "exit_ip": null,
    "ssl": true,
    "check_port": 443,
    "api_port": 443,
    "api_path": "/api/v1",
    "public_key": "5e921e4eeafd816189da3278173d9a253870c0af0199db7e6d51687101c9e144",
    "node_id": 11781938238860,
    "scanned": "2026-03-19T03:34:15.537458Z",
    "heartbeat": "2026-03-19T03:32:57.367617Z",
    "health_check": "2026-03-19T03:34:10.602317Z",
    "version": "1.1.5",
    "uptime": 100,
    "limit": 100,
    "upload": 29,
    "download": 45,
    "disk": 15.58,
    "mem": 34.7,
    "cpu": 1.030927907308479,
    "uptime_sec": 576489,
    "net_download": 859453,
    "net_upload": 856384,
    "traffic_users": 564085973533,
    "traffic_node": 1771383391943,
    "users": 1
  },
  {
    "address": "EQCt_0YYtDYxjiu_ON2aJF3N8QQf3yftQ4pa6sYjdTk1jkUf",
    "is_active": true,
    "node_registry": "EQDbPc6xGV6-nCmDH8bVXUdQCQ1tXMM062Xah-63HAMAkpq8",
    "owner": "EQA0ltvrkBHmBa0QSTNHcZSUNIvha1F6hTwCCMGPbyVPNpTq",
    "total_ratings": 0,
    "rating_count": 0,
    "average_rating": 0,
    "plan": "time",
    "hostname": "pl.cdn-vk.run",
    "country": "PL",
    "region": "Mazowieckie",
    "city": "Warsaw",
    "ip": "45.144.49.56",
    "exit_ip": null,
    "ssl": true,
    "check_port": 443,
    "api_port": 443,
    "api_path": "/api/v1",
    "public_key": "ace1db89f5d3c6f0454ff67fefc5f4166f78337c4f04d0fe456a846e48430b0f",
    "node_id": 448143848856,
    "scanned": "2026-03-19T03:34:15.244476Z",
    "heartbeat": "2026-03-19T03:34:11.154364Z",
    "health_check": "2026-03-19T03:34:07.392898Z",
    "version": "1.1.5",
    "uptime": 99,
    "limit": 100,
    "upload": 0,
    "download": 0,
    "disk": 56.19,
    "mem": 58.24,
    "cpu": 4.081632653849125,
    "uptime_sec": 157310,
    "net_download": 367516,
    "net_upload": 418789,
    "traffic_users": 3992302857766,
    "traffic_node": 10134573351509,
    "users": 30
  },
  {
    "address": "EQCqi6Q5WcPFxlbPrJe9bJdWTEDlsMmXAyOofS-xE4a3l_xL",
    "is_active": true,
    "node_registry": "EQDbPc6xGV6-nCmDH8bVXUdQCQ1tXMM062Xah-63HAMAkpq8",
    "owner": "EQA0ltvrkBHmBa0QSTNHcZSUNIvha1F6hTwCCMGPbyVPNpTq",
    "total_ratings": 0,
    "rating_count": 0,
    "average_rating": 0,
    "plan": "time",
    "hostname": "tr.yastatic.site",
    "country": "TR",
    "region": "Ankara",
    "city": "Ankara",
    "ip": "5.180.52.37",
    "exit_ip": null,
    "ssl": true,
    "check_port": 443,
    "api_port": 443,
    "api_path": "/api/v1",
    "public_key": "2f1a5352100ba48ce12aa10ad6618f057dc89299939b35bcfc600c584e646409",
    "node_id": 48179851837,
    "scanned": "2026-03-19T03:34:14.952121Z",
    "heartbeat": "2026-03-19T03:33:55.626195Z",
    "health_check": "2026-03-19T03:34:07.827953Z",
    "version": "1.1.5",
    "uptime": 100,
    "limit": 100,
    "upload": 440,
    "download": 872,
    "disk": 28.53,
    "mem": 47.83,
    "cpu": 6.6666666667288546,
    "uptime_sec": 32740,
    "net_download": 60016,
    "net_upload": 56363,
    "traffic_users": 7210612644981,
    "traffic_node": 18274170466269,
    "users": 18
  },
  {
    "address": "EQCpic66nMCZEdlY5km-G1WEStMc0TixjDryR9xr4sYak9Z8",
    "is_active": true,
    "node_registry": "EQDbPc6xGV6-nCmDH8bVXUdQCQ1tXMM062Xah-63HAMAkpq8",
    "owner": "EQA0ltvrkBHmBa0QSTNHcZSUNIvha1F6hTwCCMGPbyVPNpTq",
    "total_ratings": 0,
    "rating_count": 0,
    "average_rating": 0,
    "plan": "time",
    "hostname": "web.yastatic.site",
    "country": "VN",
    "region": "H\u1ed3 Ch\u00ed Minh",
    "city": "Ho Chi Minh City",
    "ip": "61.14.234.27",
    "exit_ip": null,
    "ssl": true,
    "check_port": 443,
    "api_port": 443,
    "api_path": "/api/v1",
    "public_key": "6fe7e0fbcd1e443941b70bd9ffe259d96d0f95c0dc5af7159fc37547b5fb2688",
    "node_id": 608138233827,
    "scanned": "2026-03-19T03:34:13.393222Z",
    "heartbeat": "2026-03-19T03:33:55.726005Z",
    "health_check": "2026-03-19T03:34:10.194840Z",
    "version": "1.1.5",
    "uptime": 100,
    "limit": 100,
    "upload": 60,
    "download": 73,
    "disk": 40.09,
    "mem": 33.3,
    "cpu": 2.000000048428774,
    "uptime_sec": 618401,
    "net_download": 117274,
    "net_upload": 154229,
    "traffic_users": 325867734118,
    "traffic_node": 1127267352997,
    "users": 3
  },
  {
    "address": "EQCpC9s6Wy0qs9TEcznguDdbz1uZvqHmqPJgureKT3if6RBk",
    "is_active": true,
    "node_registry": "EQDbPc6xGV6-nCmDH8bVXUdQCQ1tXMM062Xah-63HAMAkpq8",
    "owner": "EQA0ltvrkBHmBa0QSTNHcZSUNIvha1F6hTwCCMGPbyVPNpTq",
    "total_ratings": 0,
    "rating_count": 0,
    "average_rating": 0,
    "plan": "time",
    "hostname": "get.cdn-vk.run",
    "country": "FI",
    "region": "",
    "city": "Helsinki",
    "ip": "185.88.101.50",
    "exit_ip": null,
    "ssl": true,
    "check_port": 443,
    "api_port": 443,
    "api_path": "/api/v1",
    "public_key": "ee9aaba20d3a0aec82f1fa88f9ffab0113958eaa206c155e134a4531a1b202af",
    "node_id": 1848878100850,
    "scanned": "2026-03-19T03:34:12.863284Z",
    "heartbeat": "2026-03-19T03:33:40.821047Z",
    "health_check": "2026-03-19T03:34:08.683883Z",
    "version": "1.1.5",
    "uptime": 99,
    "limit": 100,
    "upload": 198,
    "download": 203,
    "disk": 61.69,
    "mem": 63.79,
    "cpu": 16.32653058800181,
    "uptime_sec": 128360,
    "net_download": 334689,
    "net_upload": 379406,
    "traffic_users": 4917040532608,
    "traffic_node": 11103772650296,
    "users": 17
  },
  {
    "address": "EQCbeMzO3tNf06mZymWt60aSx7VbWkpZEu6kAoVvo5u7SmMS",
    "is_active": true,
    "node_registry": "EQDbPc6xGV6-nCmDH8bVXUdQCQ1tXMM062Xah-63HAMAkpq8",
    "owner": "EQA0ltvrkBHmBa0QSTNHcZSUNIvha1F6hTwCCMGPbyVPNpTq",
    "total_ratings": 0,
    "rating_count": 0,
    "average_rating": 0,
    "plan": "time",
    "hostname": "nl.edge-apple.online",
    "country": "NL",
    "region": "North Holland",
    "city": "Amsterdam",
    "ip": "45.15.128.126",
    "exit_ip": null,
    "ssl": true,
    "check_port": 443,
    "api_port": 443,
    "api_path": "/api/v1",
    "public_key": "bfb8c44542fcc47026f38b519fb221677bf1342948cea0c9234d4f98dbc33602",
    "node_id": 4481481278126,
    "scanned": "2026-03-19T03:34:11.768780Z",
    "heartbeat": "2026-03-19T03:33:38.046544Z",
    "health_check": "2026-03-19T03:34:07.220808Z",
    "version": "1.1.6",
    "uptime": 99,
    "limit": 100,
    "upload": 0,
    "download": 0,
    "disk": 16.79,
    "mem": 58.8,
    "cpu": 44.29223743981544,
    "uptime_sec": 34484,
    "net_download": 1970462,
    "net_upload": 2021099,
    "traffic_users": 597542976964,
    "traffic_node": 1553847484430,
    "users": 17
  },
  {
    "address": "EQCXfCFr_RqyG4B21ZRcfDgpBzEIzQZ3Au6bTz9VMKRoPhNd",
    "is_active": true,
    "node_registry": "EQDbPc6xGV6-nCmDH8bVXUdQCQ1tXMM062Xah-63HAMAkpq8",
    "owner": "EQA0ltvrkBHmBa0QSTNHcZSUNIvha1F6hTwCCMGPbyVPNpTq",
    "total_ratings": 0,
    "rating_count": 0,
    "average_rating": 0,
    "plan": "time",
    "hostname": "api.cdn-vk.run",
    "country": "EE",
    "region": "Harjumaa",
    "city": "Tallinn",
    "ip": "5.180.40.16",
    "exit_ip": null,
    "ssl": true,
    "check_port": 443,
    "api_port": 443,
    "api_path": "/api/v1",
    "public_key": "1ac1984e11805e4d1c6267cb1173438dd2b48787ab0574e436420614796df2e8",
    "node_id": 48179839816,
    "scanned": "2026-03-19T03:34:11.507956Z",
    "heartbeat": "2026-03-19T03:34:01.429755Z",
    "health_check": "2026-03-19T03:34:08.096235Z",
    "version": "1.1.5",
    "uptime": 99,
    "limit": 100,
    "upload": 195,
    "download": 505,
    "disk": 21.65,
    "mem": 62.08,
    "cpu": 7.5757575928617555,
    "uptime_sec": 609220,
    "net_download": 140577,
    "net_upload": 160465,
    "traffic_users": 5849428748656,
    "traffic_node": 15025895127874,
    "users": 25
  },
  {
    "address": "EQCKqB8nDQb0Ejbxl_iG_cdSUYcfezPrSmT3NV5nCMEIruTs",
    "is_active": true,
    "node_registry": "EQDbPc6xGV6-nCmDH8bVXUdQCQ1tXMM062Xah-63HAMAkpq8",
    "owner": "EQA0ltvrkBHmBa0QSTNHcZSUNIvha1F6hTwCCMGPbyVPNpTq",
    "total_ratings": 0,
    "rating_count": 0,
    "average_rating": 0,
    "plan": "time",
    "hostname": "sp.yastatic.site",
    "country": "RU",
    "region": "St.-Petersburg",
    "city": "Saint Petersburg",
    "ip": "83.147.255.125",
    "exit_ip": null,
    "ssl": true,
    "check_port": 443,
    "api_port": 443,
    "api_path": "/api/v1",
    "public_key": "90da8535c2cacef5d55c51ee0fb7c3181a8365aa67c6d17b66ce1a05e2ba152a",
    "node_id": 82814682548125,
    "scanned": "2026-03-19T03:34:11.236713Z",
    "heartbeat": "2026-03-19T03:33:33.349601Z",
    "health_check": "2026-03-19T03:34:08.159198Z",
    "version": "1.1.6",
    "uptime": 99,
    "limit": 100,
    "upload": 0,
    "download": 0,
    "disk": 21.91,
    "mem": 21.78,
    "cpu": 1.0309278300405778,
    "uptime_sec": 321666,
    "net_download": 4424,
    "net_upload": 4608,
    "traffic_users": 188057737925,
    "traffic_node": 1465032943573,
    "users": 1
  },
  {
    "address": "EQCKFi04a6uTYAM7QCyXtnHZ60MPMoyvwMGfrix2UD-7l2Ou",
    "is_active": true,
    "node_registry": "EQDbPc6xGV6-nCmDH8bVXUdQCQ1tXMM062Xah-63HAMAkpq8",
    "owner": "EQA0ltvrkBHmBa0QSTNHcZSUNIvha1F6hTwCCMGPbyVPNpTq",
    "total_ratings": 0,
    "rating_count": 0,
    "average_rating": 0,
    "plan": "time",
    "hostname": "tr.edge-apple.online",
    "country": "TR",
    "region": "\u0130stanbul",
    "city": "Istanbul",
    "ip": "82.26.198.176",
    "exit_ip": null,
    "ssl": true,
    "check_port": 443,
    "api_port": 443,
    "api_path": "/api/v1",
    "public_key": "7bec7babd842c99ac681a425ea43c08e2c0390c3c96e1dce31f697da9bb97520",
    "node_id": 8182581978176,
    "scanned": "2026-03-19T03:34:10.824730Z",
    "heartbeat": "2026-03-19T03:33:58.092386Z",
    "health_check": "2026-03-19T03:34:07.497060Z",
    "version": "1.1.5",
    "uptime": 99,
    "limit": 100,
    "upload": 0,
    "download": 0,
    "disk": 25.44,
    "mem": 39.18,
    "cpu": 1.0101009877705533,
    "uptime_sec": 617314,
    "net_download": 15789,
    "net_upload": 15690,
    "traffic_users": 135060807418,
    "traffic_node": 615819917663,
    "users": 2
  },
  {
    "address": "EQCJLajK__ywESlcb7y4LPYKhQ5_reEsBIgJ1H5kLrabqRDF",
    "is_active": true,
    "node_registry": "EQDbPc6xGV6-nCmDH8bVXUdQCQ1tXMM062Xah-63HAMAkpq8",
    "owner": "EQA0ltvrkBHmBa0QSTNHcZSUNIvha1F6hTwCCMGPbyVPNpTq",
    "total_ratings": 0,
    "rating_count": 0,
    "average_rating": 0,
    "plan": "time",
    "hostname": "vk.com.yastatic.site",
    "country": "CH",
    "region": "Bern",
    "city": "Bern",
    "ip": "45.59.122.235",
    "exit_ip": null,
    "ssl": true,
    "check_port": 443,
    "api_port": 443,
    "api_path": "/api/v1",
    "public_key": "10846484cf93dea2f6ab0bf6361b05d38bc7f3b6f4691846804f4718716a6582",
    "node_id": 4485881218235,
    "scanned": "2026-03-19T03:34:10.436516Z",
    "heartbeat": "2026-03-19T03:33:43.188817Z",
    "health_check": "2026-03-19T03:34:07.357385Z",
    "version": "1.1.5",
    "uptime": 100,
    "limit": 100,
    "upload": 528,
    "download": 2717,
    "disk": 27.01,
    "mem": 65.78,
    "cpu": 11.111111109804542,
    "uptime_sec": 97606,
    "net_download": 496806,
    "net_upload": 516639,
    "traffic_users": 4783946322184,
    "traffic_node": 12514064063816,
    "users": 29
  },
  {
    "address": "EQC2Ps3tmhh-YFZKBvLUoGHs-nNjTJ9UXBejOWhlyuyKEMrk",
    "is_active": true,
    "node_registry": "EQDbPc6xGV6-nCmDH8bVXUdQCQ1tXMM062Xah-63HAMAkpq8",
    "owner": "EQA0ltvrkBHmBa0QSTNHcZSUNIvha1F6hTwCCMGPbyVPNpTq",
    "total_ratings": 0,
    "rating_count": 0,
    "average_rating": 0,
    "plan": "time",
    "hostname": "max.relay-apple.online",
    "country": "AE",
    "region": "Dubayy",
    "city": "Dubai",
    "ip": "89.44.80.2",
    "exit_ip": null,
    "ssl": true,
    "check_port": 443,
    "api_port": 443,
    "api_path": "/api/v1",
    "public_key": "9d7a5cd0f09c7516bb30be8a17c730f73359ceedaffffcfb2ee0c0a5e8231d57",
    "node_id": 8884387982,
    "scanned": "2026-03-19T03:34:10.052508Z",
    "heartbeat": "2026-03-19T03:33:28.537970Z",
    "health_check": "2026-03-19T03:34:07.411323Z",
    "version": "1.1.5",
    "uptime": 100,
    "limit": 100,
    "upload": 153,
    "download": 260,
    "disk": 25.43,
    "mem": 31.9,
    "cpu": 2.6578073112315646,
    "uptime_sec": 618378,
    "net_download": 197359,
    "net_upload": 231743,
    "traffic_users": 600734461059,
    "traffic_node": 1958344667248,
    "users": 6
  },
  {
    "address": "EQC-UjsuvMukXtKKaxBupC2VTSLqc5gl4--10fGHK1TZ-Odf",
    "is_active": true,
    "node_registry": "EQDbPc6xGV6-nCmDH8bVXUdQCQ1tXMM062Xah-63HAMAkpq8",
    "owner": "EQA0ltvrkBHmBa0QSTNHcZSUNIvha1F6hTwCCMGPbyVPNpTq",
    "total_ratings": 0,
    "rating_count": 0,
    "average_rating": 0,
    "plan": "time",
    "hostname": "xxl.cdn-vk.run",
    "country": "NL",
    "region": "Flevoland",
    "city": "Lelystad",
    "ip": "95.211.41.85",
    "exit_ip": null,
    "ssl": true,
    "check_port": 443,
    "api_port": 443,
    "api_path": "/api/v1",
    "public_key": "ccab9e27fdb7b7abe679bb3f0cb63938de5812e434c62efd2371c64cde4c735d",
    "node_id": 948210840885,
    "scanned": "2026-03-19T03:34:09.811986Z",
    "heartbeat": "2026-03-19T03:33:05.624275Z",
    "health_check": "2026-03-19T03:34:07.228999Z",
    "version": "1.1.5",
    "uptime": 96,
    "limit": 100,
    "upload": 0,
    "download": 0,
    "disk": 6.0,
    "mem": 12.95,
    "cpu": 12.039312003666879,
    "uptime_sec": 461413,
    "net_download": 2374994,
    "net_upload": 2379196,
    "traffic_users": 8116923358118,
    "traffic_node": 20536719228259,
    "users": 32
  },
  {
    "address": "EQBqVxQmDa_yX6Ll_V7vuukQPDiTJhVt7Qa6jt-g-YbgaE6U",
    "is_active": true,
    "node_registry": "EQDbPc6xGV6-nCmDH8bVXUdQCQ1tXMM062Xah-63HAMAkpq8",
    "owner": "EQA0ltvrkBHmBa0QSTNHcZSUNIvha1F6hTwCCMGPbyVPNpTq",
    "total_ratings": 0,
    "rating_count": 0,
    "average_rating": 0,
    "plan": "time",
    "hostname": "ekb.cdn-vk.run",
    "country": "RU",
    "region": "Sverdlovsk Oblast",
    "city": "Yekaterinburg",
    "ip": "45.11.27.161",
    "exit_ip": null,
    "ssl": true,
    "check_port": 443,
    "api_port": 443,
    "api_path": "/api/v1",
    "public_key": "8e502bc5aa8aaecd2162eb1ba28121d3bcd26b66e05c7cc9564f50e5103605b9",
    "node_id": 448108268161,
    "scanned": "2026-03-19T03:34:09.351306Z",
    "heartbeat": "2026-03-19T03:33:38.722918Z",
    "health_check": "2026-03-19T03:34:07.854786Z",
    "version": "1.1.6",
    "uptime": 100,
    "limit": 100,
    "upload": 0,
    "download": 0,
    "disk": 29.58,
    "mem": 47.1,
    "cpu": 1.010101010123281,
    "uptime_sec": 11952,
    "net_download": 434,
    "net_upload": 249,
    "traffic_users": 716221420,
    "traffic_node": 7716750639,
    "users": 1
  },
  {
    "address": "EQBpZAWIqdupl-7LhVAgpD_XAWy2I2mpkGmdCHdFd5wWiwCu",
    "is_active": true,
    "node_registry": "EQDbPc6xGV6-nCmDH8bVXUdQCQ1tXMM062Xah-63HAMAkpq8",
    "owner": "EQA0ltvrkBHmBa0QSTNHcZSUNIvha1F6hTwCCMGPbyVPNpTq",
    "total_ratings": 0,
    "rating_count": 0,
    "average_rating": 0,
    "plan": "time",
    "hostname": "de.yastatic.site",
    "country": "DE",
    "region": "Hessen",
    "city": "Frankfurt",
    "ip": "178.162.219.222",
    "exit_ip": null,
    "ssl": true,
    "check_port": 443,
    "api_port": 443,
    "api_path": "/api/v1",
    "public_key": "d80f4a808c9284f843fa9b81fe8490e6bc2f1754c0fc2a3b771ffaba0c2dcf26",
    "node_id": 177816182188222,
    "scanned": "2026-03-19T03:34:09.091871Z",
    "heartbeat": "2026-03-19T03:34:03.349557Z",
    "health_check": "2026-03-19T03:34:07.347266Z",
    "version": "1.1.5",
    "uptime": 94,
    "limit": 100,
    "upload": 0,
    "download": 0,
    "disk": 5.63,
    "mem": 14.91,
    "cpu": 20.090293430708364,
    "uptime_sec": 39088,
    "net_download": 12049639,
    "net_upload": 12123504,
    "traffic_users": 10296017650558,
    "traffic_node": 25897873135445,
    "users": 59
  },
  {
    "address": "EQBmkOJgIOA13bc8Rj4spCwCMqiabuSo1pnFtAPd5Ld1bYno",
    "is_active": true,
    "node_registry": "EQDbPc6xGV6-nCmDH8bVXUdQCQ1tXMM062Xah-63HAMAkpq8",
    "owner": "EQA0ltvrkBHmBa0QSTNHcZSUNIvha1F6hTwCCMGPbyVPNpTq",
    "total_ratings": 0,
    "rating_count": 0,
    "average_rating": 0,
    "plan": "time",
    "hostname": "ph.media-cdn.online",
    "country": "PH",
    "region": "National Capital Region",
    "city": "Makati",
    "ip": "61.245.10.36",
    "exit_ip": null,
    "ssl": true,
    "check_port": 443,
    "api_port": 443,
    "api_path": "/api/v1",
    "public_key": "563d8b95a7abbed4e30b13a66f5205caf3a1dd773c9d3d8da1ab6afe44024d92",
    "node_id": 608244809836,
    "scanned": "2026-03-19T03:34:07.883183Z",
    "heartbeat": "2026-03-19T03:33:41.178904Z",
    "health_check": "2026-03-19T03:34:09.060025Z",
    "version": "1.1.5",
    "uptime": 99,
    "limit": 100,
    "upload": 0,
    "download": 0,
    "disk": 46.8,
    "mem": 31.26,
    "cpu": 0.9999999894062058,
    "uptime_sec": 617295,
    "net_download": 1230,
    "net_upload": 1371,
    "traffic_users": 16315281845,
    "traffic_node": 136234049360,
    "users": 1
  },
  {
    "address": "EQBlby9LXxGbLz2XfW42iLo3899Os3uGxYVvw3KG5Vmk690s",
    "is_active": true,
    "node_registry": "EQDbPc6xGV6-nCmDH8bVXUdQCQ1tXMM062Xah-63HAMAkpq8",
    "owner": "EQA0ltvrkBHmBa0QSTNHcZSUNIvha1F6hTwCCMGPbyVPNpTq",
    "total_ratings": 0,
    "rating_count": 0,
    "average_rating": 0,
    "plan": "time",
    "hostname": "os.cdn-vk.run",
    "country": "RU",
    "region": "Moscow",
    "city": "Moscow",
    "ip": "194.87.57.104",
    "exit_ip": null,
    "ssl": true,
    "check_port": 443,
    "api_port": 443,
    "api_path": "/api/v1",
    "public_key": "c8626b746313a95da2a5e0a00c3e9e2219cd186a16fe4adc9c89b049cb1210ea",
    "node_id": 1938868568104,
    "scanned": "2026-03-19T03:34:07.549474Z",
    "heartbeat": "2026-03-19T03:34:07.189228Z",
    "health_check": "2026-03-19T03:34:07.522632Z",
    "version": "1.1.6",
    "uptime": 99,
    "limit": 100,
    "upload": 0,
    "download": 0,
    "disk": 38.72,
    "mem": 51.57,
    "cpu": 15.000000002328306,
    "uptime_sec": 327517,
    "net_download": 986889,
    "net_upload": 1238424,
    "traffic_users": 114234769555,
    "traffic_node": 595175452915,
    "users": 4
  },
  {
    "address": "EQBjKJ772islNaW9neRjsZIVAb8GVg4bhbbnH10NkqXs0lCi",
    "is_active": true,
    "node_registry": "EQDbPc6xGV6-nCmDH8bVXUdQCQ1tXMM062Xah-63HAMAkpq8",
    "owner": "EQA0ltvrkBHmBa0QSTNHcZSUNIvha1F6hTwCCMGPbyVPNpTq",
    "total_ratings": 0,
    "rating_count": 0,
    "average_rating": 0,
    "plan": "time",
    "hostname": "host.cdn-vk.run",
    "country": "RU",
    "region": "Moscow",
    "city": "Moscow",
    "ip": "185.130.212.84",
    "exit_ip": null,
    "ssl": true,
    "check_port": 443,
    "api_port": 443,
    "api_path": "/api/v1",
    "public_key": "a3017d09a77cdd5ae7f4bd7f925e1c46afb6b7f5c85e1f5374d5ba1c1c69b8e5",
    "node_id": 18481298211884,
    "scanned": "2026-03-19T03:34:07.021304Z",
    "heartbeat": "2026-03-19T03:34:18.585197Z",
    "health_check": "2026-03-19T03:34:08.087256Z",
    "version": "1.1.6",
    "uptime": 100,
    "limit": 100,
    "upload": 0,
    "download": 0,
    "disk": 32.79,
    "mem": 44.45,
    "cpu": 0.9999999776482582,
    "uptime_sec": 332804,
    "net_download": 1293,
    "net_upload": 1267,
    "traffic_users": 462867234697,
    "traffic_node": 2327756258042,
    "users": 7
  },
  {
    "address": "EQBiZHSojM6yzeBqo_Ka06ZauPtuR4nVPs9gqOVFL68BLEi9",
    "is_active": true,
    "node_registry": "EQDbPc6xGV6-nCmDH8bVXUdQCQ1tXMM062Xah-63HAMAkpq8",
    "owner": "EQA0ltvrkBHmBa0QSTNHcZSUNIvha1F6hTwCCMGPbyVPNpTq",
    "total_ratings": 0,
    "rating_count": 0,
    "average_rating": 0,
    "plan": "time",
    "hostname": "us.yastatic.site",
    "country": "US",
    "region": "California",
    "city": "San Jose",
    "ip": "23.106.45.14",
    "exit_ip": null,
    "ssl": true,
    "check_port": 443,
    "api_port": 443,
    "api_path": "/api/v1",
    "public_key": "1e7c0f8cc0a4f9fe2f7cd3d2165e7684feb03ed9427208fb4a5050ecf97608d1",
    "node_id": 228105844814,
    "scanned": "2026-03-19T03:34:05.977386Z",
    "heartbeat": "2026-03-19T03:34:02.139120Z",
    "health_check": "2026-03-19T03:34:08.694631Z",
    "version": "1.1.5",
    "uptime": 99,
    "limit": 100,
    "upload": 0,
    "download": 0,
    "disk": 5.13,
    "mem": 6.1,
    "cpu": 0.0,
    "uptime_sec": 612465,
    "net_download": 10111,
    "net_upload": 13095,
    "traffic_users": 929936696336,
    "traffic_node": 2695476556900,
    "users": 5
  },
  {
    "address": "EQBfzVsVNKkJ7efRh8DJIfUKIeZmUJfreUSW989_ZSZa79cC",
    "is_active": true,
    "node_registry": "EQDbPc6xGV6-nCmDH8bVXUdQCQ1tXMM062Xah-63HAMAkpq8",
    "owner": "EQA0ltvrkBHmBa0QSTNHcZSUNIvha1F6hTwCCMGPbyVPNpTq",
    "total_ratings": 0,
    "rating_count": 0,
    "average_rating": 0,
    "plan": "time",
    "hostname": "www.cdn-vk.run",
    "country": "FI",
    "region": "",
    "city": "Helsinki",
    "ip": "185.88.101.76",
    "exit_ip": null,
    "ssl": true,
    "check_port": 443,
    "api_port": 443,
    "api_path": "/api/v1",
    "public_key": "ddc79716c761d301bc2f31cb4b711eb7137d99d56b5ff27953cc58847c5d92fb",
    "node_id": 1848878100876,
    "scanned": "2026-03-19T03:34:05.418013Z",
    "heartbeat": "2026-03-19T03:34:13.052309Z",
    "health_check": "2026-03-19T03:34:09.167511Z",
    "version": "1.1.5",
    "uptime": 100,
    "limit": 100,
    "upload": 190,
    "download": 202,
    "disk": 62.16,
    "mem": 58.29,
    "cpu": 31.68316830724548,
    "uptime_sec": 308178,
    "net_download": 4637401,
    "net_upload": 3985590,
    "traffic_users": 5140768095992,
    "traffic_node": 11785469538686,
    "users": 17
  },
  {
    "address": "EQBfM5S7Wnn6MMGMoLnmBK-LXWtLc2q1z7ippDR_ZrSEeBCd",
    "is_active": true,
    "node_registry": "EQDbPc6xGV6-nCmDH8bVXUdQCQ1tXMM062Xah-63HAMAkpq8",
    "owner": "EQA0ltvrkBHmBa0QSTNHcZSUNIvha1F6hTwCCMGPbyVPNpTq",
    "total_ratings": 0,
    "rating_count": 0,
    "average_rating": 0,
    "plan": "time",
    "hostname": "k2.cdn-vk.run",
    "country": "RU",
    "region": "Kuzbass",
    "city": "Kemerovo",
    "ip": "77.110.112.98",
    "exit_ip": null,
    "ssl": true,
    "check_port": 443,
    "api_port": 443,
    "api_path": "/api/v1",
    "public_key": "0aad45e26613921a6122a8a83b2f1ce8209aa4ca9bcda8b2eaba1e351f1e05b9",
    "node_id": 7681098111898,
    "scanned": "2026-03-19T03:34:04.797843Z",
    "heartbeat": "2026-03-19T03:33:57.173156Z",
    "health_check": "2026-03-19T03:34:09.049566Z",
    "version": "1.1.6",
    "uptime": 99,
    "limit": 100,
    "upload": 0,
    "download": 0,
    "disk": 68.91,
    "mem": 38.35,
    "cpu": 1.0000000002037268,
    "uptime_sec": 25668,
    "net_download": 87084,
    "net_upload": 83590,
    "traffic_users": 82292252884,
    "traffic_node": 494062001206,
    "users": 1
  },
  {
    "address": "EQBRv1vDYL0fkotme954A8JLv9CxR6nfZYH6V6jHGsl_6szf",
    "is_active": true,
    "node_registry": "EQDbPc6xGV6-nCmDH8bVXUdQCQ1tXMM062Xah-63HAMAkpq8",
    "owner": "EQA0ltvrkBHmBa0QSTNHcZSUNIvha1F6hTwCCMGPbyVPNpTq",
    "total_ratings": 0,
    "rating_count": 0,
    "average_rating": 0,
    "plan": "time",
    "hostname": "spbnl.cdn-vk.run",
    "country": "RU",
    "region": "St.-Petersburg",
    "city": "Saint Petersburg",
    "ip": "213.178.155.199",
    "exit_ip": null,
    "ssl": true,
    "check_port": 443,
    "api_port": 443,
    "api_path": "/api/v1",
    "public_key": "3b89f7cf27240c1d39ef37acff8f8ac238025e8704e29ac9d4d9418639185dc5",
    "node_id": 212817781548199,
    "scanned": "2026-03-19T03:34:04.340306Z",
    "heartbeat": "2026-03-19T03:33:39.649903Z",
    "health_check": "2026-03-19T03:34:08.527831Z",
    "version": "1.1.6",
    "uptime": 100,
    "limit": 100,
    "upload": 0,
    "download": 0,
    "disk": 67.71,
    "mem": 55.3,
    "cpu": 0.0,
    "uptime_sec": 327987,
    "net_download": 48370,
    "net_upload": 34101,
    "traffic_users": 658126736909,
    "traffic_node": 3178005734940,
    "users": 2
  },
  {
    "address": "EQBRE7je8hKmRKgp4HE8byhLtpgoJNwucGHowaAwYrD5F_JK",
    "is_active": true,
    "node_registry": "EQDbPc6xGV6-nCmDH8bVXUdQCQ1tXMM062Xah-63HAMAkpq8",
    "owner": "EQA0ltvrkBHmBa0QSTNHcZSUNIvha1F6hTwCCMGPbyVPNpTq",
    "total_ratings": 0,
    "rating_count": 0,
    "average_rating": 0,
    "plan": "time",
    "hostname": "fin.cdn-vk.run",
    "country": "FI",
    "region": "",
    "city": "Helsinki",
    "ip": "31.56.204.94",
    "exit_ip": null,
    "ssl": true,
    "check_port": 443,
    "api_port": 443,
    "api_path": "/api/v1",
    "public_key": "0855ae5dea20161157948dc171d01ca5f616ec092a4d98bebeedce388e16ba99",
    "node_id": 308558203894,
    "scanned": "2026-03-19T03:34:04.005015Z",
    "heartbeat": "2026-03-19T03:33:44.431674Z",
    "health_check": "2026-03-19T03:34:07.689655Z",
    "version": "1.1.5",
    "uptime": 99,
    "limit": 100,
    "upload": 0,
    "download": 0,
    "disk": 29.07,
    "mem": 33.1,
    "cpu": 43.68932038829465,
    "uptime_sec": 608430,
    "net_download": 525584,
    "net_upload": 495830,
    "traffic_users": 2923421554246,
    "traffic_node": 7475689401410,
    "users": 25
  },
  {
    "address": "EQBPyeO6ABxp0FBN8E7GhUdQWPxHO2JElGqwQVq6fHXK6iGu",
    "is_active": true,
    "node_registry": "EQDbPc6xGV6-nCmDH8bVXUdQCQ1tXMM062Xah-63HAMAkpq8",
    "owner": "EQA0ltvrkBHmBa0QSTNHcZSUNIvha1F6hTwCCMGPbyVPNpTq",
    "total_ratings": 0,
    "rating_count": 0,
    "average_rating": 0,
    "plan": "time",
    "hostname": "ro.yastatic.run",
    "country": "RO",
    "region": "Bucure\u0219ti",
    "city": "Bucharest",
    "ip": "45.66.160.2",
    "exit_ip": null,
    "ssl": true,
    "check_port": 443,
    "api_port": 443,
    "api_path": "/api/v1",
    "public_key": "a8db0baa4e8ab32e1aaee052fa00fad8a7351cfd6412b59dc8977939a4188565",
    "node_id": 44865815982,
    "scanned": "2026-03-19T03:34:03.776013Z",
    "heartbeat": "2026-03-19T03:34:02.938056Z",
    "health_check": "2026-03-19T03:34:07.660164Z",
    "version": "1.1.5",
    "uptime": 97,
    "limit": 100,
    "upload": 0,
    "download": 0,
    "disk": 20.89,
    "mem": 60.62,
    "cpu": 18.137254902373396,
    "uptime_sec": 32795,
    "net_download": 398642,
    "net_upload": 180383,
    "traffic_users": 5590592325499,
    "traffic_node": 14501377938895,
    "users": 40
  },
  {
    "address": "EQBJKbZTB3OzuAPeolc49ERDF4Drv_w5_MUI2ANJa2AJNI7H",
    "is_active": true,
    "node_registry": "EQDbPc6xGV6-nCmDH8bVXUdQCQ1tXMM062Xah-63HAMAkpq8",
    "owner": "EQA0ltvrkBHmBa0QSTNHcZSUNIvha1F6hTwCCMGPbyVPNpTq",
    "total_ratings": 0,
    "rating_count": 0,
    "average_rating": 0,
    "plan": "time",
    "hostname": "cdn.edge-apple.online",
    "country": "DE",
    "region": "State of Berlin",
    "city": "Berlin",
    "ip": "45.15.129.41",
    "exit_ip": null,
    "ssl": true,
    "check_port": 443,
    "api_port": 443,
    "api_path": "/api/v1",
    "public_key": "4cefaf69d789192f4cc2c1546cdcde5890233c26ded70748922d4e895f419923",
    "node_id": 448148128841,
    "scanned": "2026-03-19T03:34:03.694725Z",
    "heartbeat": "2026-03-19T03:33:46.792432Z",
    "health_check": "2026-03-19T03:34:07.281093Z",
    "version": "1.1.6",
    "uptime": 96,
    "limit": 100,
    "upload": 0,
    "download": 0,
    "disk": 17.06,
    "mem": 63.66,
    "cpu": 15.094339625749786,
    "uptime_sec": 38131,
    "net_download": 1337658,
    "net_upload": 1356572,
    "traffic_users": 853456904623,
    "traffic_node": 2160963412498,
    "users": 26
  },
  {
    "address": "EQBI4cSVPL6Bp5SyYL1vjEKuQFETRo3ewcXInmHke7qiYuKE",
    "is_active": true,
    "node_registry": "EQDbPc6xGV6-nCmDH8bVXUdQCQ1tXMM062Xah-63HAMAkpq8",
    "owner": "EQA0ltvrkBHmBa0QSTNHcZSUNIvha1F6hTwCCMGPbyVPNpTq",
    "total_ratings": 0,
    "rating_count": 0,
    "average_rating": 0,
    "plan": "time",
    "hostname": "nl.yastatic.run",
    "country": "NL",
    "region": "Flevoland",
    "city": "Dronten",
    "ip": "195.93.244.178",
    "exit_ip": null,
    "ssl": true,
    "check_port": 443,
    "api_port": 443,
    "api_path": "/api/v1",
    "public_key": "3aa0235784fa2be34e5e6517273b8a07f519bb9320e2534533044a78e5d1c19f",
    "node_id": 19489282438178,
    "scanned": "2026-03-19T03:34:03.585939Z",
    "heartbeat": "2026-03-19T03:33:44.902641Z",
    "health_check": "2026-03-19T03:34:08.004300Z",
    "version": "1.1.5",
    "uptime": 99,
    "limit": 100,
    "upload": 0,
    "download": 0,
    "disk": 57.35,
    "mem": 59.29,
    "cpu": 14.893617021803601,
    "uptime_sec": 206598,
    "net_download": 1332042,
    "net_upload": 1429174,
    "traffic_users": 1922208343465,
    "traffic_node": 4930010297710,
    "users": 16
  },
  {
    "address": "EQBBk3gSSbfMR0ZiQVdVSqIucBhUeE9l1USNX6UEDyDImA9V",
    "is_active": true,
    "node_registry": "EQDbPc6xGV6-nCmDH8bVXUdQCQ1tXMM062Xah-63HAMAkpq8",
    "owner": "EQA0ltvrkBHmBa0QSTNHcZSUNIvha1F6hTwCCMGPbyVPNpTq",
    "total_ratings": 0,
    "rating_count": 0,
    "average_rating": 0,
    "plan": "time",
    "hostname": "pl.yastatic.site",
    "country": "PL",
    "region": "Mazovia",
    "city": "Warsaw",
    "ip": "151.241.227.114",
    "exit_ip": null,
    "ssl": true,
    "check_port": 443,
    "api_port": 443,
    "api_path": "/api/v1",
    "public_key": "c33e88777b6ceffe7000af5b96f14048a2162ba86b6e5c32abbac013ced821a1",
    "node_id": 150824082268114,
    "scanned": "2026-03-19T03:34:03.135661Z",
    "heartbeat": "2026-03-19T03:34:22.977403Z",
    "health_check": "2026-03-19T03:34:08.043790Z",
    "version": "1.1.6",
    "uptime": 100,
    "limit": 100,
    "upload": 64,
    "download": 545,
    "disk": 34.04,
    "mem": 60.72,
    "cpu": 21.87499999696835,
    "uptime_sec": 310758,
    "net_download": 790553,
    "net_upload": 480450,
    "traffic_users": 4292556707846,
    "traffic_node": 10875159811373,
    "users": 15
  },
  {
    "address": "EQB87hKLgRlHqR38TG_SS6kP1E3WatBsHcf0i1XBExhfTaSW",
    "is_active": true,
    "node_registry": "EQDbPc6xGV6-nCmDH8bVXUdQCQ1tXMM062Xah-63HAMAkpq8",
    "owner": "EQA0ltvrkBHmBa0QSTNHcZSUNIvha1F6hTwCCMGPbyVPNpTq",
    "total_ratings": 0,
    "rating_count": 0,
    "average_rating": 0,
    "plan": "time",
    "hostname": "cy.cdn-vk.rest",
    "country": "CY",
    "region": "Lefkosia",
    "city": "Nicosia",
    "ip": "194.76.154.24",
    "exit_ip": null,
    "ssl": true,
    "check_port": 443,
    "api_port": 443,
    "api_path": "/api/v1",
    "public_key": "46e7ae332d9b72582d2bb42b5c61ff3e2b6f9386e15fd4b04b2c90615780da0a",
    "node_id": 1938758153824,
    "scanned": "2026-03-19T03:34:03.013000Z",
    "heartbeat": "2026-03-19T03:33:31.163191Z",
    "health_check": "2026-03-19T03:34:08.234478Z",
    "version": "1.1.5",
    "uptime": 97,
    "limit": 100,
    "upload": 0,
    "download": 0,
    "disk": 17.31,
    "mem": 58.54,
    "cpu": 12.37113400997798,
    "uptime_sec": 611791,
    "net_download": 4986471,
    "net_upload": 5051226,
    "traffic_users": 1454470455002,
    "traffic_node": 4036410237163,
    "users": 25
  },
  {
    "address": "EQB6zQMIpcm4ONWHyhh_7XxZS9DlsODavLxwT2H0wYXlD6CP",
    "is_active": true,
    "node_registry": "EQDbPc6xGV6-nCmDH8bVXUdQCQ1tXMM062Xah-63HAMAkpq8",
    "owner": "EQA0ltvrkBHmBa0QSTNHcZSUNIvha1F6hTwCCMGPbyVPNpTq",
    "total_ratings": 0,
    "rating_count": 0,
    "average_rating": 0,
    "plan": "time",
    "hostname": "kr.yastatic.run",
    "country": "RU",
    "region": "Krasnodar Krai",
    "city": "Krasnodar",
    "ip": "193.124.121.96",
    "exit_ip": null,
    "ssl": true,
    "check_port": 443,
    "api_port": 443,
    "api_path": "/api/v1",
    "public_key": "a8cefb8309764313673d8868179c49dbdb1e03252a7a876968abf2b4ea047a0a",
    "node_id": 19281238120896,
    "scanned": "2026-03-19T03:34:02.547300Z",
    "heartbeat": "2026-03-19T03:34:25.203993Z",
    "health_check": "2026-03-19T03:34:08.910811Z",
    "version": "1.1.6",
    "uptime": 100,
    "limit": 100,
    "upload": 0,
    "download": 0,
    "disk": 42.84,
    "mem": 62.32,
    "cpu": 3.9603960430276044,
    "uptime_sec": 340912,
    "net_download": 130816,
    "net_upload": 128010,
    "traffic_users": 264822499413,
    "traffic_node": 1291970826981,
    "users": 8
  },
  {
    "address": "EQB5Xy4t1Ntsecb6CSgGByWfqYnPn6cqN16R1tSVgrdQgu5e",
    "is_active": true,
    "node_registry": "EQDbPc6xGV6-nCmDH8bVXUdQCQ1tXMM062Xah-63HAMAkpq8",
    "owner": "EQA0ltvrkBHmBa0QSTNHcZSUNIvha1F6hTwCCMGPbyVPNpTq",
    "total_ratings": 0,
    "rating_count": 0,
    "average_rating": 0,
    "plan": "time",
    "hostname": "ru.yastatic.run",
    "country": "RU",
    "region": "Moscow Oblast",
    "city": "Korolev",
    "ip": "195.133.146.211",
    "exit_ip": null,
    "ssl": true,
    "check_port": 443,
    "api_port": 443,
    "api_path": "/api/v1",
    "public_key": "1d6c45e833ca03cf9765c4f98380d96e9d4812822a25e366b2c437a870715d26",
    "node_id": 194813281458211,
    "scanned": "2026-03-19T03:34:01.399969Z",
    "heartbeat": "2026-03-19T03:33:52.210758Z",
    "health_check": "2026-03-19T03:34:08.894821Z",
    "version": "1.1.6",
    "uptime": 98,
    "limit": 100,
    "upload": 0,
    "download": 0,
    "disk": 43.96,
    "mem": 62.15,
    "cpu": 3.9603960485624965,
    "uptime_sec": 21287,
    "net_download": 37575,
    "net_upload": 38554,
    "traffic_users": 386147942650,
    "traffic_node": 2078374315648,
    "users": 10
  },
  {
    "address": "EQB1MZdNK7EazQA5daPCcxtvE44FxQOO9hSlSIg0CMfq6WIW",
    "is_active": true,
    "node_registry": "EQDbPc6xGV6-nCmDH8bVXUdQCQ1tXMM062Xah-63HAMAkpq8",
    "owner": "EQA0ltvrkBHmBa0QSTNHcZSUNIvha1F6hTwCCMGPbyVPNpTq",
    "total_ratings": 0,
    "rating_count": 0,
    "average_rating": 0,
    "plan": "time",
    "hostname": "it.cdn-vk.run",
    "country": "RU",
    "region": "Moscow",
    "city": "Moscow",
    "ip": "213.226.112.65",
    "exit_ip": null,
    "ssl": true,
    "check_port": 443,
    "api_port": 443,
    "api_path": "/api/v1",
    "public_key": "bcb46722f795e38503620dd4f470c29a24b66931ceae4d3abc72c4e210a0c7df",
    "node_id": 21282258111865,
    "scanned": "2026-03-19T03:34:00.833943Z",
    "heartbeat": "2026-03-19T03:33:26.861555Z",
    "health_check": "2026-03-19T03:34:08.512855Z",
    "version": "1.1.6",
    "uptime": 100,
    "limit": 100,
    "upload": 0,
    "download": 0,
    "disk": 64.08,
    "mem": 51.5,
    "cpu": 0.0,
    "uptime_sec": 322460,
    "net_download": 135954,
    "net_upload": 177319,
    "traffic_users": 364787087581,
    "traffic_node": 1929545899236,
    "users": 3
  },
  {
    "address": "EQAn7n9YreZRYLTUcPNHI3hIZU8QuQaVhi5q7IYGHOc9r_V2",
    "is_active": true,
    "node_registry": "EQDbPc6xGV6-nCmDH8bVXUdQCQ1tXMM062Xah-63HAMAkpq8",
    "owner": "EQA0ltvrkBHmBa0QSTNHcZSUNIvha1F6hTwCCMGPbyVPNpTq",
    "total_ratings": 0,
    "rating_count": 0,
    "average_rating": 0,
    "plan": "time",
    "hostname": "se.relay-apple.online",
    "country": "SE",
    "region": "Stockholm",
    "city": "Stockholm",
    "ip": "138.124.84.49",
    "exit_ip": null,
    "ssl": true,
    "check_port": 443,
    "api_port": 443,
    "api_path": "/api/v1",
    "public_key": "d75a8a6f44f47a99e304d7f878cc94a5fd12b14456d22f18ec427353ec323b34",
    "node_id": 1378123883849,
    "scanned": "2026-03-19T03:34:00.610892Z",
    "heartbeat": "2026-03-19T03:33:33.763050Z",
    "health_check": "2026-03-19T03:34:08.653887Z",
    "version": "1.1.6",
    "uptime": 99,
    "limit": 100,
    "upload": 0,
    "download": 0,
    "disk": 52.47,
    "mem": 56.33,
    "cpu": 8.000000001629815,
    "uptime_sec": 38417,
    "net_download": 759484,
    "net_upload": 772602,
    "traffic_users": 962468676030,
    "traffic_node": 2636682729321,
    "users": 17
  },
  {
    "address": "EQAlr2DsKzSMsO-ADlPqJVOv5GRGb0iKw0nWKpBnym4sz-hS",
    "is_active": true,
    "node_registry": "EQDbPc6xGV6-nCmDH8bVXUdQCQ1tXMM062Xah-63HAMAkpq8",
    "owner": "EQA0ltvrkBHmBa0QSTNHcZSUNIvha1F6hTwCCMGPbyVPNpTq",
    "total_ratings": 0,
    "rating_count": 0,
    "average_rating": 0,
    "plan": "time",
    "hostname": "ee.edge-apple.online",
    "country": "EE",
    "region": "Harjumaa",
    "city": "Tallinn",
    "ip": "23.230.179.233",
    "exit_ip": null,
    "ssl": true,
    "check_port": 443,
    "api_port": 443,
    "api_path": "/api/v1",
    "public_key": "6fb38fe7144ce1efc7086c54769db78be42ab0e5d301065f1c81148c65218159",
    "node_id": 22822981788233,
    "scanned": "2026-03-19T03:34:00.381627Z",
    "heartbeat": "2026-03-19T03:33:59.687266Z",
    "health_check": "2026-03-19T03:34:07.424712Z",
    "version": "1.1.6",
    "uptime": 99,
    "limit": 100,
    "upload": 0,
    "download": 0,
    "disk": 52.7,
    "mem": 61.63,
    "cpu": 14.14141414148838,
    "uptime_sec": 30271,
    "net_download": 576708,
    "net_upload": 590540,
    "traffic_users": 1086306485508,
    "traffic_node": 2795126199671,
    "users": 22
  },
  {
    "address": "EQAklR_7ov3Sz7VSYMFs-_83JylG3pdxM1OQAeayohAeuYmy",
    "is_active": true,
    "node_registry": "EQDbPc6xGV6-nCmDH8bVXUdQCQ1tXMM062Xah-63HAMAkpq8",
    "owner": "EQA0ltvrkBHmBa0QSTNHcZSUNIvha1F6hTwCCMGPbyVPNpTq",
    "total_ratings": 0,
    "rating_count": 0,
    "average_rating": 0,
    "plan": "time",
    "hostname": "cloud.cdn-vk.run",
    "country": "RU",
    "region": "Moscow Oblast",
    "city": "Korolev",
    "ip": "195.133.146.74",
    "exit_ip": null,
    "ssl": true,
    "check_port": 443,
    "api_port": 443,
    "api_path": "/api/v1",
    "public_key": "d8e3b8704806ce095628fbf133cbfc37b57b45dad1bc238bb93368dd107d3ce0",
    "node_id": 19481328145874,
    "scanned": "2026-03-19T03:33:59.870927Z",
    "heartbeat": "2026-03-19T03:33:52.466293Z",
    "health_check": "2026-03-19T03:34:07.970150Z",
    "version": "1.1.6",
    "uptime": 100,
    "limit": 100,
    "upload": 0,
    "download": 0,
    "disk": 60.68,
    "mem": 58.65,
    "cpu": 3.0303029647370088,
    "uptime_sec": 331823,
    "net_download": 35313842,
    "net_upload": 34886976,
    "traffic_users": 2613152378156,
    "traffic_node": 12859214036310,
    "users": 7
  },
  {
    "address": "EQAiqQCtVfHR1u8FpXMrb_BP5K9W7d8uZhEPGmwG9qd5fEAo",
    "is_active": true,
    "node_registry": "EQDbPc6xGV6-nCmDH8bVXUdQCQ1tXMM062Xah-63HAMAkpq8",
    "owner": "EQA0ltvrkBHmBa0QSTNHcZSUNIvha1F6hTwCCMGPbyVPNpTq",
    "total_ratings": 0,
    "rating_count": 0,
    "average_rating": 0,
    "plan": "time",
    "hostname": "ek.cdn-vk.run",
    "country": "RU",
    "region": "Sverdlovsk Oblast",
    "city": "Yekaterinburg",
    "ip": "45.11.27.93",
    "exit_ip": null,
    "ssl": true,
    "check_port": 443,
    "api_port": 443,
    "api_path": "/api/v1",
    "public_key": "28a814326caec0cea681de85b4ade2a2ac99322ed99f5d171f8023f17916c20b",
    "node_id": 44810826893,
    "scanned": "2026-03-19T03:33:59.357165Z",
    "heartbeat": "2026-03-19T03:33:49.073653Z",
    "health_check": "2026-03-19T03:34:09.178642Z",
    "version": "1.1.6",
    "uptime": 99,
    "limit": 100,
    "upload": 0,
    "download": 0,
    "disk": 44.83,
    "mem": 68.17,
    "cpu": 22.8571428552422,
    "uptime_sec": 14509,
    "net_download": 7822017,
    "net_upload": 7742318,
    "traffic_users": 301024622543,
    "traffic_node": 1499206821266,
    "users": 19
  },
  {
    "address": "EQAhzt3V7Ng5LZyQdx8LKs3ei5W2yKU5mNlEzOw5KN4PlGt7",
    "is_active": true,
    "node_registry": "EQDbPc6xGV6-nCmDH8bVXUdQCQ1tXMM062Xah-63HAMAkpq8",
    "owner": "EQA0ltvrkBHmBa0QSTNHcZSUNIvha1F6hTwCCMGPbyVPNpTq",
    "total_ratings": 0,
    "rating_count": 0,
    "average_rating": 0,
    "plan": "time",
    "hostname": "ca.yastatic.site",
    "country": "CA",
    "region": "Quebec",
    "city": "Montreal",
    "ip": "184.107.179.25",
    "exit_ip": null,
    "ssl": true,
    "check_port": 443,
    "api_port": 443,
    "api_path": "/api/v1",
    "public_key": "b01d259434de07393001ffd7d1b67e3181e191b29eb339f3dea5d660c0e8105b",
    "node_id": 18381068178825,
    "scanned": "2026-03-19T03:33:58.660874Z",
    "heartbeat": "2026-03-19T03:33:41.534372Z",
    "health_check": "2026-03-19T03:34:08.839383Z",
    "version": "1.1.5",
    "uptime": 99,
    "limit": 100,
    "upload": 0,
    "download": 0,
    "disk": 5.16,
    "mem": 5.81,
    "cpu": 0.7481296591301733,
    "uptime_sec": 612444,
    "net_download": 36199,
    "net_upload": 44841,
    "traffic_users": 318228729452,
    "traffic_node": 1381465025935,
    "users": 5
  },
  {
    "address": "EQAfwxqts_LkQ-sz-yHPHgZ2hOGIvUUmA9o28M53aaq0Yq54",
    "is_active": true,
    "node_registry": "EQDbPc6xGV6-nCmDH8bVXUdQCQ1tXMM062Xah-63HAMAkpq8",
    "owner": "EQA0ltvrkBHmBa0QSTNHcZSUNIvha1F6hTwCCMGPbyVPNpTq",
    "total_ratings": 0,
    "rating_count": 0,
    "average_rating": 0,
    "plan": "time",
    "hostname": "get.yastatic.site",
    "country": "TH",
    "region": "Krung Thep Maha Nakhon",
    "city": "Bangkok",
    "ip": "165.101.64.91",
    "exit_ip": null,
    "ssl": true,
    "check_port": 443,
    "api_port": 443,
    "api_path": "/api/v1",
    "public_key": "95a655617b2552968eca587046418cd883dc8bad43658d333c8cb5de7b31d324",
    "node_id": 1648100863891,
    "scanned": "2026-03-19T03:33:57.277436Z",
    "heartbeat": "2026-03-19T03:34:14.544516Z",
    "health_check": "2026-03-19T03:34:10.205859Z",
    "version": "1.1.5",
    "uptime": 78,
    "limit": 100,
    "upload": 239,
    "download": 672,
    "disk": 57.0,
    "mem": 39.5,
    "cpu": 2.040816375016794,
    "uptime_sec": 614290,
    "net_download": 295592,
    "net_upload": 295090,
    "traffic_users": 497095394130,
    "traffic_node": 1411550755942,
    "users": 1
  },
  {
    "address": "EQAZdBrzhtrQfAdMdIg1fXUef8j0SSf7oWlcJeAKw1jSxKts",
    "is_active": true,
    "node_registry": "EQDbPc6xGV6-nCmDH8bVXUdQCQ1tXMM062Xah-63HAMAkpq8",
    "owner": "EQA0ltvrkBHmBa0QSTNHcZSUNIvha1F6hTwCCMGPbyVPNpTq",
    "total_ratings": 0,
    "rating_count": 0,
    "average_rating": 0,
    "plan": "time",
    "hostname": "jp.yastatic.site",
    "country": "JP",
    "region": "Tokyo",
    "city": "Shinjuku",
    "ip": "142.91.109.126",
    "exit_ip": null,
    "ssl": true,
    "check_port": 443,
    "api_port": 443,
    "api_path": "/api/v1",
    "public_key": "abe7507075772510ce0abefeac25cae4401401c6a8512f6fad72dfbfe8fe3707",
    "node_id": 14189081088126,
    "scanned": "2026-03-19T03:33:55.637225Z",
    "heartbeat": "2026-03-19T03:34:12.443037Z",
    "health_check": "2026-03-19T03:34:09.375721Z",
    "version": "1.1.5",
    "uptime": 99,
    "limit": 100,
    "upload": 0,
    "download": 0,
    "disk": 5.12,
    "mem": 5.17,
    "cpu": 0.0,
    "uptime_sec": 617326,
    "net_download": 10123,
    "net_upload": 13188,
    "traffic_users": 240159373870,
    "traffic_node": 1063846288629,
    "users": 0
  },
  {
    "address": "EQAWdcYsjSA8ZEM1FhvFocz0NNEX_4O3yqiaS7p2oPAi0j4q",
    "is_active": true,
    "node_registry": "EQDbPc6xGV6-nCmDH8bVXUdQCQ1tXMM062Xah-63HAMAkpq8",
    "owner": "EQA0ltvrkBHmBa0QSTNHcZSUNIvha1F6hTwCCMGPbyVPNpTq",
    "total_ratings": 0,
    "rating_count": 0,
    "average_rating": 0,
    "plan": "time",
    "hostname": "eu.yastatic.run",
    "country": "NL",
    "region": "Flevoland",
    "city": "Dronten",
    "ip": "212.87.223.232",
    "exit_ip": null,
    "ssl": true,
    "check_port": 443,
    "api_port": 443,
    "api_path": "/api/v1",
    "public_key": "452814d87e05f130d11c100a328a7ae08db3beb61d0993bdf8c7311a1bc43397",
    "node_id": 21188682228232,
    "scanned": "2026-03-19T03:33:55.510304Z",
    "heartbeat": "2026-03-19T03:33:18.485535Z",
    "health_check": "2026-03-19T03:34:07.202491Z",
    "version": "1.1.5",
    "uptime": 99,
    "limit": 100,
    "upload": 0,
    "download": 0,
    "disk": 59.55,
    "mem": 56.76,
    "cpu": 23.000000016065314,
    "uptime_sec": 611778,
    "net_download": 2035642,
    "net_upload": 2102847,
    "traffic_users": 1642402074320,
    "traffic_node": 4280257525835,
    "users": 14
  },
  {
    "address": "EQALo8Rmy6nva0quulLFQzZDKo_SYIrmotQkAtbJWpu8kJVv",
    "is_active": true,
    "node_registry": "EQDbPc6xGV6-nCmDH8bVXUdQCQ1tXMM062Xah-63HAMAkpq8",
    "owner": "EQA0ltvrkBHmBa0QSTNHcZSUNIvha1F6hTwCCMGPbyVPNpTq",
    "total_ratings": 0,
    "rating_count": 0,
    "average_rating": 0,
    "plan": "time",
    "hostname": "m9.cdn-vk.run",
    "country": "RU",
    "region": "Moscow",
    "city": "Moscow",
    "ip": "194.87.207.232",
    "exit_ip": null,
    "ssl": true,
    "check_port": 443,
    "api_port": 443,
    "api_path": "/api/v1",
    "public_key": "ed9dc4e1207d42e75c379d987a3968a747f38f951754aa7d09472e56de837f1a",
    "node_id": 19388682068232,
    "scanned": "2026-03-19T03:33:55.001152Z",
    "heartbeat": "2026-03-19T03:34:19.928538Z",
    "health_check": "2026-03-19T03:34:08.675789Z",
    "version": "1.1.6",
    "uptime": 100,
    "limit": 100,
    "upload": 0,
    "download": 0,
    "disk": 68.54,
    "mem": 65.87,
    "cpu": 23.07692309758852,
    "uptime_sec": 330113,
    "net_download": 2304144,
    "net_upload": 2739586,
    "traffic_users": 623492484593,
    "traffic_node": 2972512654210,
    "users": 2
  },
  {
    "address": "EQAAcXmsodmvyT2e8nMcSjKWAXEEuJDkktkm-9ZMtIy0E7E1",
    "is_active": true,
    "node_registry": "EQDbPc6xGV6-nCmDH8bVXUdQCQ1tXMM062Xah-63HAMAkpq8",
    "owner": "EQA0ltvrkBHmBa0QSTNHcZSUNIvha1F6hTwCCMGPbyVPNpTq",
    "total_ratings": 0,
    "rating_count": 0,
    "average_rating": 0,
    "plan": "time",
    "hostname": "nova.cdn-vk.rest",
    "country": "RU",
    "region": "Novosibirskaya oblast'",
    "city": "Novosibirsk",
    "ip": "193.233.49.42",
    "exit_ip": null,
    "ssl": true,
    "check_port": 443,
    "api_port": 443,
    "api_path": "/api/v1",
    "public_key": "a94dc7165eff460ce70317691314364b9fc718f5c17df9bcb091937697c3156a",
    "node_id": 1928232848842,
    "scanned": "2026-03-19T03:33:54.382192Z",
    "heartbeat": "2026-03-19T03:34:09.884232Z",
    "health_check": "2026-03-19T03:34:07.988003Z",
    "version": "1.1.6",
    "uptime": 99,
    "limit": 100,
    "upload": 0,
    "download": 0,
    "disk": 45.22,
    "mem": 19.34,
    "cpu": 3.030303033153727,
    "uptime_sec": 12506,
    "net_download": 22500,
    "net_upload": 19637,
    "traffic_users": 334931588803,
    "traffic_node": 1115600503008,
    "users": 5
  },
  {
    "address": "EQA7s3Php7TJS__Y71xns5QSEqt54rtuMC9_Tg50eN4AUFnd",
    "is_active": true,
    "node_registry": "EQDbPc6xGV6-nCmDH8bVXUdQCQ1tXMM062Xah-63HAMAkpq8",
    "owner": "EQA0ltvrkBHmBa0QSTNHcZSUNIvha1F6hTwCCMGPbyVPNpTq",
    "total_ratings": 0,
    "rating_count": 0,
    "average_rating": 0,
    "plan": "time",
    "hostname": "eu.cdn-vk.run",
    "country": "FR",
    "region": "Grand-Est",
    "city": "Lauterbourg",
    "ip": "62.169.29.73",
    "exit_ip": null,
    "ssl": true,
    "check_port": 443,
    "api_port": 443,
    "api_path": "/api/v1",
    "public_key": "c7f6b5ef5cc09c29c1befeeeccb4db052a5234a595286584d416ddee69a850b3",
    "node_id": 618168828873,
    "scanned": "2026-03-19T03:33:54.207080Z",
    "heartbeat": "2026-03-19T03:33:48.073399Z",
    "health_check": "2026-03-19T03:34:08.171016Z",
    "version": "1.1.5",
    "uptime": 99,
    "limit": 100,
    "upload": 0,
    "download": 0,
    "disk": 7.02,
    "mem": 5.43,
    "cpu": 2.0565552720154487,
    "uptime_sec": 612452,
    "net_download": 41360,
    "net_upload": 57891,
    "traffic_users": 125494880591,
    "traffic_node": 660073856725,
    "users": 4
  },
  {
    "address": "EQA-YJB0ILq3Te7Ss9MZW9eKPvVeoPrHAYBOtkQWNuV7q_ae",
    "is_active": true,
    "node_registry": "EQDbPc6xGV6-nCmDH8bVXUdQCQ1tXMM062Xah-63HAMAkpq8",
    "owner": "EQA0ltvrkBHmBa0QSTNHcZSUNIvha1F6hTwCCMGPbyVPNpTq",
    "total_ratings": 0,
    "rating_count": 0,
    "average_rating": 0,
    "plan": "time",
    "hostname": "sg.yastatic.site",
    "country": "SG",
    "region": "Central Singapore",
    "city": "Singapore",
    "ip": "23.111.14.225",
    "exit_ip": null,
    "ssl": true,
    "check_port": 443,
    "api_port": 443,
    "api_path": "/api/v1",
    "public_key": "234e1731051886541b26642f19afb1d7c78fe6ec0a421076c73177df1a971d41",
    "node_id": 2281108138225,
    "scanned": "2026-03-19T03:33:53.048442Z",
    "heartbeat": "2026-03-19T03:34:10.991812Z",
    "health_check": "2026-03-19T03:34:09.033826Z",
    "version": "1.1.5",
    "uptime": 99,
    "limit": 100,
    "upload": 0,
    "download": 0,
    "disk": 5.19,
    "mem": 7.68,
    "cpu": 2.255639093883375,
    "uptime_sec": 613288,
    "net_download": 733311,
    "net_upload": 720427,
    "traffic_users": 1117672464360,
    "traffic_node": 3811146622285,
    "users": 6
  }
]