[
  {
    "address": "EQDvonw3GaGFdLleBu0YN34w2ujKgXVm7I9m5Bsfq_V3pb4b",
    "is_active": true,
    "node_registry": "EQDbPc6xGV6-nCmDH8bVXUdQCQ1tXMM062Xah-63HAMAkpq8",
    "owner": "EQA0ltvrkBHmBa0QSTNHcZSUNIvha1F6hTwCCMGPbyVPNpTq",
    "tickets_total": 32142,
    "tickets_30d": 3259,
    "ratings_total": 0,
    "ratings_30d": 0,
    "ratings_avg_stars": 0.0,
    "ratings_avg_stars_30d": 0.0,
    "plan": "time",
    "hostname": "kr.cdn-vk.run",
    "country": "RU",
    "region": "Krasnodar Krai",
    "city": "Krasnodar",
    "ip": "193.124.121.148",
    "exit_ip": null,
    "ssl": true,
    "check_port": 443,
    "api_port": 443,
    "api_path": "/api/v1",
    "public_key": "3ca2d63b23ffc90f1092bde5a943a8b289591ce1733aa4e789f5a5189ce776b1",
    "node_id": 192812381208148,
    "scanned": "2026-06-27T21:58:44.425536Z",
    "heartbeat": "2026-06-27T21:58:16.791337Z",
    "health_check": "2026-06-27T21:54:07.943989Z",
    "version": "1.2.7",
    "uptime": 99,
    "limit": 100,
    "upload": 0,
    "download": 0,
    "disk": 46.74,
    "mem": 55.06,
    "cpu": 0.9900990117144518,
    "uptime_sec": 188895,
    "net_download": 184,
    "net_upload": 250,
    "traffic_users": 1035741290811,
    "traffic_node": 5365631017091,
    "users": 0
  },
  {
    "address": "EQDepojw8ACjGgeauVIjNL7pQ73SuVVtslardEoCvSNHLMPq",
    "is_active": true,
    "node_registry": "EQDbPc6xGV6-nCmDH8bVXUdQCQ1tXMM062Xah-63HAMAkpq8",
    "owner": "EQA0ltvrkBHmBa0QSTNHcZSUNIvha1F6hTwCCMGPbyVPNpTq",
    "tickets_total": 5875,
    "tickets_30d": 1811,
    "ratings_total": 0,
    "ratings_30d": 0,
    "ratings_avg_stars": 0.0,
    "ratings_avg_stars_30d": 0.0,
    "plan": "time",
    "hostname": "deq.cdn-vk.run",
    "country": "DE",
    "region": "Hesse",
    "city": "Frankfurt am Main",
    "ip": "5.61.33.36",
    "exit_ip": null,
    "ssl": true,
    "check_port": 443,
    "api_port": 443,
    "api_path": "/api/v1",
    "public_key": "5f36858bfd5886f00da0349bdf367e2be2db9c99ab67d05226570acbe36acd45",
    "node_id": 4860832836,
    "scanned": "2026-06-27T21:58:44.419900Z",
    "heartbeat": "2026-06-27T21:58:03.407099Z",
    "health_check": "2026-06-27T21:54:07.155182Z",
    "version": "1.2.11",
    "uptime": 99,
    "limit": 100,
    "upload": 0,
    "download": 0,
    "disk": 78.86,
    "mem": 21.57,
    "cpu": 0.0,
    "uptime_sec": 3097340,
    "net_download": 369,
    "net_upload": 237,
    "traffic_users": 2840107763806,
    "traffic_node": 6648994046131,
    "users": 1
  },
  {
    "address": "EQDXCtwz_9hGIA0RXVNKUcKhkbSyHk4NyjD779OPHb0k-hz6",
    "is_active": true,
    "node_registry": "EQDbPc6xGV6-nCmDH8bVXUdQCQ1tXMM062Xah-63HAMAkpq8",
    "owner": "EQA0ltvrkBHmBa0QSTNHcZSUNIvha1F6hTwCCMGPbyVPNpTq",
    "tickets_total": 32085,
    "tickets_30d": 10670,
    "ratings_total": 0,
    "ratings_30d": 0,
    "ratings_avg_stars": 0.0,
    "ratings_avg_stars_30d": 0.0,
    "plan": "time",
    "hostname": "it.yastatic.run",
    "country": "RU",
    "region": "Tatarstan Republic",
    "city": "Kazan",
    "ip": "46.17.248.203",
    "exit_ip": null,
    "ssl": true,
    "check_port": 443,
    "api_port": 443,
    "api_path": "/api/v1",
    "public_key": "cd0c609e25326af67bab58bc8b81be2537704f547de1b26082602f43084b5bde",
    "node_id": 4581682478203,
    "scanned": "2026-06-27T21:58:44.413682Z",
    "heartbeat": "2026-06-27T21:58:31.591111Z",
    "health_check": "2026-06-27T21:54:08.274054Z",
    "version": "1.2.7",
    "uptime": 99,
    "limit": 100,
    "upload": 0,
    "download": 0,
    "disk": 46.3,
    "mem": 48.19,
    "cpu": 1.0101010110512423,
    "uptime_sec": 119575,
    "net_download": 13703,
    "net_upload": 11989,
    "traffic_users": 319678605010,
    "traffic_node": 2784918030169,
    "users": 0
  },
  {
    "address": "EQDWxL7KNSTjiFTHLWCXKrhe8INupHYBt6hzXsp1LfZj_qJd",
    "is_active": true,
    "node_registry": "EQDbPc6xGV6-nCmDH8bVXUdQCQ1tXMM062Xah-63HAMAkpq8",
    "owner": "EQA0ltvrkBHmBa0QSTNHcZSUNIvha1F6hTwCCMGPbyVPNpTq",
    "tickets_total": 20928,
    "tickets_30d": 5545,
    "ratings_total": 0,
    "ratings_30d": 0,
    "ratings_avg_stars": 0.0,
    "ratings_avg_stars_30d": 0.0,
    "plan": "time",
    "hostname": "eeq.cdn-vk.run",
    "country": "EE",
    "region": "Harjumaa",
    "city": "Tallinn",
    "ip": "80.79.125.102",
    "exit_ip": null,
    "ssl": true,
    "check_port": 443,
    "api_port": 443,
    "api_path": "/api/v1",
    "public_key": "a84d7251e69d6e7309917de7c3b80f9df04443492c026fc26ed59f8ef9a43e84",
    "node_id": 7987881248102,
    "scanned": "2026-06-27T21:58:44.407095Z",
    "heartbeat": "2026-06-27T21:57:35.720880Z",
    "health_check": "2026-06-27T21:54:07.808752Z",
    "version": "1.2.7",
    "uptime": 99,
    "limit": 10,
    "upload": 0,
    "download": 0,
    "disk": 78.02,
    "mem": 23.89,
    "cpu": 3.0000000232830644,
    "uptime_sec": 4617325,
    "net_download": 32577,
    "net_upload": 36587,
    "traffic_users": 2912141326557,
    "traffic_node": 7537447577420,
    "users": 6
  },
  {
    "address": "EQDWdWtcCwGNNVND8C00IAM1xPpQDp3m1IdM67D1-chLoiVe",
    "is_active": true,
    "node_registry": "EQDbPc6xGV6-nCmDH8bVXUdQCQ1tXMM062Xah-63HAMAkpq8",
    "owner": "EQA0ltvrkBHmBa0QSTNHcZSUNIvha1F6hTwCCMGPbyVPNpTq",
    "tickets_total": 6263,
    "tickets_30d": 4303,
    "ratings_total": 0,
    "ratings_30d": 0,
    "ratings_avg_stars": 0.0,
    "ratings_avg_stars_30d": 0.0,
    "plan": "time",
    "hostname": "k.cdn-vk.run",
    "country": "RU",
    "region": "Kuzbass",
    "city": "Kemerovo",
    "ip": "77.110.112.64",
    "exit_ip": null,
    "ssl": true,
    "check_port": 443,
    "api_port": 443,
    "api_path": "/api/v1",
    "public_key": "3da82636c5cfa428209f58465ea7daf1b2ed10ffdeba2c27c5f031f7168cc047",
    "node_id": 7681098111864,
    "scanned": "2026-06-27T21:58:44.401839Z",
    "heartbeat": "2026-06-05T01:31:59.907734Z",
    "health_check": "2026-06-05T01:44:16.404741Z",
    "version": "1.2.7",
    "uptime": 99,
    "limit": 100,
    "upload": 0,
    "download": 0,
    "disk": 79.33,
    "mem": 51.96,
    "cpu": 0.0,
    "uptime_sec": 153113,
    "net_download": 7194,
    "net_upload": 0,
    "traffic_users": 288580599412,
    "traffic_node": 1640555706165,
    "users": 0
  },
  {
    "address": "EQDW1FDkKA2rNDJco73gfyhzg-OT4_zd18SJJ-kSUttk2iw2",
    "is_active": true,
    "node_registry": "EQDbPc6xGV6-nCmDH8bVXUdQCQ1tXMM062Xah-63HAMAkpq8",
    "owner": "EQA0ltvrkBHmBa0QSTNHcZSUNIvha1F6hTwCCMGPbyVPNpTq",
    "tickets_total": 4089,
    "tickets_30d": 1835,
    "ratings_total": 0,
    "ratings_30d": 0,
    "ratings_avg_stars": 0.0,
    "ratings_avg_stars_30d": 0.0,
    "plan": "time",
    "hostname": "rude.cdn-vk.run",
    "country": "RU",
    "region": "Moscow",
    "city": "Moscow",
    "ip": "193.247.73.42",
    "exit_ip": null,
    "ssl": true,
    "check_port": 443,
    "api_port": 443,
    "api_path": "/api/v1",
    "public_key": "8fdfadb3e23aa382f4c98127833e4978f8ba7ac3ab839c9f52d4890a68943322",
    "node_id": 1928246872842,
    "scanned": "2026-06-27T21:58:44.396592Z",
    "heartbeat": "2026-06-27T21:58:23.826975Z",
    "health_check": "2026-06-27T21:54:08.266480Z",
    "version": "1.2.7",
    "uptime": 100,
    "limit": 100,
    "upload": 0,
    "download": 0,
    "disk": 81.17,
    "mem": 45.38,
    "cpu": 2.040816279983878,
    "uptime_sec": 4610009,
    "net_download": 1649,
    "net_upload": 1055,
    "traffic_users": 232420615444,
    "traffic_node": 1401591028246,
    "users": 0
  },
  {
    "address": "EQDTz0Tgjcn75_FjvcoLc3Ez7nOyHovj54kZFTH8ez5hTgxQ",
    "is_active": true,
    "node_registry": "EQDbPc6xGV6-nCmDH8bVXUdQCQ1tXMM062Xah-63HAMAkpq8",
    "owner": "EQA0ltvrkBHmBa0QSTNHcZSUNIvha1F6hTwCCMGPbyVPNpTq",
    "tickets_total": 35299,
    "tickets_30d": 12428,
    "ratings_total": 0,
    "ratings_30d": 0,
    "ratings_avg_stars": 0.0,
    "ratings_avg_stars_30d": 0.0,
    "plan": "time",
    "hostname": "fr.yastatic.site",
    "country": "FR",
    "region": "\u00cele-de-France",
    "city": "Paris",
    "ip": "138.124.70.136",
    "exit_ip": null,
    "ssl": true,
    "check_port": 443,
    "api_port": 443,
    "api_path": "/api/v1",
    "public_key": "2de84e2d25910271d0ba4ecba24039d8bb99bca38a98f95e6407bfb1842456b0",
    "node_id": 13781238698136,
    "scanned": "2026-06-27T21:58:44.390800Z",
    "heartbeat": "2026-06-27T21:58:07.437481Z",
    "health_check": "2026-06-27T21:54:07.494456Z",
    "version": "1.2.7",
    "uptime": 99,
    "limit": 100,
    "upload": 0,
    "download": 0,
    "disk": 35.59,
    "mem": 25.16,
    "cpu": 2.487562136035199,
    "uptime_sec": 4617355,
    "net_download": 3988,
    "net_upload": 1520,
    "traffic_users": 859174608793,
    "traffic_node": 2856852442179,
    "users": 2
  },
  {
    "address": "EQDCv8yYF0u16yckW6DboA-FINyn9cha0fImggWAxCth6uCr",
    "is_active": true,
    "node_registry": "EQDbPc6xGV6-nCmDH8bVXUdQCQ1tXMM062Xah-63HAMAkpq8",
    "owner": "EQA0ltvrkBHmBa0QSTNHcZSUNIvha1F6hTwCCMGPbyVPNpTq",
    "tickets_total": 4106,
    "tickets_30d": 1929,
    "ratings_total": 0,
    "ratings_30d": 0,
    "ratings_avg_stars": 0.0,
    "ratings_avg_stars_30d": 0.0,
    "plan": "time",
    "hostname": "max.cdn-vk.run",
    "country": "RU",
    "region": "Moscow",
    "city": "Moscow",
    "ip": "150.241.85.59",
    "exit_ip": null,
    "ssl": true,
    "check_port": 443,
    "api_port": 443,
    "api_path": "/api/v1",
    "public_key": "02185c834de980cb38afb83ac6471a62007b94a1d9b921e1cc9b6d33edf58d06",
    "node_id": 1498240884859,
    "scanned": "2026-06-27T21:58:44.384847Z",
    "heartbeat": "2026-06-27T21:58:14.604825Z",
    "health_check": "2026-06-27T21:54:07.841788Z",
    "version": "1.2.7",
    "uptime": 99,
    "limit": 100,
    "upload": 0,
    "download": 0,
    "disk": 20.06,
    "mem": 19.66,
    "cpu": 0.0,
    "uptime_sec": 3093715,
    "net_download": 303,
    "net_upload": 132,
    "traffic_users": 165454091500,
    "traffic_node": 1166518509464,
    "users": 0
  },
  {
    "address": "EQD6wzIFOah2NMwBM7VBAQQcEwSu1VteLgLLy9-4RmzuJ4M3",
    "is_active": true,
    "node_registry": "EQDbPc6xGV6-nCmDH8bVXUdQCQ1tXMM062Xah-63HAMAkpq8",
    "owner": "EQA0ltvrkBHmBa0QSTNHcZSUNIvha1F6hTwCCMGPbyVPNpTq",
    "tickets_total": 14610,
    "tickets_30d": 2613,
    "ratings_total": 0,
    "ratings_30d": 0,
    "ratings_avg_stars": 0.0,
    "ratings_avg_stars_30d": 0.0,
    "plan": "time",
    "hostname": "nov.cdn-vk.run",
    "country": "RU",
    "region": "Novosibirsk Oblast",
    "city": "Novosibirsk",
    "ip": "185.21.142.233",
    "exit_ip": null,
    "ssl": true,
    "check_port": 443,
    "api_port": 443,
    "api_path": "/api/v1",
    "public_key": "9615af1c7a5bcf66ffd8e78521d8b5cd4820948edeb42c88c090092d176f5e06",
    "node_id": 18482081418233,
    "scanned": "2026-06-27T21:58:44.377829Z",
    "heartbeat": "2026-06-27T21:58:16.014394Z",
    "health_check": "2026-06-27T21:54:07.747707Z",
    "version": "1.2.7",
    "uptime": 99,
    "limit": 100,
    "upload": 0,
    "download": 0,
    "disk": 63.13,
    "mem": 49.43,
    "cpu": 1.0101011735409473,
    "uptime_sec": 637894,
    "net_download": 0,
    "net_upload": 0,
    "traffic_users": 135607368511,
    "traffic_node": 1139981977256,
    "users": 0
  },
  {
    "address": "EQD6uRTOE2HhfvSuonStLzqdStM5Sdhimb4Mj_9wboKv7z12",
    "is_active": true,
    "node_registry": "EQDbPc6xGV6-nCmDH8bVXUdQCQ1tXMM062Xah-63HAMAkpq8",
    "owner": "EQA0ltvrkBHmBa0QSTNHcZSUNIvha1F6hTwCCMGPbyVPNpTq",
    "tickets_total": 13419,
    "tickets_30d": 3531,
    "ratings_total": 0,
    "ratings_30d": 0,
    "ratings_avg_stars": 0.0,
    "ratings_avg_stars_30d": 0.0,
    "plan": "time",
    "hostname": "ae.cdn-vk.run",
    "country": "RU",
    "region": "Moscow",
    "city": "Moscow",
    "ip": "85.192.56.94",
    "exit_ip": null,
    "ssl": true,
    "check_port": 443,
    "api_port": 443,
    "api_path": "/api/v1",
    "public_key": "b1c0baa4c8ace3f074c776ddaab01f8b1ca90ff3ef786a5a98c2c5bece2b7ec3",
    "node_id": 848191855894,
    "scanned": "2026-06-27T21:58:44.369735Z",
    "heartbeat": "2026-06-27T21:58:14.531449Z",
    "health_check": "2026-06-27T21:54:07.594964Z",
    "version": "1.2.7",
    "uptime": 99,
    "limit": 100,
    "upload": 0,
    "download": 0,
    "disk": 31.06,
    "mem": 14.37,
    "cpu": 0.9900990108139619,
    "uptime_sec": 1109244,
    "net_download": 388,
    "net_upload": 430,
    "traffic_users": 27999407302,
    "traffic_node": 667055084262,
    "users": 0
  },
  {
    "address": "EQD6TxPPibaYdZhY4SKxnaw5U0AM414S9iN4SNpcpzpZhOAw",
    "is_active": true,
    "node_registry": "EQDbPc6xGV6-nCmDH8bVXUdQCQ1tXMM062Xah-63HAMAkpq8",
    "owner": "EQA0ltvrkBHmBa0QSTNHcZSUNIvha1F6hTwCCMGPbyVPNpTq",
    "tickets_total": 31087,
    "tickets_30d": 16306,
    "ratings_total": 8,
    "ratings_30d": 5,
    "ratings_avg_stars": 4.62,
    "ratings_avg_stars_30d": 4.4,
    "plan": "time",
    "hostname": "ua.media-cdn.online",
    "country": "UA",
    "region": "Kyiv City",
    "city": "Kyiv",
    "ip": "5.34.182.90",
    "exit_ip": null,
    "ssl": true,
    "check_port": 443,
    "api_port": 443,
    "api_path": "/api/v1",
    "public_key": "b355ec1119586a4a389e390e169cc964a9c645d229838df16e0c7c03cff9d7af",
    "node_id": 48338181890,
    "scanned": "2026-06-27T21:58:44.363087Z",
    "heartbeat": "2026-06-27T21:58:40.129515Z",
    "health_check": "2026-06-27T21:54:07.281486Z",
    "version": "1.2.11",
    "uptime": 99,
    "limit": 100,
    "upload": 0,
    "download": 0,
    "disk": 81.49,
    "mem": 40.69,
    "cpu": 9.090908996836102,
    "uptime_sec": 3021711,
    "net_download": 128964,
    "net_upload": 8128,
    "traffic_users": 3532619823026,
    "traffic_node": 8957869569592,
    "users": 0
  },
  {
    "address": "EQD4OZw8zOQ0oMPLrXDIsa11XyFVOu6V4eXTBELFZw7jcsjf",
    "is_active": true,
    "node_registry": "EQDbPc6xGV6-nCmDH8bVXUdQCQ1tXMM062Xah-63HAMAkpq8",
    "owner": "EQA0ltvrkBHmBa0QSTNHcZSUNIvha1F6hTwCCMGPbyVPNpTq",
    "tickets_total": 6316,
    "tickets_30d": 648,
    "ratings_total": 0,
    "ratings_30d": 0,
    "ratings_avg_stars": 0.0,
    "ratings_avg_stars_30d": 0.0,
    "plan": "time",
    "hostname": "ptr.yastatic.run",
    "country": "RU",
    "region": "St.-Petersburg",
    "city": "Saint Petersburg",
    "ip": "5.188.211.136",
    "exit_ip": null,
    "ssl": true,
    "check_port": 443,
    "api_port": 443,
    "api_path": "/api/v1",
    "public_key": "3eacf3d0e360d35711976b4a69714b3b1e8580eb44906411bedeb0087c7aa651",
    "node_id": 4818782108136,
    "scanned": "2026-06-27T21:58:44.356989Z",
    "heartbeat": "2026-06-27T21:58:32.078548Z",
    "health_check": "2026-06-27T21:54:07.403544Z",
    "version": "1.2.7",
    "uptime": 99,
    "limit": 100,
    "upload": 0,
    "download": 0,
    "disk": 48.5,
    "mem": 27.61,
    "cpu": 24.752475253002583,
    "uptime_sec": 4622875,
    "net_download": 86103,
    "net_upload": 89699,
    "traffic_users": 1869411493985,
    "traffic_node": 8276707852204,
    "users": 9
  },
  {
    "address": "EQD3LT4bTCmjjN7ZRXI5qck7hgMR5iKDWUUGQWd54R2u_M5V",
    "is_active": true,
    "node_registry": "EQDbPc6xGV6-nCmDH8bVXUdQCQ1tXMM062Xah-63HAMAkpq8",
    "owner": "EQA0ltvrkBHmBa0QSTNHcZSUNIvha1F6hTwCCMGPbyVPNpTq",
    "tickets_total": 18640,
    "tickets_30d": 4789,
    "ratings_total": 0,
    "ratings_30d": 0,
    "ratings_avg_stars": 0.0,
    "ratings_avg_stars_30d": 0.0,
    "plan": "time",
    "hostname": "ru.cdn-vk.run",
    "country": "RU",
    "region": "Primorye",
    "city": "Vladivostok",
    "ip": "193.124.9.226",
    "exit_ip": null,
    "ssl": true,
    "check_port": 443,
    "api_port": 443,
    "api_path": "/api/v1",
    "public_key": "fd7e2f846288e7a1aee506adbd281d3ee5682bcf15b03687c01625fc2646eb3d",
    "node_id": 1928123888226,
    "scanned": "2026-06-27T21:58:44.350612Z",
    "heartbeat": "2026-06-27T21:58:25.511365Z",
    "health_check": "2026-06-27T21:54:09.272307Z",
    "version": "1.2.7",
    "uptime": 99,
    "limit": 100,
    "upload": 0,
    "download": 0,
    "disk": 88.07,
    "mem": 41.83,
    "cpu": 3.0303030559592994,
    "uptime_sec": 404539,
    "net_download": 9976,
    "net_upload": 12683,
    "traffic_users": 94513109926,
    "traffic_node": 1282798508366,
    "users": 0
  },
  {
    "address": "EQCwbNWT6x5mWBaajKOd5H5qgYbMgL1o3yhEtWUUqcURUHpT",
    "is_active": true,
    "node_registry": "EQDbPc6xGV6-nCmDH8bVXUdQCQ1tXMM062Xah-63HAMAkpq8",
    "owner": "EQA0ltvrkBHmBa0QSTNHcZSUNIvha1F6hTwCCMGPbyVPNpTq",
    "tickets_total": 89677,
    "tickets_30d": 37404,
    "ratings_total": 1,
    "ratings_30d": 0,
    "ratings_avg_stars": 5.0,
    "ratings_avg_stars_30d": 0.0,
    "plan": "time",
    "hostname": "uk.yastatic.site",
    "country": "GB",
    "region": "England",
    "city": "London",
    "ip": "173.208.51.125",
    "exit_ip": null,
    "ssl": true,
    "check_port": 443,
    "api_port": 443,
    "api_path": "/api/v1",
    "public_key": "2e54ff5b425264a0dd3db9e25dcde13aec657531f57e9f1cf89ae3ac93542067",
    "node_id": 17282078508125,
    "scanned": "2026-06-27T21:58:44.343341Z",
    "heartbeat": "2026-06-27T21:58:33.452500Z",
    "health_check": "2026-06-27T21:54:08.053403Z",
    "version": "1.2.7",
    "uptime": 98,
    "limit": 100,
    "upload": 0,
    "download": 0,
    "disk": 6.6,
    "mem": 8.74,
    "cpu": 0.5000000814907252,
    "uptime_sec": 4616948,
    "net_download": 480,
    "net_upload": 264,
    "traffic_users": 14515040608859,
    "traffic_node": 36317215136137,
    "users": 1
  },
  {
    "address": "EQCt_0YYtDYxjiu_ON2aJF3N8QQf3yftQ4pa6sYjdTk1jkUf",
    "is_active": true,
    "node_registry": "EQDbPc6xGV6-nCmDH8bVXUdQCQ1tXMM062Xah-63HAMAkpq8",
    "owner": "EQA0ltvrkBHmBa0QSTNHcZSUNIvha1F6hTwCCMGPbyVPNpTq",
    "tickets_total": 102853,
    "tickets_30d": 40115,
    "ratings_total": 2,
    "ratings_30d": 0,
    "ratings_avg_stars": 3.0,
    "ratings_avg_stars_30d": 0.0,
    "plan": "time",
    "hostname": "pl.cdn-vk.run",
    "country": "PL",
    "region": "Mazovia",
    "city": "Warsaw",
    "ip": "45.144.49.56",
    "exit_ip": null,
    "ssl": true,
    "check_port": 443,
    "api_port": 443,
    "api_path": "/api/v1",
    "public_key": "d1de822f637a95b783678c5c2d8207e8bed1653fe28a0f8f2c392696ddb49800",
    "node_id": 448143848856,
    "scanned": "2026-06-27T21:58:44.336630Z",
    "heartbeat": "2026-06-27T21:58:41.594744Z",
    "health_check": "2026-06-27T21:54:08.247669Z",
    "version": "1.2.7",
    "uptime": 99,
    "limit": 100,
    "upload": 0,
    "download": 0,
    "disk": 57.2,
    "mem": 26.84,
    "cpu": 5.050505032925755,
    "uptime_sec": 2306728,
    "net_download": 740475,
    "net_upload": 512277,
    "traffic_users": 5556982823649,
    "traffic_node": 16819039835114,
    "users": 9
  },
  {
    "address": "EQCpic66nMCZEdlY5km-G1WEStMc0TixjDryR9xr4sYak9Z8",
    "is_active": true,
    "node_registry": "EQDbPc6xGV6-nCmDH8bVXUdQCQ1tXMM062Xah-63HAMAkpq8",
    "owner": "EQA0ltvrkBHmBa0QSTNHcZSUNIvha1F6hTwCCMGPbyVPNpTq",
    "tickets_total": 4973,
    "tickets_30d": 4973,
    "ratings_total": 0,
    "ratings_30d": 0,
    "ratings_avg_stars": 0.0,
    "ratings_avg_stars_30d": 0.0,
    "plan": "time",
    "hostname": "web.yastatic.site",
    "country": "VN",
    "region": "Ho Chi Minh City (HCMC)",
    "city": "Ho Chi Minh City",
    "ip": "61.14.234.27",
    "exit_ip": null,
    "ssl": true,
    "check_port": 443,
    "api_port": 443,
    "api_path": "/api/v1",
    "public_key": "6fe7e0fbcd1e443941b70bd9ffe259d96d0f95c0dc5af7159fc37547b5fb2688",
    "node_id": 608138233827,
    "scanned": "2026-06-27T21:58:44.330833Z",
    "heartbeat": "2026-05-18T00:45:26.526266Z",
    "health_check": "2026-05-18T01:01:13.878306Z",
    "version": "1.2.7",
    "uptime": 100,
    "limit": 100,
    "upload": 60,
    "download": 73,
    "disk": 41.45,
    "mem": 31.04,
    "cpu": 8.080808086509474,
    "uptime_sec": 1087521,
    "net_download": 40440,
    "net_upload": 32425,
    "traffic_users": 822169256393,
    "traffic_node": 2627430854078,
    "users": 4
  },
  {
    "address": "EQCpC9s6Wy0qs9TEcznguDdbz1uZvqHmqPJgureKT3if6RBk",
    "is_active": true,
    "node_registry": "EQDbPc6xGV6-nCmDH8bVXUdQCQ1tXMM062Xah-63HAMAkpq8",
    "owner": "EQA0ltvrkBHmBa0QSTNHcZSUNIvha1F6hTwCCMGPbyVPNpTq",
    "tickets_total": 54804,
    "tickets_30d": 18231,
    "ratings_total": 2,
    "ratings_30d": 0,
    "ratings_avg_stars": 2.5,
    "ratings_avg_stars_30d": 0.0,
    "plan": "time",
    "hostname": "get.cdn-vk.run",
    "country": "FI",
    "region": "Uusimaa",
    "city": "Helsinki",
    "ip": "185.88.101.50",
    "exit_ip": null,
    "ssl": true,
    "check_port": 443,
    "api_port": 443,
    "api_path": "/api/v1",
    "public_key": "ee9aaba20d3a0aec82f1fa88f9ffab0113958eaa206c155e134a4531a1b202af",
    "node_id": 1848878100850,
    "scanned": "2026-06-27T21:58:44.324973Z",
    "heartbeat": "2026-06-27T21:58:45.336701Z",
    "health_check": "2026-06-27T21:54:07.437346Z",
    "version": "1.2.7",
    "uptime": 98,
    "limit": 100,
    "upload": 198,
    "download": 203,
    "disk": 35.97,
    "mem": 22.81,
    "cpu": 16.33663364761757,
    "uptime_sec": 1988792,
    "net_download": 72972,
    "net_upload": 1429735,
    "traffic_users": 1260847536041,
    "traffic_node": 4916272360766,
    "users": 3
  },
  {
    "address": "EQCeSadEW1a5iGzLZOLYRn-IvHwluxKttZKuFlVNbwwe0xdT",
    "is_active": true,
    "node_registry": "EQDbPc6xGV6-nCmDH8bVXUdQCQ1tXMM062Xah-63HAMAkpq8",
    "owner": "EQA0ltvrkBHmBa0QSTNHcZSUNIvha1F6hTwCCMGPbyVPNpTq",
    "tickets_total": 6064,
    "tickets_30d": 1340,
    "ratings_total": 0,
    "ratings_30d": 0,
    "ratings_avg_stars": 0.0,
    "ratings_avg_stars_30d": 0.0,
    "plan": "time",
    "hostname": "msk.yastatic.run",
    "country": "RU",
    "region": "Moscow",
    "city": "Moscow",
    "ip": "5.45.83.194",
    "exit_ip": null,
    "ssl": true,
    "check_port": 443,
    "api_port": 443,
    "api_path": "/api/v1",
    "public_key": "7acf7ca2d017c7297ed16388e28a20fa1dccf7c7e6fbd823c14ecfd47ae2a91f",
    "node_id": 48448828194,
    "scanned": "2026-06-27T21:58:44.318932Z",
    "heartbeat": "2026-06-27T21:58:15.951168Z",
    "health_check": "2026-06-27T21:54:07.323192Z",
    "version": "1.2.7",
    "uptime": 99,
    "limit": 10,
    "upload": 0,
    "download": 0,
    "disk": 39.89,
    "mem": 21.87,
    "cpu": 0.0,
    "uptime_sec": 4045931,
    "net_download": 171,
    "net_upload": 225,
    "traffic_users": 197452303914,
    "traffic_node": 1320266093962,
    "users": 0
  },
  {
    "address": "EQCbeMzO3tNf06mZymWt60aSx7VbWkpZEu6kAoVvo5u7SmMS",
    "is_active": true,
    "node_registry": "EQDbPc6xGV6-nCmDH8bVXUdQCQ1tXMM062Xah-63HAMAkpq8",
    "owner": "EQA0ltvrkBHmBa0QSTNHcZSUNIvha1F6hTwCCMGPbyVPNpTq",
    "tickets_total": 14347,
    "tickets_30d": 14347,
    "ratings_total": 1,
    "ratings_30d": 1,
    "ratings_avg_stars": 2.0,
    "ratings_avg_stars_30d": 2.0,
    "plan": "time",
    "hostname": "nl.edge-apple.online",
    "country": "NL",
    "region": "North Holland",
    "city": "Amsterdam",
    "ip": "45.15.128.126",
    "exit_ip": null,
    "ssl": true,
    "check_port": 443,
    "api_port": 443,
    "api_path": "/api/v1",
    "public_key": "9feb6386e06bff536f3f3318b795f14ef907302b60c9fc736fc70874af3c9648",
    "node_id": 4481481278126,
    "scanned": "2026-06-27T21:58:44.312813Z",
    "heartbeat": "2026-05-18T12:08:49.278265Z",
    "health_check": "2026-05-18T12:24:30.749634Z",
    "version": "1.2.7",
    "uptime": 99,
    "limit": 100,
    "upload": 0,
    "download": 0,
    "disk": 26.78,
    "mem": 57.52,
    "cpu": 24.44444445686208,
    "uptime_sec": 550,
    "net_download": 868194,
    "net_upload": 946591,
    "traffic_users": 6259748631516,
    "traffic_node": 15156913859580,
    "users": 12
  },
  {
    "address": "EQCO9bsuYzIen0Oj6J3YA3C0fzNRcLVJdjwvVgKUXEaxybbj",
    "is_active": true,
    "node_registry": "EQDbPc6xGV6-nCmDH8bVXUdQCQ1tXMM062Xah-63HAMAkpq8",
    "owner": "EQA0ltvrkBHmBa0QSTNHcZSUNIvha1F6hTwCCMGPbyVPNpTq",
    "tickets_total": 24725,
    "tickets_30d": 9457,
    "ratings_total": 0,
    "ratings_30d": 0,
    "ratings_avg_stars": 0.0,
    "ratings_avg_stars_30d": 0.0,
    "plan": "time",
    "hostname": "spb.media-cdn.online",
    "country": "RU",
    "region": "St.-Petersburg",
    "city": "Saint Petersburg",
    "ip": "193.233.91.122",
    "exit_ip": null,
    "ssl": true,
    "check_port": 443,
    "api_port": 443,
    "api_path": "/api/v1",
    "public_key": "cc0612807653e11357cf8b47d055e0a384909ec7df9120a52d207d4f551e98c9",
    "node_id": 19282328908122,
    "scanned": "2026-06-27T21:58:44.307122Z",
    "heartbeat": "2026-06-27T21:58:09.612696Z",
    "health_check": "2026-06-27T21:54:07.798985Z",
    "version": "1.2.7",
    "uptime": 99,
    "limit": 100,
    "upload": 0,
    "download": 0,
    "disk": 27.98,
    "mem": 16.69,
    "cpu": 0.0,
    "uptime_sec": 1109242,
    "net_download": 7472,
    "net_upload": 8610,
    "traffic_users": 247040101451,
    "traffic_node": 1946538532609,
    "users": 0
  },
  {
    "address": "EQCKqB8nDQb0Ejbxl_iG_cdSUYcfezPrSmT3NV5nCMEIruTs",
    "is_active": true,
    "node_registry": "EQDbPc6xGV6-nCmDH8bVXUdQCQ1tXMM062Xah-63HAMAkpq8",
    "owner": "EQA0ltvrkBHmBa0QSTNHcZSUNIvha1F6hTwCCMGPbyVPNpTq",
    "tickets_total": 21806,
    "tickets_30d": 7096,
    "ratings_total": 0,
    "ratings_30d": 0,
    "ratings_avg_stars": 0.0,
    "ratings_avg_stars_30d": 0.0,
    "plan": "time",
    "hostname": "sp.yastatic.site",
    "country": "RU",
    "region": "St.-Petersburg",
    "city": "Saint Petersburg",
    "ip": "83.147.255.125",
    "exit_ip": null,
    "ssl": true,
    "check_port": 443,
    "api_port": 443,
    "api_path": "/api/v1",
    "public_key": "90da8535c2cacef5d55c51ee0fb7c3181a8365aa67c6d17b66ce1a05e2ba152a",
    "node_id": 82814682548125,
    "scanned": "2026-06-27T21:58:44.300020Z",
    "heartbeat": "2026-06-27T21:58:04.912504Z",
    "health_check": "2026-06-27T21:54:08.568952Z",
    "version": "1.2.10",
    "uptime": 99,
    "limit": 100,
    "upload": 0,
    "download": 0,
    "disk": 30.56,
    "mem": 16.57,
    "cpu": 0.0,
    "uptime_sec": 1109236,
    "net_download": 7098,
    "net_upload": 7566,
    "traffic_users": 226549992209,
    "traffic_node": 1488989210902,
    "users": 0
  },
  {
    "address": "EQCJLajK__ywESlcb7y4LPYKhQ5_reEsBIgJ1H5kLrabqRDF",
    "is_active": true,
    "node_registry": "EQDbPc6xGV6-nCmDH8bVXUdQCQ1tXMM062Xah-63HAMAkpq8",
    "owner": "EQA0ltvrkBHmBa0QSTNHcZSUNIvha1F6hTwCCMGPbyVPNpTq",
    "tickets_total": 61898,
    "tickets_30d": 10373,
    "ratings_total": 3,
    "ratings_30d": 2,
    "ratings_avg_stars": 4.67,
    "ratings_avg_stars_30d": 5.0,
    "plan": "time",
    "hostname": "vk.com.yastatic.site",
    "country": "CH",
    "region": "Bern",
    "city": "Bern",
    "ip": "45.59.122.235",
    "exit_ip": null,
    "ssl": true,
    "check_port": 443,
    "api_port": 443,
    "api_path": "/api/v1",
    "public_key": "10846484cf93dea2f6ab0bf6361b05d38bc7f3b6f4691846804f4718716a6582",
    "node_id": 4485881218235,
    "scanned": "2026-06-27T21:58:44.291756Z",
    "heartbeat": "2026-06-27T21:58:21.489650Z",
    "health_check": "2026-06-27T21:54:07.169264Z",
    "version": "1.2.7",
    "uptime": 100,
    "limit": 100,
    "upload": 528,
    "download": 2717,
    "disk": 31.65,
    "mem": 44.95,
    "cpu": 1.0101010110512423,
    "uptime_sec": 208102,
    "net_download": 39083,
    "net_upload": 28429,
    "traffic_users": 1983773856625,
    "traffic_node": 6625523978961,
    "users": 4
  },
  {
    "address": "EQCGokVlstQbF_P-bva5AnkcOPFSOjYrhnD4Q8I7jxEMTy_H",
    "is_active": true,
    "node_registry": "EQDbPc6xGV6-nCmDH8bVXUdQCQ1tXMM062Xah-63HAMAkpq8",
    "owner": "EQA0ltvrkBHmBa0QSTNHcZSUNIvha1F6hTwCCMGPbyVPNpTq",
    "tickets_total": 10549,
    "tickets_30d": 4106,
    "ratings_total": 0,
    "ratings_30d": 0,
    "ratings_avg_stars": 0.0,
    "ratings_avg_stars_30d": 0.0,
    "plan": "time",
    "hostname": "msk.cdn-vk.rest",
    "country": "RU",
    "region": "Moscow",
    "city": "Moscow",
    "ip": "150.241.85.225",
    "exit_ip": null,
    "ssl": true,
    "check_port": 443,
    "api_port": 443,
    "api_path": "/api/v1",
    "public_key": "c1391afbc9abf68bc88933bfe9eb306a12b74d47c534d6fc95a356ad107a8254",
    "node_id": 14982408848225,
    "scanned": "2026-06-27T21:58:44.283594Z",
    "heartbeat": "2026-06-19T06:00:25.947602Z",
    "health_check": "2026-06-19T06:16:29.227816Z",
    "version": "1.2.7",
    "uptime": 99,
    "limit": 100,
    "upload": 0,
    "download": 0,
    "disk": 13.28,
    "mem": 18.95,
    "cpu": 0.0,
    "uptime_sec": 2345073,
    "net_download": 167,
    "net_upload": 54,
    "traffic_users": 342604387394,
    "traffic_node": 1984509697466,
    "users": 0
  },
  {
    "address": "EQC4c0I4lOSBM_68Yk5RxpQ0XXIfbhaTh8LA20656K6QptYO",
    "is_active": true,
    "node_registry": "EQDbPc6xGV6-nCmDH8bVXUdQCQ1tXMM062Xah-63HAMAkpq8",
    "owner": "EQA0ltvrkBHmBa0QSTNHcZSUNIvha1F6hTwCCMGPbyVPNpTq",
    "tickets_total": 15601,
    "tickets_30d": 4718,
    "ratings_total": 0,
    "ratings_30d": 0,
    "ratings_avg_stars": 0.0,
    "ratings_avg_stars_30d": 0.0,
    "plan": "time",
    "hostname": "hip.edge-apple.online",
    "country": "DE",
    "region": "Hesse",
    "city": "Frankfurt am Main",
    "ip": "46.21.82.243",
    "exit_ip": null,
    "ssl": true,
    "check_port": 443,
    "api_port": 443,
    "api_path": "/api/v1",
    "public_key": "ecae397a5489ea573de974d1dfa07497761a61d68dfa3b7a9f18e29d0be6c9f6",
    "node_id": 458208818243,
    "scanned": "2026-06-27T21:58:44.276214Z",
    "heartbeat": "2026-06-27T21:57:31.648477Z",
    "health_check": "2026-06-27T21:54:06.996161Z",
    "version": "1.2.11",
    "uptime": 99,
    "limit": 100,
    "upload": 0,
    "download": 0,
    "disk": 32.96,
    "mem": 17.9,
    "cpu": 0.0,
    "uptime_sec": 596085,
    "net_download": 707,
    "net_upload": 617,
    "traffic_users": 205908791778,
    "traffic_node": 822805695813,
    "users": 1
  },
  {
    "address": "EQC4GIB9y_6YUdWQA4Z-ZOTyvc1GCfJUU6ZFuG_fYtbsCOEV",
    "is_active": true,
    "node_registry": "EQDbPc6xGV6-nCmDH8bVXUdQCQ1tXMM062Xah-63HAMAkpq8",
    "owner": "EQA0ltvrkBHmBa0QSTNHcZSUNIvha1F6hTwCCMGPbyVPNpTq",
    "tickets_total": 63168,
    "tickets_30d": 40710,
    "ratings_total": 3,
    "ratings_30d": 3,
    "ratings_avg_stars": 5.0,
    "ratings_avg_stars_30d": 5.0,
    "plan": "time",
    "hostname": "prg.media-cdn.online",
    "country": "CZ",
    "region": "Prague",
    "city": "Prague",
    "ip": "46.28.70.243",
    "exit_ip": null,
    "ssl": true,
    "check_port": 443,
    "api_port": 443,
    "api_path": "/api/v1",
    "public_key": "1ecccba7c8accf1b17df291af5fd9e8bd33ada8f712ff3c35b459902c2e25c6a",
    "node_id": 458278698243,
    "scanned": "2026-06-27T21:58:44.268489Z",
    "heartbeat": "2026-06-27T21:58:13.123882Z",
    "health_check": "2026-06-27T21:54:07.135261Z",
    "version": "1.2.7",
    "uptime": 99,
    "limit": 100,
    "upload": 0,
    "download": 0,
    "disk": 76.27,
    "mem": 43.11,
    "cpu": 0.9999999781139196,
    "uptime_sec": 354915,
    "net_download": 19405,
    "net_upload": 442,
    "traffic_users": 10358599813328,
    "traffic_node": 27050282138695,
    "users": 0
  },
  {
    "address": "EQC1snGO9Lx7ZT2pw6cGR2OgxqN4I__u6P-KscNcI9t_7TJc",
    "is_active": true,
    "node_registry": "EQDbPc6xGV6-nCmDH8bVXUdQCQ1tXMM062Xah-63HAMAkpq8",
    "owner": "EQA0ltvrkBHmBa0QSTNHcZSUNIvha1F6hTwCCMGPbyVPNpTq",
    "tickets_total": 12452,
    "tickets_30d": 4815,
    "ratings_total": 0,
    "ratings_30d": 0,
    "ratings_avg_stars": 0.0,
    "ratings_avg_stars_30d": 0.0,
    "plan": "time",
    "hostname": "deq.yastatic.run",
    "country": "DE",
    "region": "Hesse",
    "city": "Frankfurt am Main",
    "ip": "5.61.32.103",
    "exit_ip": null,
    "ssl": true,
    "check_port": 443,
    "api_port": 443,
    "api_path": "/api/v1",
    "public_key": "bcf4a69a55e58b63c25a16bf6987b2508d1765250d7f1afa035ca48e71fe3325",
    "node_id": 48608318103,
    "scanned": "2026-06-27T21:58:44.262462Z",
    "heartbeat": "2026-06-27T21:58:21.208287Z",
    "health_check": "2026-06-27T21:54:06.971960Z",
    "version": "1.2.11",
    "uptime": 99,
    "limit": 100,
    "upload": 0,
    "download": 0,
    "disk": 27.13,
    "mem": 20.86,
    "cpu": 0.4999999771825969,
    "uptime_sec": 3097287,
    "net_download": 392,
    "net_upload": 912,
    "traffic_users": 1251758218575,
    "traffic_node": 3436937206291,
    "users": 0
  },
  {
    "address": "EQC-UjsuvMukXtKKaxBupC2VTSLqc5gl4--10fGHK1TZ-Odf",
    "is_active": true,
    "node_registry": "EQDbPc6xGV6-nCmDH8bVXUdQCQ1tXMM062Xah-63HAMAkpq8",
    "owner": "EQA0ltvrkBHmBa0QSTNHcZSUNIvha1F6hTwCCMGPbyVPNpTq",
    "tickets_total": 72003,
    "tickets_30d": 22374,
    "ratings_total": 1,
    "ratings_30d": 1,
    "ratings_avg_stars": 5.0,
    "ratings_avg_stars_30d": 5.0,
    "plan": "time",
    "hostname": "xxl.cdn-vk.run",
    "country": "NL",
    "region": "Flevoland",
    "city": "Lelystad",
    "ip": "95.211.41.85",
    "exit_ip": null,
    "ssl": true,
    "check_port": 443,
    "api_port": 443,
    "api_path": "/api/v1",
    "public_key": "ccab9e27fdb7b7abe679bb3f0cb63938de5812e434c62efd2371c64cde4c735d",
    "node_id": 948210840885,
    "scanned": "2026-06-27T21:58:44.253251Z",
    "heartbeat": "2026-06-27T21:58:25.104553Z",
    "health_check": "2026-06-27T21:54:06.942731Z",
    "version": "1.2.7",
    "uptime": 99,
    "limit": 50,
    "upload": 0,
    "download": 0,
    "disk": 8.72,
    "mem": 7.46,
    "cpu": 0.5012531449415376,
    "uptime_sec": 1544839,
    "net_download": 9000,
    "net_upload": 9247,
    "traffic_users": 2038510710433,
    "traffic_node": 6025818305206,
    "users": 3
  },
  {
    "address": "EQBuFm_RWPBbmJ2rqxgsqGjjYwkwS10gLFOmoJesuLOmlhI9",
    "is_active": true,
    "node_registry": "EQDbPc6xGV6-nCmDH8bVXUdQCQ1tXMM062Xah-63HAMAkpq8",
    "owner": "EQA0ltvrkBHmBa0QSTNHcZSUNIvha1F6hTwCCMGPbyVPNpTq",
    "tickets_total": 140349,
    "tickets_30d": 39637,
    "ratings_total": 1,
    "ratings_30d": 1,
    "ratings_avg_stars": 5.0,
    "ratings_avg_stars_30d": 5.0,
    "plan": "time",
    "hostname": "lv.relay-apple.online",
    "country": "LV",
    "region": "Riga",
    "city": "Riga",
    "ip": "92.118.170.162",
    "exit_ip": null,
    "ssl": true,
    "check_port": 443,
    "api_port": 443,
    "api_path": "/api/v1",
    "public_key": "3d3be5b90790ba2b489c17615beb4e35bf2ec525c7c1d0914600e5a0617cff73",
    "node_id": 91811781698162,
    "scanned": "2026-06-27T21:58:44.244606Z",
    "heartbeat": "2026-06-27T21:57:46.702167Z",
    "health_check": "2026-06-27T21:54:08.430616Z",
    "version": "1.2.7",
    "uptime": 99,
    "limit": 100,
    "upload": 0,
    "download": 0,
    "disk": 36.23,
    "mem": 24.72,
    "cpu": 3.9603960866220103,
    "uptime_sec": 2630721,
    "net_download": 21473,
    "net_upload": 9694,
    "traffic_users": 1436720212861,
    "traffic_node": 6742990399510,
    "users": 2
  },
  {
    "address": "EQBqVxQmDa_yX6Ll_V7vuukQPDiTJhVt7Qa6jt-g-YbgaE6U",
    "is_active": true,
    "node_registry": "EQDbPc6xGV6-nCmDH8bVXUdQCQ1tXMM062Xah-63HAMAkpq8",
    "owner": "EQA0ltvrkBHmBa0QSTNHcZSUNIvha1F6hTwCCMGPbyVPNpTq",
    "tickets_total": 37671,
    "tickets_30d": 11269,
    "ratings_total": 0,
    "ratings_30d": 0,
    "ratings_avg_stars": 0.0,
    "ratings_avg_stars_30d": 0.0,
    "plan": "time",
    "hostname": "ekb.cdn-vk.run",
    "country": "RU",
    "region": "Sverdlovsk Oblast",
    "city": "Yekaterinburg",
    "ip": "45.11.27.161",
    "exit_ip": null,
    "ssl": true,
    "check_port": 443,
    "api_port": 443,
    "api_path": "/api/v1",
    "public_key": "8e502bc5aa8aaecd2162eb1ba28121d3bcd26b66e05c7cc9564f50e5103605b9",
    "node_id": 448108268161,
    "scanned": "2026-06-27T21:58:44.238802Z",
    "heartbeat": "2026-06-27T21:58:34.572134Z",
    "health_check": "2026-06-27T21:54:08.082656Z",
    "version": "1.2.7",
    "uptime": 99,
    "limit": 100,
    "upload": 0,
    "download": 0,
    "disk": 47.38,
    "mem": 47.14,
    "cpu": 3.0303031471815904,
    "uptime_sec": 49175,
    "net_download": 839515,
    "net_upload": 824837,
    "traffic_users": 902863230825,
    "traffic_node": 5826693705030,
    "users": 1
  },
  {
    "address": "EQBmkOJgIOA13bc8Rj4spCwCMqiabuSo1pnFtAPd5Ld1bYno",
    "is_active": true,
    "node_registry": "EQDbPc6xGV6-nCmDH8bVXUdQCQ1tXMM062Xah-63HAMAkpq8",
    "owner": "EQA0ltvrkBHmBa0QSTNHcZSUNIvha1F6hTwCCMGPbyVPNpTq",
    "tickets_total": 9975,
    "tickets_30d": 7265,
    "ratings_total": 0,
    "ratings_30d": 0,
    "ratings_avg_stars": 0.0,
    "ratings_avg_stars_30d": 0.0,
    "plan": "time",
    "hostname": "ph.media-cdn.online",
    "country": "PH",
    "region": "National Capital Region",
    "city": "Makati City",
    "ip": "61.245.10.36",
    "exit_ip": null,
    "ssl": true,
    "check_port": 443,
    "api_port": 443,
    "api_path": "/api/v1",
    "public_key": "563d8b95a7abbed4e30b13a66f5205caf3a1dd773c9d3d8da1ab6afe44024d92",
    "node_id": 608244809836,
    "scanned": "2026-06-27T21:58:44.232882Z",
    "heartbeat": "2026-06-27T21:58:43.290342Z",
    "health_check": "2026-06-27T21:54:09.953567Z",
    "version": "1.2.11",
    "uptime": 99,
    "limit": 100,
    "upload": 0,
    "download": 0,
    "disk": 56.98,
    "mem": 38.83,
    "cpu": 16.494845372702592,
    "uptime_sec": 2306709,
    "net_download": 1955826,
    "net_upload": 1679158,
    "traffic_users": 1115929754380,
    "traffic_node": 3156363162162,
    "users": 1
  },
  {
    "address": "EQBlby9LXxGbLz2XfW42iLo3899Os3uGxYVvw3KG5Vmk690s",
    "is_active": true,
    "node_registry": "EQDbPc6xGV6-nCmDH8bVXUdQCQ1tXMM062Xah-63HAMAkpq8",
    "owner": "EQA0ltvrkBHmBa0QSTNHcZSUNIvha1F6hTwCCMGPbyVPNpTq",
    "tickets_total": 1636,
    "tickets_30d": 196,
    "ratings_total": 0,
    "ratings_30d": 0,
    "ratings_avg_stars": 0.0,
    "ratings_avg_stars_30d": 0.0,
    "plan": "time",
    "hostname": "os.cdn-vk.run",
    "country": "RU",
    "region": "Moscow",
    "city": "Moscow",
    "ip": "194.87.57.104",
    "exit_ip": null,
    "ssl": true,
    "check_port": 443,
    "api_port": 443,
    "api_path": "/api/v1",
    "public_key": "c8626b746313a95da2a5e0a00c3e9e2219cd186a16fe4adc9c89b049cb1210ea",
    "node_id": 1938868568104,
    "scanned": "2026-06-27T21:58:44.225754Z",
    "heartbeat": "2026-06-27T21:58:24.968915Z",
    "health_check": "2026-06-27T21:54:07.909339Z",
    "version": "1.2.7",
    "uptime": 99,
    "limit": 100,
    "upload": 0,
    "download": 0,
    "disk": 84.06,
    "mem": 58.47,
    "cpu": 10.101010249246324,
    "uptime_sec": 1238910,
    "net_download": 1679651,
    "net_upload": 1609505,
    "traffic_users": 2684229926049,
    "traffic_node": 11518100399051,
    "users": 9
  },
  {
    "address": "EQBjKJ772islNaW9neRjsZIVAb8GVg4bhbbnH10NkqXs0lCi",
    "is_active": true,
    "node_registry": "EQDbPc6xGV6-nCmDH8bVXUdQCQ1tXMM062Xah-63HAMAkpq8",
    "owner": "EQA0ltvrkBHmBa0QSTNHcZSUNIvha1F6hTwCCMGPbyVPNpTq",
    "tickets_total": 5107,
    "tickets_30d": 2426,
    "ratings_total": 0,
    "ratings_30d": 0,
    "ratings_avg_stars": 0.0,
    "ratings_avg_stars_30d": 0.0,
    "plan": "time",
    "hostname": "host.cdn-vk.run",
    "country": "RU",
    "region": "Moscow",
    "city": "Moscow",
    "ip": "185.130.212.84",
    "exit_ip": null,
    "ssl": true,
    "check_port": 443,
    "api_port": 443,
    "api_path": "/api/v1",
    "public_key": "a3017d09a77cdd5ae7f4bd7f925e1c46afb6b7f5c85e1f5374d5ba1c1c69b8e5",
    "node_id": 18481298211884,
    "scanned": "2026-06-27T21:58:44.220418Z",
    "heartbeat": "2026-06-27T21:57:46.076186Z",
    "health_check": "2026-06-27T21:54:07.625158Z",
    "version": "1.2.11",
    "uptime": 100,
    "limit": 5,
    "upload": 0,
    "download": 0,
    "disk": 63.0,
    "mem": 35.97,
    "cpu": 0.9999999776482582,
    "uptime_sec": 2641888,
    "net_download": 120,
    "net_upload": 60,
    "traffic_users": 407478689316,
    "traffic_node": 2328031103978,
    "users": 0
  },
  {
    "address": "EQBiZHSojM6yzeBqo_Ka06ZauPtuR4nVPs9gqOVFL68BLEi9",
    "is_active": true,
    "node_registry": "EQDbPc6xGV6-nCmDH8bVXUdQCQ1tXMM062Xah-63HAMAkpq8",
    "owner": "EQA0ltvrkBHmBa0QSTNHcZSUNIvha1F6hTwCCMGPbyVPNpTq",
    "tickets_total": 57817,
    "tickets_30d": 36130,
    "ratings_total": 1,
    "ratings_30d": 0,
    "ratings_avg_stars": 5.0,
    "ratings_avg_stars_30d": 0.0,
    "plan": "time",
    "hostname": "us.yastatic.site",
    "country": "US",
    "region": "California",
    "city": "San Jose",
    "ip": "23.106.45.14",
    "exit_ip": null,
    "ssl": true,
    "check_port": 443,
    "api_port": 443,
    "api_path": "/api/v1",
    "public_key": "1e7c0f8cc0a4f9fe2f7cd3d2165e7684feb03ed9427208fb4a5050ecf97608d1",
    "node_id": 228105844814,
    "scanned": "2026-06-27T21:58:44.214737Z",
    "heartbeat": "2026-06-27T21:58:10.653103Z",
    "health_check": "2026-06-27T21:54:09.286256Z",
    "version": "1.2.7",
    "uptime": 99,
    "limit": 100,
    "upload": 0,
    "download": 0,
    "disk": 5.26,
    "mem": 9.32,
    "cpu": 0.24937650670922273,
    "uptime_sec": 4617549,
    "net_download": 1158,
    "net_upload": 902,
    "traffic_users": 14648559483298,
    "traffic_node": 35485801406008,
    "users": 1
  },
  {
    "address": "EQBfzVsVNKkJ7efRh8DJIfUKIeZmUJfreUSW989_ZSZa79cC",
    "is_active": true,
    "node_registry": "EQDbPc6xGV6-nCmDH8bVXUdQCQ1tXMM062Xah-63HAMAkpq8",
    "owner": "EQA0ltvrkBHmBa0QSTNHcZSUNIvha1F6hTwCCMGPbyVPNpTq",
    "tickets_total": 54027,
    "tickets_30d": 13500,
    "ratings_total": 0,
    "ratings_30d": 0,
    "ratings_avg_stars": 0.0,
    "ratings_avg_stars_30d": 0.0,
    "plan": "time",
    "hostname": "www.cdn-vk.run",
    "country": "FI",
    "region": "Uusimaa",
    "city": "Helsinki",
    "ip": "185.88.101.76",
    "exit_ip": null,
    "ssl": true,
    "check_port": 443,
    "api_port": 443,
    "api_path": "/api/v1",
    "public_key": "ddc79716c761d301bc2f31cb4b711eb7137d99d56b5ff27953cc58847c5d92fb",
    "node_id": 1848878100876,
    "scanned": "2026-06-27T21:58:44.203290Z",
    "heartbeat": "2026-06-27T21:58:04.491148Z",
    "health_check": "2026-06-27T21:54:07.305401Z",
    "version": "1.2.7",
    "uptime": 99,
    "limit": 100,
    "upload": 190,
    "download": 202,
    "disk": 35.43,
    "mem": 28.38,
    "cpu": 14.427860680150514,
    "uptime_sec": 1989132,
    "net_download": 554487,
    "net_upload": 530002,
    "traffic_users": 5809892836194,
    "traffic_node": 14148682998701,
    "users": 4
  },
  {
    "address": "EQBfM5S7Wnn6MMGMoLnmBK-LXWtLc2q1z7ippDR_ZrSEeBCd",
    "is_active": true,
    "node_registry": "EQDbPc6xGV6-nCmDH8bVXUdQCQ1tXMM062Xah-63HAMAkpq8",
    "owner": "EQA0ltvrkBHmBa0QSTNHcZSUNIvha1F6hTwCCMGPbyVPNpTq",
    "tickets_total": 8964,
    "tickets_30d": 2528,
    "ratings_total": 0,
    "ratings_30d": 0,
    "ratings_avg_stars": 0.0,
    "ratings_avg_stars_30d": 0.0,
    "plan": "time",
    "hostname": "k2.cdn-vk.run",
    "country": "RU",
    "region": "Kuzbass",
    "city": "Kemerovo",
    "ip": "77.110.112.98",
    "exit_ip": null,
    "ssl": true,
    "check_port": 443,
    "api_port": 443,
    "api_path": "/api/v1",
    "public_key": "0aad45e26613921a6122a8a83b2f1ce8209aa4ca9bcda8b2eaba1e351f1e05b9",
    "node_id": 7681098111898,
    "scanned": "2026-06-27T21:58:44.196062Z",
    "heartbeat": "2026-06-27T21:58:22.379368Z",
    "health_check": "2026-06-27T21:54:09.327811Z",
    "version": "1.2.7",
    "uptime": 99,
    "limit": 100,
    "upload": 0,
    "download": 0,
    "disk": 81.36,
    "mem": 30.86,
    "cpu": 0.9900990108139619,
    "uptime_sec": 588127,
    "net_download": 7918,
    "net_upload": 560,
    "traffic_users": 11739501323,
    "traffic_node": 749661699496,
    "users": 0
  },
  {
    "address": "EQBZC7OlRVv3KiL-vCEXWbjryAMk-OExcaPGp-cavU3ZytPT",
    "is_active": true,
    "node_registry": "EQDbPc6xGV6-nCmDH8bVXUdQCQ1tXMM062Xah-63HAMAkpq8",
    "owner": "EQA0ltvrkBHmBa0QSTNHcZSUNIvha1F6hTwCCMGPbyVPNpTq",
    "tickets_total": 22684,
    "tickets_30d": 12799,
    "ratings_total": 0,
    "ratings_30d": 0,
    "ratings_avg_stars": 0.0,
    "ratings_avg_stars_30d": 0.0,
    "plan": "time",
    "hostname": "au.media-cdn.online",
    "country": "DE",
    "region": "Hesse",
    "city": "Frankfurt am Main",
    "ip": "193.233.129.190",
    "exit_ip": null,
    "ssl": true,
    "check_port": 443,
    "api_port": 443,
    "api_path": "/api/v1",
    "public_key": "6a0ff3dee7047b1ce942f0c6547cce25edcb48e128c42f3e175f159507558bdd",
    "node_id": 192823281288190,
    "scanned": "2026-06-27T21:58:44.190343Z",
    "heartbeat": "2026-06-27T21:58:26.488652Z",
    "health_check": "2026-06-27T21:54:07.788491Z",
    "version": "1.2.11",
    "uptime": 99,
    "limit": 100,
    "upload": 0,
    "download": 0,
    "disk": 28.39,
    "mem": 15.09,
    "cpu": 0.0,
    "uptime_sec": 1101813,
    "net_download": 0,
    "net_upload": 0,
    "traffic_users": 706688862776,
    "traffic_node": 2553628860692,
    "users": 1
  },
  {
    "address": "EQBSQeJKxwFKaoeRmclry4iYzr3ymo8sPDEiaEF6G9snSAH0",
    "is_active": true,
    "node_registry": "EQDbPc6xGV6-nCmDH8bVXUdQCQ1tXMM062Xah-63HAMAkpq8",
    "owner": "EQA0ltvrkBHmBa0QSTNHcZSUNIvha1F6hTwCCMGPbyVPNpTq",
    "tickets_total": 6702,
    "tickets_30d": 2078,
    "ratings_total": 0,
    "ratings_30d": 0,
    "ratings_avg_stars": 0.0,
    "ratings_avg_stars_30d": 0.0,
    "plan": "time",
    "hostname": "deq.cdn-vk.rest",
    "country": "DE",
    "region": "Hesse",
    "city": "Frankfurt am Main",
    "ip": "5.61.41.115",
    "exit_ip": null,
    "ssl": true,
    "check_port": 443,
    "api_port": 443,
    "api_path": "/api/v1",
    "public_key": "3997593665976beb9d1058a44bd4034cdd812394f8c46736463d8854d58371bf",
    "node_id": 48608408115,
    "scanned": "2026-06-27T21:58:44.184848Z",
    "heartbeat": "2026-06-27T21:57:56.060102Z",
    "health_check": "2026-06-27T21:54:07.021925Z",
    "version": "1.2.11",
    "uptime": 99,
    "limit": 100,
    "upload": 0,
    "download": 0,
    "disk": 85.08,
    "mem": 15.65,
    "cpu": 8.910891076327305,
    "uptime_sec": 3097270,
    "net_download": 15905,
    "net_upload": 14727,
    "traffic_users": 2498877589512,
    "traffic_node": 5953350288566,
    "users": 1
  },
  {
    "address": "EQBRv1vDYL0fkotme954A8JLv9CxR6nfZYH6V6jHGsl_6szf",
    "is_active": true,
    "node_registry": "EQDbPc6xGV6-nCmDH8bVXUdQCQ1tXMM062Xah-63HAMAkpq8",
    "owner": "EQA0ltvrkBHmBa0QSTNHcZSUNIvha1F6hTwCCMGPbyVPNpTq",
    "tickets_total": 8698,
    "tickets_30d": 2327,
    "ratings_total": 0,
    "ratings_30d": 0,
    "ratings_avg_stars": 0.0,
    "ratings_avg_stars_30d": 0.0,
    "plan": "time",
    "hostname": "spbnl.cdn-vk.run",
    "country": "RU",
    "region": "St.-Petersburg",
    "city": "Saint Petersburg",
    "ip": "213.178.155.199",
    "exit_ip": null,
    "ssl": true,
    "check_port": 443,
    "api_port": 443,
    "api_path": "/api/v1",
    "public_key": "3b89f7cf27240c1d39ef37acff8f8ac238025e8704e29ac9d4d9418639185dc5",
    "node_id": 212817781548199,
    "scanned": "2026-06-27T21:58:44.178190Z",
    "heartbeat": "2026-06-27T21:58:15.297550Z",
    "health_check": "2026-06-27T21:54:07.814286Z",
    "version": "1.2.7",
    "uptime": 100,
    "limit": 100,
    "upload": 0,
    "download": 0,
    "disk": 65.36,
    "mem": 57.35,
    "cpu": 1.9999999552965164,
    "uptime_sec": 4625362,
    "net_download": 6804,
    "net_upload": 9973,
    "traffic_users": 225258277381,
    "traffic_node": 1513463012968,
    "users": 0
  },
  {
    "address": "EQBRE7je8hKmRKgp4HE8byhLtpgoJNwucGHowaAwYrD5F_JK",
    "is_active": true,
    "node_registry": "EQDbPc6xGV6-nCmDH8bVXUdQCQ1tXMM062Xah-63HAMAkpq8",
    "owner": "EQA0ltvrkBHmBa0QSTNHcZSUNIvha1F6hTwCCMGPbyVPNpTq",
    "tickets_total": 41931,
    "tickets_30d": 10339,
    "ratings_total": 0,
    "ratings_30d": 0,
    "ratings_avg_stars": 0.0,
    "ratings_avg_stars_30d": 0.0,
    "plan": "time",
    "hostname": "fin.cdn-vk.run",
    "country": "FI",
    "region": "Uusimaa",
    "city": "Helsinki",
    "ip": "31.56.204.94",
    "exit_ip": null,
    "ssl": true,
    "check_port": 443,
    "api_port": 443,
    "api_path": "/api/v1",
    "public_key": "0855ae5dea20161157948dc171d01ca5f616ec092a4d98bebeedce388e16ba99",
    "node_id": 308558203894,
    "scanned": "2026-06-27T21:58:44.168564Z",
    "heartbeat": "2026-06-27T21:58:19.191232Z",
    "health_check": "2026-06-27T21:54:07.189431Z",
    "version": "1.2.7",
    "uptime": 99,
    "limit": 100,
    "upload": 0,
    "download": 0,
    "disk": 41.72,
    "mem": 17.46,
    "cpu": 3.0303030442001764,
    "uptime_sec": 1076810,
    "net_download": 367717,
    "net_upload": 283576,
    "traffic_users": 1748457699655,
    "traffic_node": 5049101989958,
    "users": 2
  },
  {
    "address": "EQBJKbZTB3OzuAPeolc49ERDF4Drv_w5_MUI2ANJa2AJNI7H",
    "is_active": true,
    "node_registry": "EQDbPc6xGV6-nCmDH8bVXUdQCQ1tXMM062Xah-63HAMAkpq8",
    "owner": "EQA0ltvrkBHmBa0QSTNHcZSUNIvha1F6hTwCCMGPbyVPNpTq",
    "tickets_total": 32388,
    "tickets_30d": 21311,
    "ratings_total": 0,
    "ratings_30d": 0,
    "ratings_avg_stars": 0.0,
    "ratings_avg_stars_30d": 0.0,
    "plan": "time",
    "hostname": "cdn.edge-apple.online",
    "country": "NL",
    "region": "North Holland",
    "city": "Amsterdam",
    "ip": "45.15.129.41",
    "exit_ip": null,
    "ssl": true,
    "check_port": 443,
    "api_port": 443,
    "api_path": "/api/v1",
    "public_key": "4cefaf69d789192f4cc2c1546cdcde5890233c26ded70748922d4e895f419923",
    "node_id": 448148128841,
    "scanned": "2026-06-27T21:58:44.159546Z",
    "heartbeat": "2026-06-02T11:57:24.601699Z",
    "health_check": "2026-06-02T12:12:28.821653Z",
    "version": "1.2.7",
    "uptime": 99,
    "limit": 100,
    "upload": 0,
    "download": 0,
    "disk": 28.35,
    "mem": 68.62,
    "cpu": 32.67326735731723,
    "uptime_sec": 10538,
    "net_download": 1948840,
    "net_upload": 2394389,
    "traffic_users": 6970055836163,
    "traffic_node": 16896049230346,
    "users": 38
  },
  {
    "address": "EQBI4cSVPL6Bp5SyYL1vjEKuQFETRo3ewcXInmHke7qiYuKE",
    "is_active": true,
    "node_registry": "EQDbPc6xGV6-nCmDH8bVXUdQCQ1tXMM062Xah-63HAMAkpq8",
    "owner": "EQA0ltvrkBHmBa0QSTNHcZSUNIvha1F6hTwCCMGPbyVPNpTq",
    "tickets_total": 10884,
    "tickets_30d": 1177,
    "ratings_total": 0,
    "ratings_30d": 0,
    "ratings_avg_stars": 0.0,
    "ratings_avg_stars_30d": 0.0,
    "plan": "time",
    "hostname": "nl.yastatic.run",
    "country": "NL",
    "region": "Flevoland",
    "city": "Dronten",
    "ip": "195.93.244.178",
    "exit_ip": null,
    "ssl": true,
    "check_port": 443,
    "api_port": 443,
    "api_path": "/api/v1",
    "public_key": "3aa0235784fa2be34e5e6517273b8a07f519bb9320e2534533044a78e5d1c19f",
    "node_id": 19489282438178,
    "scanned": "2026-06-27T21:58:44.146991Z",
    "heartbeat": "2026-06-27T21:58:18.143961Z",
    "health_check": "2026-06-27T21:54:07.313507Z",
    "version": "1.2.11",
    "uptime": 99,
    "limit": 100,
    "upload": 0,
    "download": 0,
    "disk": 30.58,
    "mem": 19.45,
    "cpu": 7.211538462399522,
    "uptime_sec": 106038,
    "net_download": 30441,
    "net_upload": 10892,
    "traffic_users": 122443337473,
    "traffic_node": 394353625046,
    "users": 1
  },
  {
    "address": "EQBDGon7vbR_yN8H__V3bFFcFX5_8WAgk-fX3dsIKT8JhWtM",
    "is_active": true,
    "node_registry": "EQDbPc6xGV6-nCmDH8bVXUdQCQ1tXMM062Xah-63HAMAkpq8",
    "owner": "EQA0ltvrkBHmBa0QSTNHcZSUNIvha1F6hTwCCMGPbyVPNpTq",
    "tickets_total": 29266,
    "tickets_30d": 10671,
    "ratings_total": 1,
    "ratings_30d": 1,
    "ratings_avg_stars": 5.0,
    "ratings_avg_stars_30d": 5.0,
    "plan": "time",
    "hostname": "de.cdn-vk.run",
    "country": "DE",
    "region": "Hesse",
    "city": "Frankfurt am Main",
    "ip": "212.95.33.169",
    "exit_ip": null,
    "ssl": true,
    "check_port": 443,
    "api_port": 443,
    "api_path": "/api/v1",
    "public_key": "8880b7834449f8b81b60252e82b973e3a3dad8f5774f0c3cdf363df4a4243e3e",
    "node_id": 2118948328169,
    "scanned": "2026-06-27T21:58:44.136236Z",
    "heartbeat": "2026-06-27T21:58:15.403880Z",
    "health_check": "2026-06-27T21:54:07.513045Z",
    "version": "1.2.7",
    "uptime": 99,
    "limit": 100,
    "upload": 0,
    "download": 0,
    "disk": 6.76,
    "mem": 7.72,
    "cpu": 0.0,
    "uptime_sec": 4617366,
    "net_download": 4880,
    "net_upload": 4789,
    "traffic_users": 3580815526578,
    "traffic_node": 9097470139688,
    "users": 2
  },
  {
    "address": "EQB6zQMIpcm4ONWHyhh_7XxZS9DlsODavLxwT2H0wYXlD6CP",
    "is_active": true,
    "node_registry": "EQDbPc6xGV6-nCmDH8bVXUdQCQ1tXMM062Xah-63HAMAkpq8",
    "owner": "EQA0ltvrkBHmBa0QSTNHcZSUNIvha1F6hTwCCMGPbyVPNpTq",
    "tickets_total": 31858,
    "tickets_30d": 17082,
    "ratings_total": 0,
    "ratings_30d": 0,
    "ratings_avg_stars": 0.0,
    "ratings_avg_stars_30d": 0.0,
    "plan": "time",
    "hostname": "kr.yastatic.run",
    "country": "RU",
    "region": "Krasnodar Krai",
    "city": "Krasnodar",
    "ip": "193.124.121.96",
    "exit_ip": null,
    "ssl": true,
    "check_port": 443,
    "api_port": 443,
    "api_path": "/api/v1",
    "public_key": "a8cefb8309764313673d8868179c49dbdb1e03252a7a876968abf2b4ea047a0a",
    "node_id": 19281238120896,
    "scanned": "2026-06-27T21:58:44.127584Z",
    "heartbeat": "2026-06-27T21:57:32.885842Z",
    "health_check": "2026-06-27T21:54:11.355383Z",
    "version": "1.2.7",
    "uptime": 99,
    "limit": 100,
    "upload": 0,
    "download": 0,
    "disk": 47.15,
    "mem": 67.98,
    "cpu": 3.0612244895496996,
    "uptime_sec": 356,
    "net_download": 20399,
    "net_upload": 22584,
    "traffic_users": 158018177021,
    "traffic_node": 3099786709290,
    "users": 0
  },
  {
    "address": "EQB5Xy4t1Ntsecb6CSgGByWfqYnPn6cqN16R1tSVgrdQgu5e",
    "is_active": true,
    "node_registry": "EQDbPc6xGV6-nCmDH8bVXUdQCQ1tXMM062Xah-63HAMAkpq8",
    "owner": "EQA0ltvrkBHmBa0QSTNHcZSUNIvha1F6hTwCCMGPbyVPNpTq",
    "tickets_total": 31074,
    "tickets_30d": 19137,
    "ratings_total": 0,
    "ratings_30d": 0,
    "ratings_avg_stars": 0.0,
    "ratings_avg_stars_30d": 0.0,
    "plan": "time",
    "hostname": "ru.yastatic.run",
    "country": "RU",
    "region": "Moscow Oblast",
    "city": "Korolev",
    "ip": "195.133.146.211",
    "exit_ip": null,
    "ssl": true,
    "check_port": 443,
    "api_port": 443,
    "api_path": "/api/v1",
    "public_key": "1d6c45e833ca03cf9765c4f98380d96e9d4812822a25e366b2c437a870715d26",
    "node_id": 194813281458211,
    "scanned": "2026-06-27T21:58:44.115347Z",
    "heartbeat": "2026-06-06T06:51:58.971557Z",
    "health_check": "2026-06-06T07:01:16.781390Z",
    "version": "1.2.7",
    "uptime": 97,
    "limit": 100,
    "upload": 0,
    "download": 0,
    "disk": 60.88,
    "mem": 52.64,
    "cpu": 5.050505077586668,
    "uptime_sec": 144627,
    "net_download": 7480,
    "net_upload": 8340,
    "traffic_users": 854001738532,
    "traffic_node": 5871632596080,
    "users": 0
  },
  {
    "address": "EQB2RQBZGpJocyFl8KAkvuVIkK7JFjnYHX0D6c9ISJk5WAWo",
    "is_active": true,
    "node_registry": "EQDbPc6xGV6-nCmDH8bVXUdQCQ1tXMM062Xah-63HAMAkpq8",
    "owner": "EQA0ltvrkBHmBa0QSTNHcZSUNIvha1F6hTwCCMGPbyVPNpTq",
    "tickets_total": 15682,
    "tickets_30d": 3249,
    "ratings_total": 0,
    "ratings_30d": 0,
    "ratings_avg_stars": 0.0,
    "ratings_avg_stars_30d": 0.0,
    "plan": "time",
    "hostname": "nov.media-cdn.online",
    "country": "RU",
    "region": "Novosibirsk Oblast",
    "city": "Novosibirsk",
    "ip": "194.87.213.185",
    "exit_ip": null,
    "ssl": true,
    "check_port": 443,
    "api_port": 443,
    "api_path": "/api/v1",
    "public_key": "2763286777beb9092b6dd0a65161e3c35e5b058bc61b7177ea4b26e459eae96e",
    "node_id": 19388682128185,
    "scanned": "2026-06-27T21:58:44.109065Z",
    "heartbeat": "2026-06-27T21:57:56.770300Z",
    "health_check": "2026-06-27T21:54:08.362529Z",
    "version": "1.2.7",
    "uptime": 99,
    "limit": 100,
    "upload": 0,
    "download": 0,
    "disk": 46.63,
    "mem": 45.18,
    "cpu": 1.980197975979332,
    "uptime_sec": 107079,
    "net_download": 105,
    "net_upload": 171,
    "traffic_users": 146930463165,
    "traffic_node": 1268416414549,
    "users": 0
  },
  {
    "address": "EQB1MZdNK7EazQA5daPCcxtvE44FxQOO9hSlSIg0CMfq6WIW",
    "is_active": true,
    "node_registry": "EQDbPc6xGV6-nCmDH8bVXUdQCQ1tXMM062Xah-63HAMAkpq8",
    "owner": "EQA0ltvrkBHmBa0QSTNHcZSUNIvha1F6hTwCCMGPbyVPNpTq",
    "tickets_total": 24527,
    "tickets_30d": 6258,
    "ratings_total": 0,
    "ratings_30d": 0,
    "ratings_avg_stars": 0.0,
    "ratings_avg_stars_30d": 0.0,
    "plan": "time",
    "hostname": "it.cdn-vk.run",
    "country": "RU",
    "region": "Tatarstan Republic",
    "city": "Kazan",
    "ip": "213.226.112.65",
    "exit_ip": null,
    "ssl": true,
    "check_port": 443,
    "api_port": 443,
    "api_path": "/api/v1",
    "public_key": "bcb46722f795e38503620dd4f470c29a24b66931ceae4d3abc72c4e210a0c7df",
    "node_id": 21282258111865,
    "scanned": "2026-06-27T21:58:44.103211Z",
    "heartbeat": "2026-06-27T21:58:07.255037Z",
    "health_check": "2026-06-27T21:54:08.260890Z",
    "version": "1.2.10",
    "uptime": 100,
    "limit": 100,
    "upload": 0,
    "download": 0,
    "disk": 48.86,
    "mem": 55.72,
    "cpu": 0.0,
    "uptime_sec": 356980,
    "net_download": 120,
    "net_upload": 54,
    "traffic_users": 520094131006,
    "traffic_node": 3282282631532,
    "users": 0
  },
  {
    "address": "EQAn7n9YreZRYLTUcPNHI3hIZU8QuQaVhi5q7IYGHOc9r_V2",
    "is_active": true,
    "node_registry": "EQDbPc6xGV6-nCmDH8bVXUdQCQ1tXMM062Xah-63HAMAkpq8",
    "owner": "EQA0ltvrkBHmBa0QSTNHcZSUNIvha1F6hTwCCMGPbyVPNpTq",
    "tickets_total": 92851,
    "tickets_30d": 26712,
    "ratings_total": 4,
    "ratings_30d": 1,
    "ratings_avg_stars": 4.5,
    "ratings_avg_stars_30d": 5.0,
    "plan": "time",
    "hostname": "se.relay-apple.online",
    "country": "SE",
    "region": "Stockholm",
    "city": "Stockholm",
    "ip": "138.124.84.49",
    "exit_ip": null,
    "ssl": true,
    "check_port": 443,
    "api_port": 443,
    "api_path": "/api/v1",
    "public_key": "d75a8a6f44f47a99e304d7f878cc94a5fd12b14456d22f18ec427353ec323b34",
    "node_id": 1378123883849,
    "scanned": "2026-06-27T21:58:44.096912Z",
    "heartbeat": "2026-06-27T21:57:32.458564Z",
    "health_check": "2026-06-27T21:54:07.175535Z",
    "version": "1.2.7",
    "uptime": 99,
    "limit": 80,
    "upload": 0,
    "download": 0,
    "disk": 37.02,
    "mem": 26.88,
    "cpu": 8.585858627193685,
    "uptime_sec": 3327544,
    "net_download": 62186,
    "net_upload": 17700,
    "traffic_users": 1966620843786,
    "traffic_node": 6871756268763,
    "users": 6
  },
  {
    "address": "EQAlr2DsKzSMsO-ADlPqJVOv5GRGb0iKw0nWKpBnym4sz-hS",
    "is_active": true,
    "node_registry": "EQDbPc6xGV6-nCmDH8bVXUdQCQ1tXMM062Xah-63HAMAkpq8",
    "owner": "EQA0ltvrkBHmBa0QSTNHcZSUNIvha1F6hTwCCMGPbyVPNpTq",
    "tickets_total": 130597,
    "tickets_30d": 38630,
    "ratings_total": 3,
    "ratings_30d": 3,
    "ratings_avg_stars": 5.0,
    "ratings_avg_stars_30d": 5.0,
    "plan": "time",
    "hostname": "ee.edge-apple.online",
    "country": "EE",
    "region": "Harjumaa",
    "city": "Tallinn",
    "ip": "23.230.179.233",
    "exit_ip": null,
    "ssl": true,
    "check_port": 443,
    "api_port": 443,
    "api_path": "/api/v1",
    "public_key": "6fb38fe7144ce1efc7086c54769db78be42ab0e5d301065f1c81148c65218159",
    "node_id": 22822981788233,
    "scanned": "2026-06-27T21:58:44.089831Z",
    "heartbeat": "2026-06-27T21:58:42.389989Z",
    "health_check": "2026-06-27T21:54:07.201549Z",
    "version": "1.2.7",
    "uptime": 99,
    "limit": 100,
    "upload": 0,
    "download": 0,
    "disk": 38.62,
    "mem": 25.75,
    "cpu": 1.5075377013769202,
    "uptime_sec": 2762757,
    "net_download": 2383,
    "net_upload": 3185,
    "traffic_users": 2387247414184,
    "traffic_node": 9951038207065,
    "users": 5
  },
  {
    "address": "EQAklR_7ov3Sz7VSYMFs-_83JylG3pdxM1OQAeayohAeuYmy",
    "is_active": true,
    "node_registry": "EQDbPc6xGV6-nCmDH8bVXUdQCQ1tXMM062Xah-63HAMAkpq8",
    "owner": "EQA0ltvrkBHmBa0QSTNHcZSUNIvha1F6hTwCCMGPbyVPNpTq",
    "tickets_total": 27203,
    "tickets_30d": 13360,
    "ratings_total": 0,
    "ratings_30d": 0,
    "ratings_avg_stars": 0.0,
    "ratings_avg_stars_30d": 0.0,
    "plan": "time",
    "hostname": "cloud.cdn-vk.run",
    "country": "RU",
    "region": "Moscow Oblast",
    "city": "Korolev",
    "ip": "195.133.146.74",
    "exit_ip": null,
    "ssl": true,
    "check_port": 443,
    "api_port": 443,
    "api_path": "/api/v1",
    "public_key": "d8e3b8704806ce095628fbf133cbfc37b57b45dad1bc238bb93368dd107d3ce0",
    "node_id": 19481328145874,
    "scanned": "2026-06-27T21:58:44.083653Z",
    "heartbeat": "2026-06-27T21:57:56.722345Z",
    "health_check": "2026-06-27T21:54:07.446461Z",
    "version": "1.2.7",
    "uptime": 100,
    "limit": 100,
    "upload": 0,
    "download": 0,
    "disk": 49.53,
    "mem": 41.17,
    "cpu": 0.9999999776482582,
    "uptime_sec": 125164,
    "net_download": 1145,
    "net_upload": 1211,
    "traffic_users": 205735804576,
    "traffic_node": 2490139211592,
    "users": 0
  },
  {
    "address": "EQAiqQCtVfHR1u8FpXMrb_BP5K9W7d8uZhEPGmwG9qd5fEAo",
    "is_active": true,
    "node_registry": "EQDbPc6xGV6-nCmDH8bVXUdQCQ1tXMM062Xah-63HAMAkpq8",
    "owner": "EQA0ltvrkBHmBa0QSTNHcZSUNIvha1F6hTwCCMGPbyVPNpTq",
    "tickets_total": 30977,
    "tickets_30d": 6311,
    "ratings_total": 0,
    "ratings_30d": 0,
    "ratings_avg_stars": 0.0,
    "ratings_avg_stars_30d": 0.0,
    "plan": "time",
    "hostname": "ek.cdn-vk.run",
    "country": "RU",
    "region": "Sverdlovsk Oblast",
    "city": "Yekaterinburg",
    "ip": "45.11.27.93",
    "exit_ip": null,
    "ssl": true,
    "check_port": 443,
    "api_port": 443,
    "api_path": "/api/v1",
    "public_key": "28a814326caec0cea681de85b4ade2a2ac99322ed99f5d171f8023f17916c20b",
    "node_id": 44810826893,
    "scanned": "2026-06-27T21:58:44.074190Z",
    "heartbeat": "2026-06-27T21:58:07.429821Z",
    "health_check": "2026-06-27T21:54:07.828190Z",
    "version": "1.2.7",
    "uptime": 99,
    "limit": 100,
    "upload": 0,
    "download": 0,
    "disk": 47.7,
    "mem": 48.06,
    "cpu": 4.00000000372529,
    "uptime_sec": 367232,
    "net_download": 55311,
    "net_upload": 29281,
    "traffic_users": 1677659921130,
    "traffic_node": 8700687537108,
    "users": 2
  },
  {
    "address": "EQAhzt3V7Ng5LZyQdx8LKs3ei5W2yKU5mNlEzOw5KN4PlGt7",
    "is_active": true,
    "node_registry": "EQDbPc6xGV6-nCmDH8bVXUdQCQ1tXMM062Xah-63HAMAkpq8",
    "owner": "EQA0ltvrkBHmBa0QSTNHcZSUNIvha1F6hTwCCMGPbyVPNpTq",
    "tickets_total": 24567,
    "tickets_30d": 15701,
    "ratings_total": 1,
    "ratings_30d": 1,
    "ratings_avg_stars": 5.0,
    "ratings_avg_stars_30d": 5.0,
    "plan": "time",
    "hostname": "ca.yastatic.site",
    "country": "CA",
    "region": "Quebec",
    "city": "Montr\u00e9al",
    "ip": "184.107.179.25",
    "exit_ip": null,
    "ssl": true,
    "check_port": 443,
    "api_port": 443,
    "api_path": "/api/v1",
    "public_key": "b01d259434de07393001ffd7d1b67e3181e191b29eb339f3dea5d660c0e8105b",
    "node_id": 18381068178825,
    "scanned": "2026-06-27T21:58:44.066068Z",
    "heartbeat": "2026-06-27T21:58:07.772265Z",
    "health_check": "2026-06-27T21:54:07.673124Z",
    "version": "1.2.11",
    "uptime": 99,
    "limit": 100,
    "upload": 0,
    "download": 0,
    "disk": 5.22,
    "mem": 7.43,
    "cpu": 0.0,
    "uptime_sec": 3099487,
    "net_download": 53492,
    "net_upload": 4952,
    "traffic_users": 4478124860417,
    "traffic_node": 11193887068362,
    "users": 0
  },
  {
    "address": "EQAfwxqts_LkQ-sz-yHPHgZ2hOGIvUUmA9o28M53aaq0Yq54",
    "is_active": true,
    "node_registry": "EQDbPc6xGV6-nCmDH8bVXUdQCQ1tXMM062Xah-63HAMAkpq8",
    "owner": "EQA0ltvrkBHmBa0QSTNHcZSUNIvha1F6hTwCCMGPbyVPNpTq",
    "tickets_total": 8728,
    "tickets_30d": 5034,
    "ratings_total": 1,
    "ratings_30d": 0,
    "ratings_avg_stars": 5.0,
    "ratings_avg_stars_30d": 0.0,
    "plan": "time",
    "hostname": "get.yastatic.site",
    "country": "TH",
    "region": "Bangkok",
    "city": "Bangkok",
    "ip": "165.101.64.91",
    "exit_ip": null,
    "ssl": true,
    "check_port": 443,
    "api_port": 443,
    "api_path": "/api/v1",
    "public_key": "95a655617b2552968eca587046418cd883dc8bad43658d333c8cb5de7b31d324",
    "node_id": 1648100863891,
    "scanned": "2026-06-27T21:58:44.057092Z",
    "heartbeat": "2026-06-12T07:01:37.172810Z",
    "health_check": "2026-06-12T07:10:52.163228Z",
    "version": "1.2.11",
    "uptime": 90,
    "limit": 100,
    "upload": 239,
    "download": 672,
    "disk": 55.87,
    "mem": 44.81,
    "cpu": 0.9999999795109034,
    "uptime_sec": 1749692,
    "net_download": 19900,
    "net_upload": 18176,
    "traffic_users": 1341079523194,
    "traffic_node": 3582334890365,
    "users": 2
  },
  {
    "address": "EQAchHEeIMxdV2V3eV5LCgMvIkD626XCsszEcz34XyTdVB3A",
    "is_active": true,
    "node_registry": "EQDbPc6xGV6-nCmDH8bVXUdQCQ1tXMM062Xah-63HAMAkpq8",
    "owner": "EQA0ltvrkBHmBa0QSTNHcZSUNIvha1F6hTwCCMGPbyVPNpTq",
    "tickets_total": 5792,
    "tickets_30d": 3693,
    "ratings_total": 0,
    "ratings_30d": 0,
    "ratings_avg_stars": 0.0,
    "ratings_avg_stars_30d": 0.0,
    "plan": "time",
    "hostname": "ca.cdn-vk.rest",
    "country": "CA",
    "region": "Quebec",
    "city": "Montr\u00e9al",
    "ip": "68.71.45.152",
    "exit_ip": null,
    "ssl": true,
    "check_port": 443,
    "api_port": 443,
    "api_path": "/api/v1",
    "public_key": "7c465c1ca9dbc6d968694a74fd4ad177077a28506893adf98b8015fd652ec4d5",
    "node_id": 678708448152,
    "scanned": "2026-06-27T21:58:44.047319Z",
    "heartbeat": "2026-06-27T21:58:06.402658Z",
    "health_check": "2026-06-27T21:54:08.733477Z",
    "version": "1.2.11",
    "uptime": 99,
    "limit": 100,
    "upload": 0,
    "download": 0,
    "disk": 78.03,
    "mem": 16.42,
    "cpu": 6.93069309395717,
    "uptime_sec": 3097310,
    "net_download": 2281197,
    "net_upload": 2292857,
    "traffic_users": 1529249034569,
    "traffic_node": 3948998109103,
    "users": 1
  },
  {
    "address": "EQAZdBrzhtrQfAdMdIg1fXUef8j0SSf7oWlcJeAKw1jSxKts",
    "is_active": true,
    "node_registry": "EQDbPc6xGV6-nCmDH8bVXUdQCQ1tXMM062Xah-63HAMAkpq8",
    "owner": "EQA0ltvrkBHmBa0QSTNHcZSUNIvha1F6hTwCCMGPbyVPNpTq",
    "tickets_total": 15492,
    "tickets_30d": 8618,
    "ratings_total": 0,
    "ratings_30d": 0,
    "ratings_avg_stars": 0.0,
    "ratings_avg_stars_30d": 0.0,
    "plan": "time",
    "hostname": "jp.yastatic.site",
    "country": "JP",
    "region": "Tokyo",
    "city": "Tokyo",
    "ip": "142.91.109.126",
    "exit_ip": null,
    "ssl": true,
    "check_port": 443,
    "api_port": 443,
    "api_path": "/api/v1",
    "public_key": "abe7507075772510ce0abefeac25cae4401401c6a8512f6fad72dfbfe8fe3707",
    "node_id": 14189081088126,
    "scanned": "2026-06-27T21:58:44.038033Z",
    "heartbeat": "2026-06-27T21:57:42.398672Z",
    "health_check": "2026-06-27T21:54:10.227232Z",
    "version": "1.2.11",
    "uptime": 99,
    "limit": 100,
    "upload": 0,
    "download": 0,
    "disk": 5.2,
    "mem": 7.69,
    "cpu": 0.7518797287320166,
    "uptime_sec": 3099459,
    "net_download": 128639,
    "net_upload": 32114,
    "traffic_users": 1834552420895,
    "traffic_node": 4965328979865,
    "users": 0
  },
  {
    "address": "EQAWdcYsjSA8ZEM1FhvFocz0NNEX_4O3yqiaS7p2oPAi0j4q",
    "is_active": true,
    "node_registry": "EQDbPc6xGV6-nCmDH8bVXUdQCQ1tXMM062Xah-63HAMAkpq8",
    "owner": "EQA0ltvrkBHmBa0QSTNHcZSUNIvha1F6hTwCCMGPbyVPNpTq",
    "tickets_total": 14546,
    "tickets_30d": 1776,
    "ratings_total": 4,
    "ratings_30d": 0,
    "ratings_avg_stars": 4.25,
    "ratings_avg_stars_30d": 0.0,
    "plan": "time",
    "hostname": "eu.yastatic.run",
    "country": "NL",
    "region": "Flevoland",
    "city": "Dronten",
    "ip": "212.87.223.232",
    "exit_ip": null,
    "ssl": true,
    "check_port": 443,
    "api_port": 443,
    "api_path": "/api/v1",
    "public_key": "452814d87e05f130d11c100a328a7ae08db3beb61d0993bdf8c7311a1bc43397",
    "node_id": 21188682228232,
    "scanned": "2026-06-27T21:58:44.029837Z",
    "heartbeat": "2026-06-27T21:58:29.565872Z",
    "health_check": "2026-06-27T21:54:14.856563Z",
    "version": "1.2.7",
    "uptime": 98,
    "limit": 100,
    "upload": 0,
    "download": 0,
    "disk": 30.41,
    "mem": 17.15,
    "cpu": 1.4999999956635293,
    "uptime_sec": 105999,
    "net_download": 4169849,
    "net_upload": 2526836,
    "traffic_users": 100174557232,
    "traffic_node": 408116739200,
    "users": 2
  },
  {
    "address": "EQALo8Rmy6nva0quulLFQzZDKo_SYIrmotQkAtbJWpu8kJVv",
    "is_active": true,
    "node_registry": "EQDbPc6xGV6-nCmDH8bVXUdQCQ1tXMM062Xah-63HAMAkpq8",
    "owner": "EQA0ltvrkBHmBa0QSTNHcZSUNIvha1F6hTwCCMGPbyVPNpTq",
    "tickets_total": 9429,
    "tickets_30d": 2366,
    "ratings_total": 0,
    "ratings_30d": 0,
    "ratings_avg_stars": 0.0,
    "ratings_avg_stars_30d": 0.0,
    "plan": "time",
    "hostname": "m9.cdn-vk.run",
    "country": "RU",
    "region": "Moscow",
    "city": "Moscow",
    "ip": "194.87.207.232",
    "exit_ip": null,
    "ssl": true,
    "check_port": 443,
    "api_port": 443,
    "api_path": "/api/v1",
    "public_key": "ed9dc4e1207d42e75c379d987a3968a747f38f951754aa7d09472e56de837f1a",
    "node_id": 19388682068232,
    "scanned": "2026-06-27T21:58:44.023600Z",
    "heartbeat": "2026-06-27T21:58:27.290472Z",
    "health_check": "2026-06-27T21:54:08.382109Z",
    "version": "1.2.7",
    "uptime": 100,
    "limit": 100,
    "upload": 0,
    "download": 0,
    "disk": 48.49,
    "mem": 50.36,
    "cpu": 2.0202020686638624,
    "uptime_sec": 4610012,
    "net_download": 97899,
    "net_upload": 57248,
    "traffic_users": 102838039862,
    "traffic_node": 989672751443,
    "users": 0
  },
  {
    "address": "EQAIdINT1SJWqJ4I7ISaeEaYN6dp2q5ORt0VQZlCPlwjYJyz",
    "is_active": true,
    "node_registry": "EQDbPc6xGV6-nCmDH8bVXUdQCQ1tXMM062Xah-63HAMAkpq8",
    "owner": "EQA0ltvrkBHmBa0QSTNHcZSUNIvha1F6hTwCCMGPbyVPNpTq",
    "tickets_total": 14200,
    "tickets_30d": 4403,
    "ratings_total": 0,
    "ratings_30d": 0,
    "ratings_avg_stars": 0.0,
    "ratings_avg_stars_30d": 0.0,
    "plan": "time",
    "hostname": "msk.media-cdn.online",
    "country": "RU",
    "region": "Moscow",
    "city": "Moscow",
    "ip": "150.241.85.124",
    "exit_ip": null,
    "ssl": true,
    "check_port": 443,
    "api_port": 443,
    "api_path": "/api/v1",
    "public_key": "a26d906f82cd4ff5a270dbd3694cd1e5f9485c5636d862ca90b39be4f7f88f12",
    "node_id": 14982408848124,
    "scanned": "2026-06-27T21:58:44.016193Z",
    "heartbeat": "2026-06-27T21:58:29.902101Z",
    "health_check": "2026-06-27T21:53:06.326291Z",
    "version": "1.2.7",
    "uptime": 99,
    "limit": 100,
    "upload": 0,
    "download": 0,
    "disk": 21.24,
    "mem": 20.74,
    "cpu": 0.0,
    "uptime_sec": 3093718,
    "net_download": 293,
    "net_upload": 0,
    "traffic_users": 256789644945,
    "traffic_node": 1666607553496,
    "users": 0
  },
  {
    "address": "EQAAcXmsodmvyT2e8nMcSjKWAXEEuJDkktkm-9ZMtIy0E7E1",
    "is_active": true,
    "node_registry": "EQDbPc6xGV6-nCmDH8bVXUdQCQ1tXMM062Xah-63HAMAkpq8",
    "owner": "EQA0ltvrkBHmBa0QSTNHcZSUNIvha1F6hTwCCMGPbyVPNpTq",
    "tickets_total": 37538,
    "tickets_30d": 12660,
    "ratings_total": 0,
    "ratings_30d": 0,
    "ratings_avg_stars": 0.0,
    "ratings_avg_stars_30d": 0.0,
    "plan": "time",
    "hostname": "nova.cdn-vk.rest",
    "country": "RU",
    "region": "Orenburgskaya oblast'",
    "city": "\u041a\u0438\u0440\u043f\u0438\u0447\u043d\u044b\u0439 \u0417\u0430\u0432\u043e\u0434",
    "ip": "193.233.49.42",
    "exit_ip": null,
    "ssl": true,
    "check_port": 443,
    "api_port": 443,
    "api_path": "/api/v1",
    "public_key": "a94dc7165eff460ce70317691314364b9fc718f5c17df9bcb091937697c3156a",
    "node_id": 1928232848842,
    "scanned": "2026-06-27T21:58:44.006666Z",
    "heartbeat": "2026-06-27T21:57:51.922375Z",
    "health_check": "2026-06-27T21:54:08.986149Z",
    "version": "1.2.5",
    "uptime": 99,
    "limit": 30,
    "upload": 0,
    "download": 0,
    "disk": 56.7,
    "mem": 21.09,
    "cpu": 7.070707011792675,
    "uptime_sec": 4539137,
    "net_download": 12383,
    "net_upload": 7632,
    "traffic_users": 1620599641624,
    "traffic_node": 8707792944967,
    "users": 0
  },
  {
    "address": "EQA7s3Php7TJS__Y71xns5QSEqt54rtuMC9_Tg50eN4AUFnd",
    "is_active": true,
    "node_registry": "EQDbPc6xGV6-nCmDH8bVXUdQCQ1tXMM062Xah-63HAMAkpq8",
    "owner": "EQA0ltvrkBHmBa0QSTNHcZSUNIvha1F6hTwCCMGPbyVPNpTq",
    "tickets_total": 38391,
    "tickets_30d": 12569,
    "ratings_total": 1,
    "ratings_30d": 0,
    "ratings_avg_stars": 4.0,
    "ratings_avg_stars_30d": 0.0,
    "plan": "time",
    "hostname": "eu.cdn-vk.run",
    "country": "FR",
    "region": "Grand Est",
    "city": "Lauterbourg",
    "ip": "62.169.29.73",
    "exit_ip": null,
    "ssl": true,
    "check_port": 443,
    "api_port": 443,
    "api_path": "/api/v1",
    "public_key": "c7f6b5ef5cc09c29c1befeeeccb4db052a5234a595286584d416ddee69a850b3",
    "node_id": 618168828873,
    "scanned": "2026-06-27T21:58:43.994712Z",
    "heartbeat": "2026-06-27T21:58:44.122956Z",
    "health_check": "2026-06-27T21:54:08.093314Z",
    "version": "1.2.11",
    "uptime": 99,
    "limit": 100,
    "upload": 0,
    "download": 0,
    "disk": 10.8,
    "mem": 5.76,
    "cpu": 0.24937650670922273,
    "uptime_sec": 3098495,
    "net_download": 86,
    "net_upload": 196,
    "traffic_users": 427803339048,
    "traffic_node": 1774309852826,
    "users": 1
  },
  {
    "address": "EQA-YJB0ILq3Te7Ss9MZW9eKPvVeoPrHAYBOtkQWNuV7q_ae",
    "is_active": true,
    "node_registry": "EQDbPc6xGV6-nCmDH8bVXUdQCQ1tXMM062Xah-63HAMAkpq8",
    "owner": "EQA0ltvrkBHmBa0QSTNHcZSUNIvha1F6hTwCCMGPbyVPNpTq",
    "tickets_total": 24123,
    "tickets_30d": 10511,
    "ratings_total": 31,
    "ratings_30d": 0,
    "ratings_avg_stars": 4.77,
    "ratings_avg_stars_30d": 0.0,
    "plan": "time",
    "hostname": "sg.yastatic.site",
    "country": "SG",
    "region": "Singapore",
    "city": "Singapore",
    "ip": "23.111.14.225",
    "exit_ip": null,
    "ssl": true,
    "check_port": 443,
    "api_port": 443,
    "api_path": "/api/v1",
    "public_key": "234e1731051886541b26642f19afb1d7c78fe6ec0a421076c73177df1a971d41",
    "node_id": 2281108138225,
    "scanned": "2026-06-27T21:58:43.980664Z",
    "heartbeat": "2026-06-27T21:58:09.972705Z",
    "health_check": "2026-06-27T21:54:09.761392Z",
    "version": "1.2.11",
    "uptime": 99,
    "limit": 100,
    "upload": 0,
    "download": 0,
    "disk": 5.19,
    "mem": 7.63,
    "cpu": 1.7587937948779078,
    "uptime_sec": 3099488,
    "net_download": 154764,
    "net_upload": 40732,
    "traffic_users": 3161928248747,
    "traffic_node": 8535629726161,
    "users": 0
  }
]