[
  {
    "address": "EQDvonw3GaGFdLleBu0YN34w2ujKgXVm7I9m5Bsfq_V3pb4b",
    "is_active": true,
    "node_registry": "EQDbPc6xGV6-nCmDH8bVXUdQCQ1tXMM062Xah-63HAMAkpq8",
    "owner": "EQA0ltvrkBHmBa0QSTNHcZSUNIvha1F6hTwCCMGPbyVPNpTq",
    "tickets_total": 16904,
    "tickets_30d": 16904,
    "ratings_total": 0,
    "ratings_30d": 0,
    "ratings_avg_stars": 0.0,
    "ratings_avg_stars_30d": 0.0,
    "plan": "time",
    "hostname": "kr.cdn-vk.run",
    "country": "RU",
    "region": "Krasnodar Krai",
    "city": "Krasnodar",
    "ip": "193.124.121.148",
    "exit_ip": null,
    "ssl": true,
    "check_port": 443,
    "api_port": 443,
    "api_path": "/api/v1",
    "public_key": "3ca2d63b23ffc90f1092bde5a943a8b289591ce1733aa4e789f5a5189ce776b1",
    "node_id": 192812381208148,
    "scanned": "2026-05-05T03:44:08.485792Z",
    "heartbeat": "2026-05-05T03:43:47.206423Z",
    "health_check": "2026-05-05T03:44:08.433884Z",
    "version": "1.2.5",
    "uptime": 99,
    "limit": 100,
    "upload": 0,
    "download": 0,
    "disk": 73.46,
    "mem": 65.91,
    "cpu": 14.141414171584014,
    "uptime_sec": 33817,
    "net_download": 3409160,
    "net_upload": 3350231,
    "traffic_users": 3383370578305,
    "traffic_node": 17182863916619,
    "users": 26
  },
  {
    "address": "EQDepojw8ACjGgeauVIjNL7pQ73SuVVtslardEoCvSNHLMPq",
    "is_active": true,
    "node_registry": "EQDbPc6xGV6-nCmDH8bVXUdQCQ1tXMM062Xah-63HAMAkpq8",
    "owner": "EQA0ltvrkBHmBa0QSTNHcZSUNIvha1F6hTwCCMGPbyVPNpTq",
    "tickets_total": 1163,
    "tickets_30d": 1163,
    "ratings_total": 0,
    "ratings_30d": 0,
    "ratings_avg_stars": 0.0,
    "ratings_avg_stars_30d": 0.0,
    "plan": "time",
    "hostname": "deq.cdn-vk.run",
    "country": "DE",
    "region": "Hesse",
    "city": "Frankfurt am Main",
    "ip": "5.61.33.36",
    "exit_ip": null,
    "ssl": true,
    "check_port": 443,
    "api_port": 443,
    "api_path": "/api/v1",
    "public_key": "5f36858bfd5886f00da0349bdf367e2be2db9c99ab67d05226570acbe36acd45",
    "node_id": 4860832836,
    "scanned": "2026-05-05T03:44:08.477731Z",
    "heartbeat": "2026-05-05T03:43:22.870424Z",
    "health_check": "2026-05-05T03:44:07.297017Z",
    "version": "1.2.5",
    "uptime": 99,
    "limit": 100,
    "upload": 0,
    "download": 0,
    "disk": 73.71,
    "mem": 23.84,
    "cpu": 0.0,
    "uptime_sec": 1211382,
    "net_download": 15425,
    "net_upload": 16418,
    "traffic_users": 2576873541830,
    "traffic_node": 5962153587024,
    "users": 4
  },
  {
    "address": "EQDXCtwz_9hGIA0RXVNKUcKhkbSyHk4NyjD779OPHb0k-hz6",
    "is_active": true,
    "node_registry": "EQDbPc6xGV6-nCmDH8bVXUdQCQ1tXMM062Xah-63HAMAkpq8",
    "owner": "EQA0ltvrkBHmBa0QSTNHcZSUNIvha1F6hTwCCMGPbyVPNpTq",
    "tickets_total": 8243,
    "tickets_30d": 8243,
    "ratings_total": 0,
    "ratings_30d": 0,
    "ratings_avg_stars": 0.0,
    "ratings_avg_stars_30d": 0.0,
    "plan": "time",
    "hostname": "it.yastatic.run",
    "country": "RU",
    "region": "Tatarstan Republic",
    "city": "Kazan",
    "ip": "46.17.248.203",
    "exit_ip": null,
    "ssl": true,
    "check_port": 443,
    "api_port": 443,
    "api_path": "/api/v1",
    "public_key": "cd0c609e25326af67bab58bc8b81be2537704f547de1b26082602f43084b5bde",
    "node_id": 4581682478203,
    "scanned": "2026-05-05T03:44:08.470205Z",
    "heartbeat": "2026-05-05T03:43:41.937780Z",
    "health_check": "2026-05-05T03:44:07.247593Z",
    "version": "1.2.5",
    "uptime": 99,
    "limit": 100,
    "upload": 0,
    "download": 0,
    "disk": 39.61,
    "mem": 53.03,
    "cpu": 9.090909075942934,
    "uptime_sec": 28251,
    "net_download": 72572,
    "net_upload": 69349,
    "traffic_users": 2133317572960,
    "traffic_node": 10699564815674,
    "users": 12
  },
  {
    "address": "EQDWdWtcCwGNNVND8C00IAM1xPpQDp3m1IdM67D1-chLoiVe",
    "is_active": true,
    "node_registry": "EQDbPc6xGV6-nCmDH8bVXUdQCQ1tXMM062Xah-63HAMAkpq8",
    "owner": "EQA0ltvrkBHmBa0QSTNHcZSUNIvha1F6hTwCCMGPbyVPNpTq",
    "tickets_total": 1887,
    "tickets_30d": 1887,
    "ratings_total": 0,
    "ratings_30d": 0,
    "ratings_avg_stars": 0.0,
    "ratings_avg_stars_30d": 0.0,
    "plan": "time",
    "hostname": "k.cdn-vk.run",
    "country": "RU",
    "region": "Kuzbass",
    "city": "Kemerovo",
    "ip": "77.110.112.64",
    "exit_ip": null,
    "ssl": true,
    "check_port": 443,
    "api_port": 443,
    "api_path": "/api/v1",
    "public_key": "3da82636c5cfa428209f58465ea7daf1b2ed10ffdeba2c27c5f031f7168cc047",
    "node_id": 7681098111864,
    "scanned": "2026-05-05T03:44:08.454660Z",
    "heartbeat": "2026-05-05T03:43:44.530382Z",
    "health_check": "2026-05-05T03:44:07.658562Z",
    "version": "1.2.5",
    "uptime": 98,
    "limit": 100,
    "upload": 0,
    "download": 0,
    "disk": 76.39,
    "mem": 32.18,
    "cpu": 0.999999999476131,
    "uptime_sec": 119484,
    "net_download": 25924,
    "net_upload": 20296,
    "traffic_users": 329999777897,
    "traffic_node": 1779548286656,
    "users": 1
  },
  {
    "address": "EQDW1FDkKA2rNDJco73gfyhzg-OT4_zd18SJJ-kSUttk2iw2",
    "is_active": true,
    "node_registry": "EQDbPc6xGV6-nCmDH8bVXUdQCQ1tXMM062Xah-63HAMAkpq8",
    "owner": "EQA0ltvrkBHmBa0QSTNHcZSUNIvha1F6hTwCCMGPbyVPNpTq",
    "tickets_total": 567,
    "tickets_30d": 567,
    "ratings_total": 0,
    "ratings_30d": 0,
    "ratings_avg_stars": 0.0,
    "ratings_avg_stars_30d": 0.0,
    "plan": "time",
    "hostname": "rude.cdn-vk.run",
    "country": "RU",
    "region": "Moscow",
    "city": "Moscow",
    "ip": "193.247.73.42",
    "exit_ip": null,
    "ssl": true,
    "check_port": 443,
    "api_port": 443,
    "api_path": "/api/v1",
    "public_key": "8fdfadb3e23aa382f4c98127833e4978f8ba7ac3ab839c9f52d4890a68943322",
    "node_id": 1928246872842,
    "scanned": "2026-05-05T03:44:08.446603Z",
    "heartbeat": "2026-05-05T03:44:10.220608Z",
    "health_check": "2026-05-05T03:44:06.960985Z",
    "version": "1.2.5",
    "uptime": 100,
    "limit": 100,
    "upload": 0,
    "download": 0,
    "disk": 80.6,
    "mem": 57.78,
    "cpu": 22.222222096791572,
    "uptime_sec": 568006,
    "net_download": 226551,
    "net_upload": 260475,
    "traffic_users": 1731993071123,
    "traffic_node": 7325669089501,
    "users": 6
  },
  {
    "address": "EQDTz0Tgjcn75_FjvcoLc3Ez7nOyHovj54kZFTH8ez5hTgxQ",
    "is_active": true,
    "node_registry": "EQDbPc6xGV6-nCmDH8bVXUdQCQ1tXMM062Xah-63HAMAkpq8",
    "owner": "EQA0ltvrkBHmBa0QSTNHcZSUNIvha1F6hTwCCMGPbyVPNpTq",
    "tickets_total": 10984,
    "tickets_30d": 10984,
    "ratings_total": 0,
    "ratings_30d": 0,
    "ratings_avg_stars": 0.0,
    "ratings_avg_stars_30d": 0.0,
    "plan": "time",
    "hostname": "fr.yastatic.site",
    "country": "FR",
    "region": "\u00cele-de-France",
    "city": "Paris",
    "ip": "138.124.70.136",
    "exit_ip": null,
    "ssl": true,
    "check_port": 443,
    "api_port": 443,
    "api_path": "/api/v1",
    "public_key": "2de84e2d25910271d0ba4ecba24039d8bb99bca38a98f95e6407bfb1842456b0",
    "node_id": 13781238698136,
    "scanned": "2026-05-05T03:44:08.438292Z",
    "heartbeat": "2026-05-05T03:44:04.629476Z",
    "health_check": "2026-05-05T03:44:07.598902Z",
    "version": "1.2.5",
    "uptime": 99,
    "limit": 100,
    "upload": 0,
    "download": 0,
    "disk": 27.6,
    "mem": 26.64,
    "cpu": 0.0,
    "uptime_sec": 1211966,
    "net_download": 1237162,
    "net_upload": 1246177,
    "traffic_users": 2533901052934,
    "traffic_node": 6812997126194,
    "users": 6
  },
  {
    "address": "EQDF6UK5d3F9hMcPBdqxgHwnpDyFi8FjZpV2dKGMQeCCqsTd",
    "is_active": true,
    "node_registry": "EQDbPc6xGV6-nCmDH8bVXUdQCQ1tXMM062Xah-63HAMAkpq8",
    "owner": "EQA0ltvrkBHmBa0QSTNHcZSUNIvha1F6hTwCCMGPbyVPNpTq",
    "tickets_total": 1304,
    "tickets_30d": 1304,
    "ratings_total": 0,
    "ratings_30d": 0,
    "ratings_avg_stars": 0.0,
    "ratings_avg_stars_30d": 0.0,
    "plan": "time",
    "hostname": "web.cdn-vk.rest",
    "country": "FR",
    "region": "Provence-Alpes-C\u00f4te d'Azur",
    "city": "Marseille",
    "ip": "185.253.117.69",
    "exit_ip": null,
    "ssl": true,
    "check_port": 443,
    "api_port": 443,
    "api_path": "/api/v1",
    "public_key": "30ae5c52e4b2969502dd80e79e8b14e6c7199b2e9752935d262facaca3b21cf5",
    "node_id": 18482528116869,
    "scanned": "2026-05-05T03:44:08.430828Z",
    "heartbeat": "2026-05-05T03:43:48.800496Z",
    "health_check": "2026-05-05T03:44:08.054473Z",
    "version": "1.2.5",
    "uptime": 100,
    "limit": 100,
    "upload": 243,
    "download": 325,
    "disk": 29.93,
    "mem": 34.45,
    "cpu": 0.6756756918326597,
    "uptime_sec": 1212341,
    "net_download": 20255,
    "net_upload": 6134,
    "traffic_users": 688990956353,
    "traffic_node": 2256229871916,
    "users": 3
  },
  {
    "address": "EQDCu-7klU0X0BJ09Atn3zT2WEgzYMYGJ49wTJUY1YEGpJsz",
    "is_active": true,
    "node_registry": "EQDbPc6xGV6-nCmDH8bVXUdQCQ1tXMM062Xah-63HAMAkpq8",
    "owner": "EQA0ltvrkBHmBa0QSTNHcZSUNIvha1F6hTwCCMGPbyVPNpTq",
    "tickets_total": 1934,
    "tickets_30d": 1934,
    "ratings_total": 0,
    "ratings_30d": 0,
    "ratings_avg_stars": 0.0,
    "ratings_avg_stars_30d": 0.0,
    "plan": "time",
    "hostname": "get.cdn-vk.rest",
    "country": "FR",
    "region": "Provence-Alpes-C\u00f4te d'Azur",
    "city": "Marseille",
    "ip": "185.253.118.233",
    "exit_ip": null,
    "ssl": true,
    "check_port": 443,
    "api_port": 443,
    "api_path": "/api/v1",
    "public_key": "3548eaf740c60c7e277a75abd085c409f112d70dcfb972735977ab8bbeb4cbb2",
    "node_id": 184825281178233,
    "scanned": "2026-05-05T03:44:08.422848Z",
    "heartbeat": "2026-05-05T03:43:23.718164Z",
    "health_check": "2026-05-05T03:44:08.505786Z",
    "version": "1.2.5",
    "uptime": 100,
    "limit": 100,
    "upload": 249,
    "download": 422,
    "disk": 29.88,
    "mem": 33.79,
    "cpu": 0.33670032920406046,
    "uptime_sec": 1212316,
    "net_download": 14998,
    "net_upload": 14422,
    "traffic_users": 1061868550125,
    "traffic_node": 3601975175862,
    "users": 1
  },
  {
    "address": "EQD6wzIFOah2NMwBM7VBAQQcEwSu1VteLgLLy9-4RmzuJ4M3",
    "is_active": true,
    "node_registry": "EQDbPc6xGV6-nCmDH8bVXUdQCQ1tXMM062Xah-63HAMAkpq8",
    "owner": "EQA0ltvrkBHmBa0QSTNHcZSUNIvha1F6hTwCCMGPbyVPNpTq",
    "tickets_total": 6114,
    "tickets_30d": 6114,
    "ratings_total": 0,
    "ratings_30d": 0,
    "ratings_avg_stars": 0.0,
    "ratings_avg_stars_30d": 0.0,
    "plan": "time",
    "hostname": "nov.cdn-vk.run",
    "country": "RU",
    "region": "Novosibirsk Oblast",
    "city": "Novosibirsk",
    "ip": "185.21.142.233",
    "exit_ip": null,
    "ssl": true,
    "check_port": 443,
    "api_port": 443,
    "api_path": "/api/v1",
    "public_key": "9615af1c7a5bcf66ffd8e78521d8b5cd4820948edeb42c88c090092d176f5e06",
    "node_id": 18482081418233,
    "scanned": "2026-05-05T03:44:08.414062Z",
    "heartbeat": "2026-05-05T03:43:35.067034Z",
    "health_check": "2026-05-05T03:44:08.022439Z",
    "version": "1.2.5",
    "uptime": 99,
    "limit": 100,
    "upload": 0,
    "download": 0,
    "disk": 57.51,
    "mem": 62.53,
    "cpu": 3.0303031471815904,
    "uptime_sec": 989436,
    "net_download": 88859,
    "net_upload": 102278,
    "traffic_users": 1834466514440,
    "traffic_node": 9311206634162,
    "users": 5
  },
  {
    "address": "EQD6uRTOE2HhfvSuonStLzqdStM5Sdhimb4Mj_9wboKv7z12",
    "is_active": true,
    "node_registry": "EQDbPc6xGV6-nCmDH8bVXUdQCQ1tXMM062Xah-63HAMAkpq8",
    "owner": "EQA0ltvrkBHmBa0QSTNHcZSUNIvha1F6hTwCCMGPbyVPNpTq",
    "tickets_total": 4208,
    "tickets_30d": 4208,
    "ratings_total": 0,
    "ratings_30d": 0,
    "ratings_avg_stars": 0.0,
    "ratings_avg_stars_30d": 0.0,
    "plan": "time",
    "hostname": "ae.cdn-vk.run",
    "country": "RU",
    "region": "Moscow",
    "city": "Moscow",
    "ip": "85.192.56.94",
    "exit_ip": null,
    "ssl": true,
    "check_port": 443,
    "api_port": 443,
    "api_path": "/api/v1",
    "public_key": "b1c0baa4c8ace3f074c776ddaab01f8b1ca90ff3ef786a5a98c2c5bece2b7ec3",
    "node_id": 848191855894,
    "scanned": "2026-05-05T03:44:08.405086Z",
    "heartbeat": "2026-05-05T03:43:12.874618Z",
    "health_check": "2026-05-05T03:44:06.955052Z",
    "version": "1.2.5",
    "uptime": 99,
    "limit": 100,
    "upload": 0,
    "download": 0,
    "disk": 29.22,
    "mem": 18.73,
    "cpu": 3.9603960432558476,
    "uptime_sec": 660927,
    "net_download": 535783,
    "net_upload": 568636,
    "traffic_users": 2647233410155,
    "traffic_node": 8995205627138,
    "users": 5
  },
  {
    "address": "EQD6TxPPibaYdZhY4SKxnaw5U0AM414S9iN4SNpcpzpZhOAw",
    "is_active": true,
    "node_registry": "EQDbPc6xGV6-nCmDH8bVXUdQCQ1tXMM062Xah-63HAMAkpq8",
    "owner": "EQA0ltvrkBHmBa0QSTNHcZSUNIvha1F6hTwCCMGPbyVPNpTq",
    "tickets_total": 5273,
    "tickets_30d": 5273,
    "ratings_total": 2,
    "ratings_30d": 2,
    "ratings_avg_stars": 5.0,
    "ratings_avg_stars_30d": 5.0,
    "plan": "time",
    "hostname": "ua.media-cdn.online",
    "country": "UA",
    "region": "Kyiv City",
    "city": "Kyiv",
    "ip": "5.34.182.90",
    "exit_ip": null,
    "ssl": true,
    "check_port": 443,
    "api_port": 443,
    "api_path": "/api/v1",
    "public_key": "b355ec1119586a4a389e390e169cc964a9c645d229838df16e0c7c03cff9d7af",
    "node_id": 48338181890,
    "scanned": "2026-05-05T03:44:08.386751Z",
    "heartbeat": "2026-05-05T03:43:48.745637Z",
    "health_check": "2026-05-05T03:44:08.112082Z",
    "version": "1.2.5",
    "uptime": 99,
    "limit": 100,
    "upload": 0,
    "download": 0,
    "disk": 78.09,
    "mem": 36.6,
    "cpu": 3.0927834368569904,
    "uptime_sec": 1211951,
    "net_download": 26860,
    "net_upload": 4480,
    "traffic_users": 2257321384835,
    "traffic_node": 5869883042359,
    "users": 2
  },
  {
    "address": "EQD4OZw8zOQ0oMPLrXDIsa11XyFVOu6V4eXTBELFZw7jcsjf",
    "is_active": true,
    "node_registry": "EQDbPc6xGV6-nCmDH8bVXUdQCQ1tXMM062Xah-63HAMAkpq8",
    "owner": "EQA0ltvrkBHmBa0QSTNHcZSUNIvha1F6hTwCCMGPbyVPNpTq",
    "tickets_total": 2321,
    "tickets_30d": 2321,
    "ratings_total": 0,
    "ratings_30d": 0,
    "ratings_avg_stars": 0.0,
    "ratings_avg_stars_30d": 0.0,
    "plan": "time",
    "hostname": "ptr.yastatic.run",
    "country": "RU",
    "region": "St.-Petersburg",
    "city": "Saint Petersburg",
    "ip": "5.188.211.136",
    "exit_ip": null,
    "ssl": true,
    "check_port": 443,
    "api_port": 443,
    "api_path": "/api/v1",
    "public_key": "3eacf3d0e360d35711976b4a69714b3b1e8580eb44906411bedeb0087c7aa651",
    "node_id": 4818782108136,
    "scanned": "2026-05-05T03:44:08.381442Z",
    "heartbeat": "2026-05-05T03:43:56.903183Z",
    "health_check": "2026-05-05T03:44:07.041175Z",
    "version": "1.2.5",
    "uptime": 99,
    "limit": 100,
    "upload": 0,
    "download": 0,
    "disk": 41.21,
    "mem": 27.95,
    "cpu": 1.000000000698492,
    "uptime_sec": 1209212,
    "net_download": 167633,
    "net_upload": 205659,
    "traffic_users": 1613724233179,
    "traffic_node": 6742773258294,
    "users": 7
  },
  {
    "address": "EQD3LT4bTCmjjN7ZRXI5qck7hgMR5iKDWUUGQWd54R2u_M5V",
    "is_active": true,
    "node_registry": "EQDbPc6xGV6-nCmDH8bVXUdQCQ1tXMM062Xah-63HAMAkpq8",
    "owner": "EQA0ltvrkBHmBa0QSTNHcZSUNIvha1F6hTwCCMGPbyVPNpTq",
    "tickets_total": 5840,
    "tickets_30d": 5840,
    "ratings_total": 0,
    "ratings_30d": 0,
    "ratings_avg_stars": 0.0,
    "ratings_avg_stars_30d": 0.0,
    "plan": "time",
    "hostname": "ru.cdn-vk.run",
    "country": "RU",
    "region": "Primorye",
    "city": "Vladivostok",
    "ip": "193.124.9.226",
    "exit_ip": null,
    "ssl": true,
    "check_port": 443,
    "api_port": 443,
    "api_path": "/api/v1",
    "public_key": "fd7e2f846288e7a1aee506adbd281d3ee5682bcf15b03687c01625fc2646eb3d",
    "node_id": 1928123888226,
    "scanned": "2026-05-05T03:44:08.374692Z",
    "heartbeat": "2026-05-05T03:44:08.191295Z",
    "health_check": "2026-05-05T03:44:08.339040Z",
    "version": "1.2.5",
    "uptime": 99,
    "limit": 100,
    "upload": 0,
    "download": 0,
    "disk": 82.8,
    "mem": 59.78,
    "cpu": 5.050505077586668,
    "uptime_sec": 148942,
    "net_download": 1383035,
    "net_upload": 1521774,
    "traffic_users": 2066684893675,
    "traffic_node": 10284598554327,
    "users": 8
  },
  {
    "address": "EQD1vwDcZN_Q_mPxtHIoLkPW2RoqxmA1ltd1mVSWWjkfrR-S",
    "is_active": true,
    "node_registry": "EQDbPc6xGV6-nCmDH8bVXUdQCQ1tXMM062Xah-63HAMAkpq8",
    "owner": "EQA0ltvrkBHmBa0QSTNHcZSUNIvha1F6hTwCCMGPbyVPNpTq",
    "tickets_total": 2248,
    "tickets_30d": 2248,
    "ratings_total": 0,
    "ratings_30d": 0,
    "ratings_avg_stars": 0.0,
    "ratings_avg_stars_30d": 0.0,
    "plan": "time",
    "hostname": "ph.edge-apple.online",
    "country": "PH",
    "region": "National Capital Region",
    "city": "Pasay",
    "ip": "206.237.107.68",
    "exit_ip": null,
    "ssl": true,
    "check_port": 443,
    "api_port": 443,
    "api_path": "/api/v1",
    "public_key": "b3cb2c6b7d9f82c4803570d273d79e65539c807df03594ce2dd1cbcd0ab7e074",
    "node_id": 20582368106868,
    "scanned": "2026-05-05T03:44:08.368850Z",
    "heartbeat": "2026-05-05T03:43:59.527155Z",
    "health_check": "2026-05-05T03:44:10.084725Z",
    "version": "1.2.5",
    "uptime": 99,
    "limit": 100,
    "upload": 0,
    "download": 0,
    "disk": 42.09,
    "mem": 29.56,
    "cpu": 1.0204081409616625,
    "uptime_sec": 1208293,
    "net_download": 8706,
    "net_upload": 4954,
    "traffic_users": 288994314856,
    "traffic_node": 1209541155386,
    "users": 2
  },
  {
    "address": "EQCwbNWT6x5mWBaajKOd5H5qgYbMgL1o3yhEtWUUqcURUHpT",
    "is_active": true,
    "node_registry": "EQDbPc6xGV6-nCmDH8bVXUdQCQ1tXMM062Xah-63HAMAkpq8",
    "owner": "EQA0ltvrkBHmBa0QSTNHcZSUNIvha1F6hTwCCMGPbyVPNpTq",
    "tickets_total": 22539,
    "tickets_30d": 22539,
    "ratings_total": 1,
    "ratings_30d": 1,
    "ratings_avg_stars": 5.0,
    "ratings_avg_stars_30d": 5.0,
    "plan": "time",
    "hostname": "uk.yastatic.site",
    "country": "GB",
    "region": "England",
    "city": "London",
    "ip": "173.208.51.125",
    "exit_ip": null,
    "ssl": true,
    "check_port": 443,
    "api_port": 443,
    "api_path": "/api/v1",
    "public_key": "2e54ff5b425264a0dd3db9e25dcde13aec657531f57e9f1cf89ae3ac93542067",
    "node_id": 17282078508125,
    "scanned": "2026-05-05T03:44:08.362496Z",
    "heartbeat": "2026-05-05T03:43:13.571098Z",
    "health_check": "2026-05-05T03:44:06.715279Z",
    "version": "1.2.5",
    "uptime": 97,
    "limit": 100,
    "upload": 0,
    "download": 0,
    "disk": 5.4,
    "mem": 8.79,
    "cpu": 2.770780842241406,
    "uptime_sec": 576224,
    "net_download": 302373,
    "net_upload": 415420,
    "traffic_users": 9617101315726,
    "traffic_node": 24515592785846,
    "users": 42
  },
  {
    "address": "EQCt_0YYtDYxjiu_ON2aJF3N8QQf3yftQ4pa6sYjdTk1jkUf",
    "is_active": true,
    "node_registry": "EQDbPc6xGV6-nCmDH8bVXUdQCQ1tXMM062Xah-63HAMAkpq8",
    "owner": "EQA0ltvrkBHmBa0QSTNHcZSUNIvha1F6hTwCCMGPbyVPNpTq",
    "tickets_total": 16538,
    "tickets_30d": 16538,
    "ratings_total": 2,
    "ratings_30d": 2,
    "ratings_avg_stars": 3.0,
    "ratings_avg_stars_30d": 3.0,
    "plan": "time",
    "hostname": "pl.cdn-vk.run",
    "country": "PL",
    "region": "Mazovia",
    "city": "Warsaw",
    "ip": "45.144.49.56",
    "exit_ip": null,
    "ssl": true,
    "check_port": 443,
    "api_port": 443,
    "api_path": "/api/v1",
    "public_key": "d1de822f637a95b783678c5c2d8207e8bed1653fe28a0f8f2c392696ddb49800",
    "node_id": 448143848856,
    "scanned": "2026-05-05T03:44:08.355146Z",
    "heartbeat": "2026-05-05T03:44:04.997070Z",
    "health_check": "2026-05-05T03:44:06.849978Z",
    "version": "1.2.5",
    "uptime": 99,
    "limit": 100,
    "upload": 0,
    "download": 0,
    "disk": 55.81,
    "mem": 27.12,
    "cpu": 7.920792074985426,
    "uptime_sec": 914854,
    "net_download": 1721746,
    "net_upload": 1375242,
    "traffic_users": 8595977659594,
    "traffic_node": 21785058934111,
    "users": 33
  },
  {
    "address": "EQCpic66nMCZEdlY5km-G1WEStMc0TixjDryR9xr4sYak9Z8",
    "is_active": true,
    "node_registry": "EQDbPc6xGV6-nCmDH8bVXUdQCQ1tXMM062Xah-63HAMAkpq8",
    "owner": "EQA0ltvrkBHmBa0QSTNHcZSUNIvha1F6hTwCCMGPbyVPNpTq",
    "tickets_total": 2744,
    "tickets_30d": 2744,
    "ratings_total": 0,
    "ratings_30d": 0,
    "ratings_avg_stars": 0.0,
    "ratings_avg_stars_30d": 0.0,
    "plan": "time",
    "hostname": "web.yastatic.site",
    "country": "VN",
    "region": "Ho Chi Minh City (HCMC)",
    "city": "Ho Chi Minh City",
    "ip": "61.14.234.27",
    "exit_ip": null,
    "ssl": true,
    "check_port": 443,
    "api_port": 443,
    "api_path": "/api/v1",
    "public_key": "6fe7e0fbcd1e443941b70bd9ffe259d96d0f95c0dc5af7159fc37547b5fb2688",
    "node_id": 608138233827,
    "scanned": "2026-05-05T03:44:08.347308Z",
    "heartbeat": "2026-05-05T03:43:18.805419Z",
    "health_check": "2026-05-05T03:44:10.872789Z",
    "version": "1.2.5",
    "uptime": 100,
    "limit": 100,
    "upload": 60,
    "download": 73,
    "disk": 41.28,
    "mem": 36.32,
    "cpu": 13.131313374572573,
    "uptime_sec": 1208659,
    "net_download": 291376,
    "net_upload": 309513,
    "traffic_users": 682798474906,
    "traffic_node": 2241471152525,
    "users": 6
  },
  {
    "address": "EQCpC9s6Wy0qs9TEcznguDdbz1uZvqHmqPJgureKT3if6RBk",
    "is_active": true,
    "node_registry": "EQDbPc6xGV6-nCmDH8bVXUdQCQ1tXMM062Xah-63HAMAkpq8",
    "owner": "EQA0ltvrkBHmBa0QSTNHcZSUNIvha1F6hTwCCMGPbyVPNpTq",
    "tickets_total": 15770,
    "tickets_30d": 15770,
    "ratings_total": 2,
    "ratings_30d": 2,
    "ratings_avg_stars": 2.5,
    "ratings_avg_stars_30d": 2.5,
    "plan": "time",
    "hostname": "get.cdn-vk.run",
    "country": "FI",
    "region": "Uusimaa",
    "city": "Helsinki",
    "ip": "185.88.101.50",
    "exit_ip": null,
    "ssl": true,
    "check_port": 443,
    "api_port": 443,
    "api_path": "/api/v1",
    "public_key": "ee9aaba20d3a0aec82f1fa88f9ffab0113958eaa206c155e134a4531a1b202af",
    "node_id": 1848878100850,
    "scanned": "2026-05-05T03:44:08.341552Z",
    "heartbeat": "2026-05-05T03:43:45.448331Z",
    "health_check": "2026-05-05T03:44:07.568983Z",
    "version": "1.2.5",
    "uptime": 97,
    "limit": 100,
    "upload": 198,
    "download": 203,
    "disk": 30.03,
    "mem": 33.39,
    "cpu": 36.71497585182245,
    "uptime_sec": 988137,
    "net_download": 3355180,
    "net_upload": 4506601,
    "traffic_users": 9360045452691,
    "traffic_node": 22238459682022,
    "users": 26
  },
  {
    "address": "EQCeSadEW1a5iGzLZOLYRn-IvHwluxKttZKuFlVNbwwe0xdT",
    "is_active": true,
    "node_registry": "EQDbPc6xGV6-nCmDH8bVXUdQCQ1tXMM062Xah-63HAMAkpq8",
    "owner": "EQA0ltvrkBHmBa0QSTNHcZSUNIvha1F6hTwCCMGPbyVPNpTq",
    "tickets_total": 2008,
    "tickets_30d": 2008,
    "ratings_total": 0,
    "ratings_30d": 0,
    "ratings_avg_stars": 0.0,
    "ratings_avg_stars_30d": 0.0,
    "plan": "time",
    "hostname": "msk.yastatic.run",
    "country": "RU",
    "region": "Moscow",
    "city": "Moscow",
    "ip": "5.45.83.194",
    "exit_ip": null,
    "ssl": true,
    "check_port": 443,
    "api_port": 443,
    "api_path": "/api/v1",
    "public_key": "7acf7ca2d017c7297ed16388e28a20fa1dccf7c7e6fbd823c14ecfd47ae2a91f",
    "node_id": 48448828194,
    "scanned": "2026-05-05T03:44:08.332825Z",
    "heartbeat": "2026-05-05T03:43:02.898981Z",
    "health_check": "2026-05-05T03:44:08.142641Z",
    "version": "1.2.5",
    "uptime": 99,
    "limit": 10,
    "upload": 0,
    "download": 0,
    "disk": 38.56,
    "mem": 28.38,
    "cpu": 3.0000000027939677,
    "uptime_sec": 1206792,
    "net_download": 1516618,
    "net_upload": 2584802,
    "traffic_users": 1080901309234,
    "traffic_node": 5475431195813,
    "users": 3
  },
  {
    "address": "EQCbeMzO3tNf06mZymWt60aSx7VbWkpZEu6kAoVvo5u7SmMS",
    "is_active": true,
    "node_registry": "EQDbPc6xGV6-nCmDH8bVXUdQCQ1tXMM062Xah-63HAMAkpq8",
    "owner": "EQA0ltvrkBHmBa0QSTNHcZSUNIvha1F6hTwCCMGPbyVPNpTq",
    "tickets_total": 8886,
    "tickets_30d": 8886,
    "ratings_total": 1,
    "ratings_30d": 1,
    "ratings_avg_stars": 2.0,
    "ratings_avg_stars_30d": 2.0,
    "plan": "time",
    "hostname": "nl.edge-apple.online",
    "country": "NL",
    "region": "North Holland",
    "city": "Amsterdam",
    "ip": "45.15.128.126",
    "exit_ip": null,
    "ssl": true,
    "check_port": 443,
    "api_port": 443,
    "api_path": "/api/v1",
    "public_key": "9feb6386e06bff536f3f3318b795f14ef907302b60c9fc736fc70874af3c9648",
    "node_id": 4481481278126,
    "scanned": "2026-05-05T03:44:08.323393Z",
    "heartbeat": "2026-05-05T03:43:29.527334Z",
    "health_check": "2026-05-05T03:44:06.620828Z",
    "version": "1.2.5",
    "uptime": 99,
    "limit": 100,
    "upload": 0,
    "download": 0,
    "disk": 24.96,
    "mem": 56.42,
    "cpu": 21.052631585934435,
    "uptime_sec": 35546,
    "net_download": 771493,
    "net_upload": 747468,
    "traffic_users": 6938041723798,
    "traffic_node": 17276625123413,
    "users": 11
  },
  {
    "address": "EQCO9bsuYzIen0Oj6J3YA3C0fzNRcLVJdjwvVgKUXEaxybbj",
    "is_active": true,
    "node_registry": "EQDbPc6xGV6-nCmDH8bVXUdQCQ1tXMM062Xah-63HAMAkpq8",
    "owner": "EQA0ltvrkBHmBa0QSTNHcZSUNIvha1F6hTwCCMGPbyVPNpTq",
    "tickets_total": 6407,
    "tickets_30d": 6407,
    "ratings_total": 0,
    "ratings_30d": 0,
    "ratings_avg_stars": 0.0,
    "ratings_avg_stars_30d": 0.0,
    "plan": "time",
    "hostname": "spb.media-cdn.online",
    "country": "RU",
    "region": "St.-Petersburg",
    "city": "Saint Petersburg",
    "ip": "193.233.91.122",
    "exit_ip": null,
    "ssl": true,
    "check_port": 443,
    "api_port": 443,
    "api_path": "/api/v1",
    "public_key": "cc0612807653e11357cf8b47d055e0a384909ec7df9120a52d207d4f551e98c9",
    "node_id": 19282328908122,
    "scanned": "2026-05-05T03:44:08.316381Z",
    "heartbeat": "2026-05-05T03:42:58.570277Z",
    "health_check": "2026-05-05T03:44:07.214589Z",
    "version": "1.2.5",
    "uptime": 99,
    "limit": 100,
    "upload": 0,
    "download": 0,
    "disk": 21.68,
    "mem": 17.94,
    "cpu": 1.0000000009313226,
    "uptime_sec": 660194,
    "net_download": 1508,
    "net_upload": 2126,
    "traffic_users": 1352560309908,
    "traffic_node": 5745967390535,
    "users": 4
  },
  {
    "address": "EQCKqB8nDQb0Ejbxl_iG_cdSUYcfezPrSmT3NV5nCMEIruTs",
    "is_active": true,
    "node_registry": "EQDbPc6xGV6-nCmDH8bVXUdQCQ1tXMM062Xah-63HAMAkpq8",
    "owner": "EQA0ltvrkBHmBa0QSTNHcZSUNIvha1F6hTwCCMGPbyVPNpTq",
    "tickets_total": 5588,
    "tickets_30d": 5588,
    "ratings_total": 0,
    "ratings_30d": 0,
    "ratings_avg_stars": 0.0,
    "ratings_avg_stars_30d": 0.0,
    "plan": "time",
    "hostname": "sp.yastatic.site",
    "country": "RU",
    "region": "St.-Petersburg",
    "city": "Saint Petersburg",
    "ip": "83.147.255.125",
    "exit_ip": null,
    "ssl": true,
    "check_port": 443,
    "api_port": 443,
    "api_path": "/api/v1",
    "public_key": "90da8535c2cacef5d55c51ee0fb7c3181a8365aa67c6d17b66ce1a05e2ba152a",
    "node_id": 82814682548125,
    "scanned": "2026-05-05T03:44:08.310523Z",
    "heartbeat": "2026-05-05T03:43:45.607120Z",
    "health_check": "2026-05-05T03:44:08.318716Z",
    "version": "1.2.5",
    "uptime": 99,
    "limit": 100,
    "upload": 0,
    "download": 0,
    "disk": 25.19,
    "mem": 22.42,
    "cpu": 10.999999998603016,
    "uptime_sec": 981439,
    "net_download": 179898,
    "net_upload": 175085,
    "traffic_users": 2542219063945,
    "traffic_node": 9528670582303,
    "users": 10
  },
  {
    "address": "EQCJLajK__ywESlcb7y4LPYKhQ5_reEsBIgJ1H5kLrabqRDF",
    "is_active": true,
    "node_registry": "EQDbPc6xGV6-nCmDH8bVXUdQCQ1tXMM062Xah-63HAMAkpq8",
    "owner": "EQA0ltvrkBHmBa0QSTNHcZSUNIvha1F6hTwCCMGPbyVPNpTq",
    "tickets_total": 25346,
    "tickets_30d": 25346,
    "ratings_total": 1,
    "ratings_30d": 1,
    "ratings_avg_stars": 4.0,
    "ratings_avg_stars_30d": 4.0,
    "plan": "time",
    "hostname": "vk.com.yastatic.site",
    "country": "CH",
    "region": "Bern",
    "city": "Bern",
    "ip": "45.59.122.235",
    "exit_ip": null,
    "ssl": true,
    "check_port": 443,
    "api_port": 443,
    "api_path": "/api/v1",
    "public_key": "10846484cf93dea2f6ab0bf6361b05d38bc7f3b6f4691846804f4718716a6582",
    "node_id": 4485881218235,
    "scanned": "2026-05-05T03:44:08.305036Z",
    "heartbeat": "2026-05-05T03:43:44.853797Z",
    "health_check": "2026-05-05T03:44:06.812143Z",
    "version": "1.2.5",
    "uptime": 100,
    "limit": 100,
    "upload": 528,
    "download": 2717,
    "disk": 28.52,
    "mem": 63.88,
    "cpu": 40.816326547824836,
    "uptime_sec": 49475,
    "net_download": 4267893,
    "net_upload": 4671235,
    "traffic_users": 7708295719858,
    "traffic_node": 21379343117750,
    "users": 72
  },
  {
    "address": "EQCGokVlstQbF_P-bva5AnkcOPFSOjYrhnD4Q8I7jxEMTy_H",
    "is_active": true,
    "node_registry": "EQDbPc6xGV6-nCmDH8bVXUdQCQ1tXMM062Xah-63HAMAkpq8",
    "owner": "EQA0ltvrkBHmBa0QSTNHcZSUNIvha1F6hTwCCMGPbyVPNpTq",
    "tickets_total": 4293,
    "tickets_30d": 4293,
    "ratings_total": 0,
    "ratings_30d": 0,
    "ratings_avg_stars": 0.0,
    "ratings_avg_stars_30d": 0.0,
    "plan": "time",
    "hostname": "msk.cdn-vk.rest",
    "country": "RU",
    "region": "Moscow",
    "city": "Moscow",
    "ip": "150.241.85.225",
    "exit_ip": null,
    "ssl": true,
    "check_port": 443,
    "api_port": 443,
    "api_path": "/api/v1",
    "public_key": "c1391afbc9abf68bc88933bfe9eb306a12b74d47c534d6fc95a356ad107a8254",
    "node_id": 14982408848225,
    "scanned": "2026-05-05T03:44:08.292051Z",
    "heartbeat": "2026-05-05T03:42:58.355099Z",
    "health_check": "2026-05-05T03:44:08.285793Z",
    "version": "1.2.5",
    "uptime": 99,
    "limit": 100,
    "upload": 0,
    "download": 0,
    "disk": 11.02,
    "mem": 30.64,
    "cpu": 7.142857125886979,
    "uptime_sec": 1206789,
    "net_download": 110488,
    "net_upload": 624080,
    "traffic_users": 808270974333,
    "traffic_node": 4171052036881,
    "users": 5
  },
  {
    "address": "EQC4c0I4lOSBM_68Yk5RxpQ0XXIfbhaTh8LA20656K6QptYO",
    "is_active": true,
    "node_registry": "EQDbPc6xGV6-nCmDH8bVXUdQCQ1tXMM062Xah-63HAMAkpq8",
    "owner": "EQA0ltvrkBHmBa0QSTNHcZSUNIvha1F6hTwCCMGPbyVPNpTq",
    "tickets_total": 2558,
    "tickets_30d": 2558,
    "ratings_total": 0,
    "ratings_30d": 0,
    "ratings_avg_stars": 0.0,
    "ratings_avg_stars_30d": 0.0,
    "plan": "time",
    "hostname": "hip.edge-apple.online",
    "country": "DE",
    "region": "Hesse",
    "city": "Frankfurt am Main",
    "ip": "46.21.82.243",
    "exit_ip": null,
    "ssl": true,
    "check_port": 443,
    "api_port": 443,
    "api_path": "/api/v1",
    "public_key": "ecae397a5489ea573de974d1dfa07497761a61d68dfa3b7a9f18e29d0be6c9f6",
    "node_id": 458208818243,
    "scanned": "2026-05-05T03:44:08.287205Z",
    "heartbeat": "2026-05-05T03:43:14.021533Z",
    "health_check": "2026-05-05T03:44:07.545740Z",
    "version": "1.2.5",
    "uptime": 99,
    "limit": 100,
    "upload": 0,
    "download": 0,
    "disk": 27.93,
    "mem": 21.52,
    "cpu": 3.553299483506678,
    "uptime_sec": 1207026,
    "net_download": 3255,
    "net_upload": 3765,
    "traffic_users": 774399090666,
    "traffic_node": 2204073205906,
    "users": 2
  },
  {
    "address": "EQC2Ps3tmhh-YFZKBvLUoGHs-nNjTJ9UXBejOWhlyuyKEMrk",
    "is_active": true,
    "node_registry": "EQDbPc6xGV6-nCmDH8bVXUdQCQ1tXMM062Xah-63HAMAkpq8",
    "owner": "EQA0ltvrkBHmBa0QSTNHcZSUNIvha1F6hTwCCMGPbyVPNpTq",
    "tickets_total": 2067,
    "tickets_30d": 2067,
    "ratings_total": 0,
    "ratings_30d": 0,
    "ratings_avg_stars": 0.0,
    "ratings_avg_stars_30d": 0.0,
    "plan": "time",
    "hostname": "max.relay-apple.online",
    "country": "FR",
    "region": "Provence-Alpes-C\u00f4te d'Azur",
    "city": "Marseille",
    "ip": "89.44.80.2",
    "exit_ip": null,
    "ssl": true,
    "check_port": 443,
    "api_port": 443,
    "api_path": "/api/v1",
    "public_key": "f71863aa8761dfeea22d2caf697ebe98e0109f469008bd848f7e3a836c1bfc0f",
    "node_id": 8884387982,
    "scanned": "2026-05-05T03:44:08.282172Z",
    "heartbeat": "2026-05-05T03:43:54.321327Z",
    "health_check": "2026-05-05T03:44:06.792024Z",
    "version": "1.2.5",
    "uptime": 100,
    "limit": 100,
    "upload": 0,
    "download": 0,
    "disk": 25.76,
    "mem": 36.09,
    "cpu": 2.6845637456995144,
    "uptime_sec": 1212347,
    "net_download": 39545,
    "net_upload": 16584,
    "traffic_users": 2201997172422,
    "traffic_node": 6124063975063,
    "users": 5
  },
  {
    "address": "EQC1snGO9Lx7ZT2pw6cGR2OgxqN4I__u6P-KscNcI9t_7TJc",
    "is_active": true,
    "node_registry": "EQDbPc6xGV6-nCmDH8bVXUdQCQ1tXMM062Xah-63HAMAkpq8",
    "owner": "EQA0ltvrkBHmBa0QSTNHcZSUNIvha1F6hTwCCMGPbyVPNpTq",
    "tickets_total": 2659,
    "tickets_30d": 2659,
    "ratings_total": 0,
    "ratings_30d": 0,
    "ratings_avg_stars": 0.0,
    "ratings_avg_stars_30d": 0.0,
    "plan": "time",
    "hostname": "deq.yastatic.run",
    "country": "DE",
    "region": "Hesse",
    "city": "Frankfurt am Main",
    "ip": "5.61.32.103",
    "exit_ip": null,
    "ssl": true,
    "check_port": 443,
    "api_port": 443,
    "api_path": "/api/v1",
    "public_key": "bcf4a69a55e58b63c25a16bf6987b2508d1765250d7f1afa035ca48e71fe3325",
    "node_id": 48608318103,
    "scanned": "2026-05-05T03:44:08.277114Z",
    "heartbeat": "2026-05-05T03:43:49.809046Z",
    "health_check": "2026-05-05T03:44:07.959525Z",
    "version": "1.2.5",
    "uptime": 99,
    "limit": 100,
    "upload": 0,
    "download": 0,
    "disk": 24.72,
    "mem": 19.49,
    "cpu": 0.5025125516431852,
    "uptime_sec": 1208289,
    "net_download": 22886,
    "net_upload": 27822,
    "traffic_users": 509984800794,
    "traffic_node": 1534582956829,
    "users": 2
  },
  {
    "address": "EQC-UjsuvMukXtKKaxBupC2VTSLqc5gl4--10fGHK1TZ-Odf",
    "is_active": true,
    "node_registry": "EQDbPc6xGV6-nCmDH8bVXUdQCQ1tXMM062Xah-63HAMAkpq8",
    "owner": "EQA0ltvrkBHmBa0QSTNHcZSUNIvha1F6hTwCCMGPbyVPNpTq",
    "tickets_total": 19598,
    "tickets_30d": 19598,
    "ratings_total": 0,
    "ratings_30d": 0,
    "ratings_avg_stars": 0.0,
    "ratings_avg_stars_30d": 0.0,
    "plan": "time",
    "hostname": "xxl.cdn-vk.run",
    "country": "NL",
    "region": "Flevoland",
    "city": "Lelystad",
    "ip": "95.211.41.85",
    "exit_ip": null,
    "ssl": true,
    "check_port": 443,
    "api_port": 443,
    "api_path": "/api/v1",
    "public_key": "ccab9e27fdb7b7abe679bb3f0cb63938de5812e434c62efd2371c64cde4c735d",
    "node_id": 948210840885,
    "scanned": "2026-05-05T03:44:08.271842Z",
    "heartbeat": "2026-05-05T03:43:30.738820Z",
    "health_check": "2026-05-05T03:44:07.869111Z",
    "version": "1.2.5",
    "uptime": 98,
    "limit": 50,
    "upload": 0,
    "download": 0,
    "disk": 7.52,
    "mem": 13.75,
    "cpu": 12.467532456159933,
    "uptime_sec": 394934,
    "net_download": 4933587,
    "net_upload": 8181346,
    "traffic_users": 15683584098466,
    "traffic_node": 38885580231424,
    "users": 34
  },
  {
    "address": "EQBuFm_RWPBbmJ2rqxgsqGjjYwkwS10gLFOmoJesuLOmlhI9",
    "is_active": true,
    "node_registry": "EQDbPc6xGV6-nCmDH8bVXUdQCQ1tXMM062Xah-63HAMAkpq8",
    "owner": "EQA0ltvrkBHmBa0QSTNHcZSUNIvha1F6hTwCCMGPbyVPNpTq",
    "tickets_total": 43728,
    "tickets_30d": 43728,
    "ratings_total": 0,
    "ratings_30d": 0,
    "ratings_avg_stars": 0.0,
    "ratings_avg_stars_30d": 0.0,
    "plan": "time",
    "hostname": "lv.relay-apple.online",
    "country": "LV",
    "region": "Riga",
    "city": "Riga",
    "ip": "92.118.170.162",
    "exit_ip": null,
    "ssl": true,
    "check_port": 443,
    "api_port": 443,
    "api_path": "/api/v1",
    "public_key": "3d3be5b90790ba2b489c17615beb4e35bf2ec525c7c1d0914600e5a0617cff73",
    "node_id": 91811781698162,
    "scanned": "2026-05-05T03:44:08.266204Z",
    "heartbeat": "2026-05-05T03:43:39.073322Z",
    "health_check": "2026-05-05T03:44:06.904851Z",
    "version": "1.2.5",
    "uptime": 99,
    "limit": 100,
    "upload": 0,
    "download": 0,
    "disk": 29.37,
    "mem": 33.32,
    "cpu": 23.188405780800206,
    "uptime_sec": 728459,
    "net_download": 1810493,
    "net_upload": 2003634,
    "traffic_users": 8298744003133,
    "traffic_node": 22337622511580,
    "users": 37
  },
  {
    "address": "EQBqVxQmDa_yX6Ll_V7vuukQPDiTJhVt7Qa6jt-g-YbgaE6U",
    "is_active": true,
    "node_registry": "EQDbPc6xGV6-nCmDH8bVXUdQCQ1tXMM062Xah-63HAMAkpq8",
    "owner": "EQA0ltvrkBHmBa0QSTNHcZSUNIvha1F6hTwCCMGPbyVPNpTq",
    "tickets_total": 10556,
    "tickets_30d": 10556,
    "ratings_total": 0,
    "ratings_30d": 0,
    "ratings_avg_stars": 0.0,
    "ratings_avg_stars_30d": 0.0,
    "plan": "time",
    "hostname": "ekb.cdn-vk.run",
    "country": "RU",
    "region": "Sverdlovsk Oblast",
    "city": "Yekaterinburg",
    "ip": "45.11.27.161",
    "exit_ip": null,
    "ssl": true,
    "check_port": 443,
    "api_port": 443,
    "api_path": "/api/v1",
    "public_key": "8e502bc5aa8aaecd2162eb1ba28121d3bcd26b66e05c7cc9564f50e5103605b9",
    "node_id": 448108268161,
    "scanned": "2026-05-05T03:44:08.260487Z",
    "heartbeat": "2026-05-05T03:43:36.723935Z",
    "health_check": "2026-05-05T03:44:08.619396Z",
    "version": "1.2.5",
    "uptime": 99,
    "limit": 100,
    "upload": 0,
    "download": 0,
    "disk": 41.52,
    "mem": 61.43,
    "cpu": 4.000000006635673,
    "uptime_sec": 35512,
    "net_download": 3036447,
    "net_upload": 3058342,
    "traffic_users": 3069663554968,
    "traffic_node": 15614291928541,
    "users": 23
  },
  {
    "address": "EQBmkOJgIOA13bc8Rj4spCwCMqiabuSo1pnFtAPd5Ld1bYno",
    "is_active": true,
    "node_registry": "EQDbPc6xGV6-nCmDH8bVXUdQCQ1tXMM062Xah-63HAMAkpq8",
    "owner": "EQA0ltvrkBHmBa0QSTNHcZSUNIvha1F6hTwCCMGPbyVPNpTq",
    "tickets_total": 309,
    "tickets_30d": 309,
    "ratings_total": 0,
    "ratings_30d": 0,
    "ratings_avg_stars": 0.0,
    "ratings_avg_stars_30d": 0.0,
    "plan": "time",
    "hostname": "ph.media-cdn.online",
    "country": "PH",
    "region": "National Capital Region",
    "city": "Makati City",
    "ip": "61.245.10.36",
    "exit_ip": null,
    "ssl": true,
    "check_port": 443,
    "api_port": 443,
    "api_path": "/api/v1",
    "public_key": "563d8b95a7abbed4e30b13a66f5205caf3a1dd773c9d3d8da1ab6afe44024d92",
    "node_id": 608244809836,
    "scanned": "2026-05-05T03:44:08.254730Z",
    "heartbeat": "2026-04-24T07:43:01.490695Z",
    "health_check": "2026-04-24T07:52:17.677130Z",
    "version": "1.2.5",
    "uptime": 99,
    "limit": 100,
    "upload": 0,
    "download": 0,
    "disk": 56.1,
    "mem": 38.75,
    "cpu": 2.061855672577645,
    "uptime_sec": 272238,
    "net_download": 2122617,
    "net_upload": 2193845,
    "traffic_users": 118525866446,
    "traffic_node": 655178361634,
    "users": 4
  },
  {
    "address": "EQBlby9LXxGbLz2XfW42iLo3899Os3uGxYVvw3KG5Vmk690s",
    "is_active": true,
    "node_registry": "EQDbPc6xGV6-nCmDH8bVXUdQCQ1tXMM062Xah-63HAMAkpq8",
    "owner": "EQA0ltvrkBHmBa0QSTNHcZSUNIvha1F6hTwCCMGPbyVPNpTq",
    "tickets_total": 1094,
    "tickets_30d": 1094,
    "ratings_total": 0,
    "ratings_30d": 0,
    "ratings_avg_stars": 0.0,
    "ratings_avg_stars_30d": 0.0,
    "plan": "time",
    "hostname": "os.cdn-vk.run",
    "country": "RU",
    "region": "Moscow",
    "city": "Moscow",
    "ip": "194.87.57.104",
    "exit_ip": null,
    "ssl": true,
    "check_port": 443,
    "api_port": 443,
    "api_path": "/api/v1",
    "public_key": "c8626b746313a95da2a5e0a00c3e9e2219cd186a16fe4adc9c89b049cb1210ea",
    "node_id": 1938868568104,
    "scanned": "2026-05-05T03:44:08.249017Z",
    "heartbeat": "2026-05-05T03:43:28.172222Z",
    "health_check": "2026-05-05T03:44:08.127540Z",
    "version": "1.2.5",
    "uptime": 99,
    "limit": 100,
    "upload": 0,
    "download": 0,
    "disk": 78.21,
    "mem": 60.64,
    "cpu": 2.040816281923325,
    "uptime_sec": 1206818,
    "net_download": 30075,
    "net_upload": 29900,
    "traffic_users": 1364898675962,
    "traffic_node": 6257894661375,
    "users": 8
  },
  {
    "address": "EQBjKJ772islNaW9neRjsZIVAb8GVg4bhbbnH10NkqXs0lCi",
    "is_active": true,
    "node_registry": "EQDbPc6xGV6-nCmDH8bVXUdQCQ1tXMM062Xah-63HAMAkpq8",
    "owner": "EQA0ltvrkBHmBa0QSTNHcZSUNIvha1F6hTwCCMGPbyVPNpTq",
    "tickets_total": 1053,
    "tickets_30d": 1053,
    "ratings_total": 0,
    "ratings_30d": 0,
    "ratings_avg_stars": 0.0,
    "ratings_avg_stars_30d": 0.0,
    "plan": "time",
    "hostname": "host.cdn-vk.run",
    "country": "RU",
    "region": "Moscow",
    "city": "Moscow",
    "ip": "185.130.212.84",
    "exit_ip": null,
    "ssl": true,
    "check_port": 443,
    "api_port": 443,
    "api_path": "/api/v1",
    "public_key": "a3017d09a77cdd5ae7f4bd7f925e1c46afb6b7f5c85e1f5374d5ba1c1c69b8e5",
    "node_id": 18481298211884,
    "scanned": "2026-05-05T03:44:08.241169Z",
    "heartbeat": "2026-05-05T03:44:18.118577Z",
    "health_check": "2026-05-05T03:44:06.943638Z",
    "version": "1.2.5",
    "uptime": 100,
    "limit": 5,
    "upload": 0,
    "download": 0,
    "disk": 60.44,
    "mem": 55.95,
    "cpu": 0.0,
    "uptime_sec": 1198750,
    "net_download": 735262,
    "net_upload": 718187,
    "traffic_users": 1878916479873,
    "traffic_node": 8636299913796,
    "users": 3
  },
  {
    "address": "EQBiZHSojM6yzeBqo_Ka06ZauPtuR4nVPs9gqOVFL68BLEi9",
    "is_active": true,
    "node_registry": "EQDbPc6xGV6-nCmDH8bVXUdQCQ1tXMM062Xah-63HAMAkpq8",
    "owner": "EQA0ltvrkBHmBa0QSTNHcZSUNIvha1F6hTwCCMGPbyVPNpTq",
    "tickets_total": 8254,
    "tickets_30d": 8254,
    "ratings_total": 1,
    "ratings_30d": 1,
    "ratings_avg_stars": 5.0,
    "ratings_avg_stars_30d": 5.0,
    "plan": "time",
    "hostname": "us.yastatic.site",
    "country": "US",
    "region": "California",
    "city": "San Jose",
    "ip": "23.106.45.14",
    "exit_ip": null,
    "ssl": true,
    "check_port": 443,
    "api_port": 443,
    "api_path": "/api/v1",
    "public_key": "1e7c0f8cc0a4f9fe2f7cd3d2165e7684feb03ed9427208fb4a5050ecf97608d1",
    "node_id": 228105844814,
    "scanned": "2026-05-05T03:44:08.234689Z",
    "heartbeat": "2026-05-05T03:43:34.545098Z",
    "health_check": "2026-05-05T03:44:09.421176Z",
    "version": "1.2.5",
    "uptime": 99,
    "limit": 100,
    "upload": 0,
    "download": 0,
    "disk": 5.08,
    "mem": 8.19,
    "cpu": 1.5189874024178007,
    "uptime_sec": 1212325,
    "net_download": 1093473,
    "net_upload": 1546329,
    "traffic_users": 3970840319045,
    "traffic_node": 10067961005542,
    "users": 17
  },
  {
    "address": "EQBfzVsVNKkJ7efRh8DJIfUKIeZmUJfreUSW989_ZSZa79cC",
    "is_active": true,
    "node_registry": "EQDbPc6xGV6-nCmDH8bVXUdQCQ1tXMM062Xah-63HAMAkpq8",
    "owner": "EQA0ltvrkBHmBa0QSTNHcZSUNIvha1F6hTwCCMGPbyVPNpTq",
    "tickets_total": 18141,
    "tickets_30d": 18141,
    "ratings_total": 0,
    "ratings_30d": 0,
    "ratings_avg_stars": 0.0,
    "ratings_avg_stars_30d": 0.0,
    "plan": "time",
    "hostname": "www.cdn-vk.run",
    "country": "FI",
    "region": "Uusimaa",
    "city": "Helsinki",
    "ip": "185.88.101.76",
    "exit_ip": null,
    "ssl": true,
    "check_port": 443,
    "api_port": 443,
    "api_path": "/api/v1",
    "public_key": "ddc79716c761d301bc2f31cb4b711eb7137d99d56b5ff27953cc58847c5d92fb",
    "node_id": 1848878100876,
    "scanned": "2026-05-05T03:44:08.227580Z",
    "heartbeat": "2026-05-05T03:43:49.654074Z",
    "health_check": "2026-05-05T03:44:07.232496Z",
    "version": "1.2.5",
    "uptime": 99,
    "limit": 100,
    "upload": 190,
    "download": 202,
    "disk": 29.72,
    "mem": 35.09,
    "cpu": 14.358974370975622,
    "uptime_sec": 894129,
    "net_download": 528489,
    "net_upload": 614820,
    "traffic_users": 10630127665492,
    "traffic_node": 25144781740559,
    "users": 27
  },
  {
    "address": "EQBfM5S7Wnn6MMGMoLnmBK-LXWtLc2q1z7ippDR_ZrSEeBCd",
    "is_active": true,
    "node_registry": "EQDbPc6xGV6-nCmDH8bVXUdQCQ1tXMM062Xah-63HAMAkpq8",
    "owner": "EQA0ltvrkBHmBa0QSTNHcZSUNIvha1F6hTwCCMGPbyVPNpTq",
    "tickets_total": 3948,
    "tickets_30d": 3948,
    "ratings_total": 0,
    "ratings_30d": 0,
    "ratings_avg_stars": 0.0,
    "ratings_avg_stars_30d": 0.0,
    "plan": "time",
    "hostname": "k2.cdn-vk.run",
    "country": "RU",
    "region": "Kuzbass",
    "city": "Kemerovo",
    "ip": "77.110.112.98",
    "exit_ip": null,
    "ssl": true,
    "check_port": 443,
    "api_port": 443,
    "api_path": "/api/v1",
    "public_key": "0aad45e26613921a6122a8a83b2f1ce8209aa4ca9bcda8b2eaba1e351f1e05b9",
    "node_id": 7681098111898,
    "scanned": "2026-05-05T03:44:08.221848Z",
    "heartbeat": "2026-05-05T03:44:04.754964Z",
    "health_check": "2026-05-05T03:44:08.820343Z",
    "version": "1.2.5",
    "uptime": 99,
    "limit": 100,
    "upload": 0,
    "download": 0,
    "disk": 76.82,
    "mem": 33.19,
    "cpu": 3.030303030213946,
    "uptime_sec": 140249,
    "net_download": 5827,
    "net_upload": 1513,
    "traffic_users": 486525544971,
    "traffic_node": 2913877849937,
    "users": 1
  },
  {
    "address": "EQBZC7OlRVv3KiL-vCEXWbjryAMk-OExcaPGp-cavU3ZytPT",
    "is_active": true,
    "node_registry": "EQDbPc6xGV6-nCmDH8bVXUdQCQ1tXMM062Xah-63HAMAkpq8",
    "owner": "EQA0ltvrkBHmBa0QSTNHcZSUNIvha1F6hTwCCMGPbyVPNpTq",
    "tickets_total": 2020,
    "tickets_30d": 2020,
    "ratings_total": 0,
    "ratings_30d": 0,
    "ratings_avg_stars": 0.0,
    "ratings_avg_stars_30d": 0.0,
    "plan": "time",
    "hostname": "au.media-cdn.online",
    "country": "DE",
    "region": "Hesse",
    "city": "Frankfurt am Main",
    "ip": "193.233.129.190",
    "exit_ip": null,
    "ssl": true,
    "check_port": 443,
    "api_port": 443,
    "api_path": "/api/v1",
    "public_key": "6a0ff3dee7047b1ce942f0c6547cce25edcb48e128c42f3e175f159507558bdd",
    "node_id": 192823281288190,
    "scanned": "2026-05-05T03:44:08.216149Z",
    "heartbeat": "2026-05-05T03:43:18.486045Z",
    "health_check": "2026-05-05T03:44:07.584646Z",
    "version": "1.2.5",
    "uptime": 99,
    "limit": 100,
    "upload": 0,
    "download": 0,
    "disk": 22.18,
    "mem": 15.65,
    "cpu": 0.0,
    "uptime_sec": 661828,
    "net_download": 1094,
    "net_upload": 1214,
    "traffic_users": 1380386033414,
    "traffic_node": 3694325562402,
    "users": 4
  },
  {
    "address": "EQBSQeJKxwFKaoeRmclry4iYzr3ymo8sPDEiaEF6G9snSAH0",
    "is_active": true,
    "node_registry": "EQDbPc6xGV6-nCmDH8bVXUdQCQ1tXMM062Xah-63HAMAkpq8",
    "owner": "EQA0ltvrkBHmBa0QSTNHcZSUNIvha1F6hTwCCMGPbyVPNpTq",
    "tickets_total": 1784,
    "tickets_30d": 1784,
    "ratings_total": 0,
    "ratings_30d": 0,
    "ratings_avg_stars": 0.0,
    "ratings_avg_stars_30d": 0.0,
    "plan": "time",
    "hostname": "deq.cdn-vk.rest",
    "country": "DE",
    "region": "Hesse",
    "city": "Frankfurt am Main",
    "ip": "5.61.41.115",
    "exit_ip": null,
    "ssl": true,
    "check_port": 443,
    "api_port": 443,
    "api_path": "/api/v1",
    "public_key": "3997593665976beb9d1058a44bd4034cdd812394f8c46736463d8854d58371bf",
    "node_id": 48608408115,
    "scanned": "2026-05-05T03:44:08.210147Z",
    "heartbeat": "2026-05-05T03:44:14.576270Z",
    "health_check": "2026-05-05T03:44:07.741963Z",
    "version": "1.2.5",
    "uptime": 99,
    "limit": 100,
    "upload": 0,
    "download": 0,
    "disk": 76.56,
    "mem": 16.82,
    "cpu": 8.080808088409938,
    "uptime_sec": 1207087,
    "net_download": 2960,
    "net_upload": 3069,
    "traffic_users": 1854853626289,
    "traffic_node": 4419132819290,
    "users": 1
  },
  {
    "address": "EQBRv1vDYL0fkotme954A8JLv9CxR6nfZYH6V6jHGsl_6szf",
    "is_active": true,
    "node_registry": "EQDbPc6xGV6-nCmDH8bVXUdQCQ1tXMM062Xah-63HAMAkpq8",
    "owner": "EQA0ltvrkBHmBa0QSTNHcZSUNIvha1F6hTwCCMGPbyVPNpTq",
    "tickets_total": 2446,
    "tickets_30d": 2446,
    "ratings_total": 0,
    "ratings_30d": 0,
    "ratings_avg_stars": 0.0,
    "ratings_avg_stars_30d": 0.0,
    "plan": "time",
    "hostname": "spbnl.cdn-vk.run",
    "country": "RU",
    "region": "St.-Petersburg",
    "city": "Saint Petersburg",
    "ip": "213.178.155.199",
    "exit_ip": null,
    "ssl": true,
    "check_port": 443,
    "api_port": 443,
    "api_path": "/api/v1",
    "public_key": "3b89f7cf27240c1d39ef37acff8f8ac238025e8704e29ac9d4d9418639185dc5",
    "node_id": 212817781548199,
    "scanned": "2026-05-05T03:44:08.186193Z",
    "heartbeat": "2026-05-05T03:44:10.000951Z",
    "health_check": "2026-05-05T03:44:07.803959Z",
    "version": "1.2.5",
    "uptime": 100,
    "limit": 100,
    "upload": 0,
    "download": 0,
    "disk": 63.68,
    "mem": 66.05,
    "cpu": 9.999999795109034,
    "uptime_sec": 1177578,
    "net_download": 744676,
    "net_upload": 706900,
    "traffic_users": 1296600419142,
    "traffic_node": 6338109956044,
    "users": 3
  },
  {
    "address": "EQBRE7je8hKmRKgp4HE8byhLtpgoJNwucGHowaAwYrD5F_JK",
    "is_active": true,
    "node_registry": "EQDbPc6xGV6-nCmDH8bVXUdQCQ1tXMM062Xah-63HAMAkpq8",
    "owner": "EQA0ltvrkBHmBa0QSTNHcZSUNIvha1F6hTwCCMGPbyVPNpTq",
    "tickets_total": 14157,
    "tickets_30d": 14157,
    "ratings_total": 0,
    "ratings_30d": 0,
    "ratings_avg_stars": 0.0,
    "ratings_avg_stars_30d": 0.0,
    "plan": "time",
    "hostname": "fin.cdn-vk.run",
    "country": "FI",
    "region": "Uusimaa",
    "city": "Helsinki",
    "ip": "31.56.204.94",
    "exit_ip": null,
    "ssl": true,
    "check_port": 443,
    "api_port": 443,
    "api_path": "/api/v1",
    "public_key": "0855ae5dea20161157948dc171d01ca5f616ec092a4d98bebeedce388e16ba99",
    "node_id": 308558203894,
    "scanned": "2026-05-05T03:44:08.180210Z",
    "heartbeat": "2026-05-05T03:44:06.214021Z",
    "health_check": "2026-05-05T03:44:07.284244Z",
    "version": "1.2.5",
    "uptime": 99,
    "limit": 100,
    "upload": 0,
    "download": 0,
    "disk": 38.75,
    "mem": 36.09,
    "cpu": 57.89473683952542,
    "uptime_sec": 467023,
    "net_download": 2139088,
    "net_upload": 2040241,
    "traffic_users": 11288729221965,
    "traffic_node": 26837451294011,
    "users": 25
  },
  {
    "address": "EQBJKbZTB3OzuAPeolc49ERDF4Drv_w5_MUI2ANJa2AJNI7H",
    "is_active": true,
    "node_registry": "EQDbPc6xGV6-nCmDH8bVXUdQCQ1tXMM062Xah-63HAMAkpq8",
    "owner": "EQA0ltvrkBHmBa0QSTNHcZSUNIvha1F6hTwCCMGPbyVPNpTq",
    "tickets_total": 11724,
    "tickets_30d": 11724,
    "ratings_total": 0,
    "ratings_30d": 0,
    "ratings_avg_stars": 0.0,
    "ratings_avg_stars_30d": 0.0,
    "plan": "time",
    "hostname": "cdn.edge-apple.online",
    "country": "NL",
    "region": "North Holland",
    "city": "Amsterdam",
    "ip": "45.15.129.41",
    "exit_ip": null,
    "ssl": true,
    "check_port": 443,
    "api_port": 443,
    "api_path": "/api/v1",
    "public_key": "4cefaf69d789192f4cc2c1546cdcde5890233c26ded70748922d4e895f419923",
    "node_id": 448148128841,
    "scanned": "2026-05-05T03:44:08.174566Z",
    "heartbeat": "2026-05-05T03:43:50.948381Z",
    "health_check": "2026-05-05T03:44:06.995045Z",
    "version": "1.2.5",
    "uptime": 99,
    "limit": 100,
    "upload": 0,
    "download": 0,
    "disk": 26.39,
    "mem": 62.43,
    "cpu": 30.86956519027908,
    "uptime_sec": 42838,
    "net_download": 911683,
    "net_upload": 899326,
    "traffic_users": 7081487229050,
    "traffic_node": 17817973931565,
    "users": 22
  },
  {
    "address": "EQBI4cSVPL6Bp5SyYL1vjEKuQFETRo3ewcXInmHke7qiYuKE",
    "is_active": true,
    "node_registry": "EQDbPc6xGV6-nCmDH8bVXUdQCQ1tXMM062Xah-63HAMAkpq8",
    "owner": "EQA0ltvrkBHmBa0QSTNHcZSUNIvha1F6hTwCCMGPbyVPNpTq",
    "tickets_total": 5130,
    "tickets_30d": 5130,
    "ratings_total": 0,
    "ratings_30d": 0,
    "ratings_avg_stars": 0.0,
    "ratings_avg_stars_30d": 0.0,
    "plan": "time",
    "hostname": "nl.yastatic.run",
    "country": "NL",
    "region": "Flevoland",
    "city": "Dronten",
    "ip": "195.93.244.178",
    "exit_ip": null,
    "ssl": true,
    "check_port": 443,
    "api_port": 443,
    "api_path": "/api/v1",
    "public_key": "3aa0235784fa2be34e5e6517273b8a07f519bb9320e2534533044a78e5d1c19f",
    "node_id": 19489282438178,
    "scanned": "2026-05-05T03:44:08.167792Z",
    "heartbeat": "2026-05-05T03:43:26.420326Z",
    "health_check": "2026-05-05T03:44:06.987136Z",
    "version": "1.2.5",
    "uptime": 99,
    "limit": 100,
    "upload": 0,
    "download": 0,
    "disk": 29.66,
    "mem": 30.22,
    "cpu": 27.619047621370648,
    "uptime_sec": 374413,
    "net_download": 19835,
    "net_upload": 10104,
    "traffic_users": 6357583262168,
    "traffic_node": 15433569123882,
    "users": 5
  },
  {
    "address": "EQBDGon7vbR_yN8H__V3bFFcFX5_8WAgk-fX3dsIKT8JhWtM",
    "is_active": true,
    "node_registry": "EQDbPc6xGV6-nCmDH8bVXUdQCQ1tXMM062Xah-63HAMAkpq8",
    "owner": "EQA0ltvrkBHmBa0QSTNHcZSUNIvha1F6hTwCCMGPbyVPNpTq",
    "tickets_total": 4847,
    "tickets_30d": 4847,
    "ratings_total": 0,
    "ratings_30d": 0,
    "ratings_avg_stars": 0.0,
    "ratings_avg_stars_30d": 0.0,
    "plan": "time",
    "hostname": "de.cdn-vk.run",
    "country": "DE",
    "region": "Hesse",
    "city": "Frankfurt am Main",
    "ip": "212.95.33.169",
    "exit_ip": null,
    "ssl": true,
    "check_port": 443,
    "api_port": 443,
    "api_path": "/api/v1",
    "public_key": "8880b7834449f8b81b60252e82b973e3a3dad8f5774f0c3cdf363df4a4243e3e",
    "node_id": 2118948328169,
    "scanned": "2026-05-05T03:44:08.161903Z",
    "heartbeat": "2026-05-05T03:44:01.174837Z",
    "health_check": "2026-05-05T03:44:06.642199Z",
    "version": "1.2.5",
    "uptime": 99,
    "limit": 100,
    "upload": 0,
    "download": 0,
    "disk": 5.38,
    "mem": 8.3,
    "cpu": 1.0075566992901583,
    "uptime_sec": 1208301,
    "net_download": 133571,
    "net_upload": 135169,
    "traffic_users": 2974679908489,
    "traffic_node": 7817100464286,
    "users": 11
  },
  {
    "address": "EQBBk3gSSbfMR0ZiQVdVSqIucBhUeE9l1USNX6UEDyDImA9V",
    "is_active": true,
    "node_registry": "EQDbPc6xGV6-nCmDH8bVXUdQCQ1tXMM062Xah-63HAMAkpq8",
    "owner": "EQA0ltvrkBHmBa0QSTNHcZSUNIvha1F6hTwCCMGPbyVPNpTq",
    "tickets_total": 17260,
    "tickets_30d": 17260,
    "ratings_total": 2,
    "ratings_30d": 2,
    "ratings_avg_stars": 5.0,
    "ratings_avg_stars_30d": 5.0,
    "plan": "time",
    "hostname": "pl.yastatic.site",
    "country": "PL",
    "region": "Mazovia",
    "city": "Warsaw",
    "ip": "151.241.227.114",
    "exit_ip": null,
    "ssl": true,
    "check_port": 443,
    "api_port": 443,
    "api_path": "/api/v1",
    "public_key": "50dd2683a3519eb41b4eaf8ac515ccc4eabdfa5cff15bacd0d05ecb7b4400e64",
    "node_id": 150824082268114,
    "scanned": "2026-05-05T03:44:08.156181Z",
    "heartbeat": "2026-05-05T03:43:57.322205Z",
    "health_check": "2026-05-05T03:44:06.864338Z",
    "version": "1.2.5",
    "uptime": 100,
    "limit": 100,
    "upload": 0,
    "download": 0,
    "disk": 31.26,
    "mem": 48.03,
    "cpu": 58.94736842763123,
    "uptime_sec": 41204,
    "net_download": 1391558,
    "net_upload": 1488807,
    "traffic_users": 5232253530250,
    "traffic_node": 14459463599901,
    "users": 18
  },
  {
    "address": "EQB5Xy4t1Ntsecb6CSgGByWfqYnPn6cqN16R1tSVgrdQgu5e",
    "is_active": true,
    "node_registry": "EQDbPc6xGV6-nCmDH8bVXUdQCQ1tXMM062Xah-63HAMAkpq8",
    "owner": "EQA0ltvrkBHmBa0QSTNHcZSUNIvha1F6hTwCCMGPbyVPNpTq",
    "tickets_total": 11055,
    "tickets_30d": 11055,
    "ratings_total": 0,
    "ratings_30d": 0,
    "ratings_avg_stars": 0.0,
    "ratings_avg_stars_30d": 0.0,
    "plan": "time",
    "hostname": "ru.yastatic.run",
    "country": "RU",
    "region": "Moscow Oblast",
    "city": "Korolev",
    "ip": "195.133.146.211",
    "exit_ip": null,
    "ssl": true,
    "check_port": 443,
    "api_port": 443,
    "api_path": "/api/v1",
    "public_key": "1d6c45e833ca03cf9765c4f98380d96e9d4812822a25e366b2c437a870715d26",
    "node_id": 194813281458211,
    "scanned": "2026-05-05T03:44:08.140600Z",
    "heartbeat": "2026-05-05T03:44:11.835997Z",
    "health_check": "2026-05-05T03:44:11.725035Z",
    "version": "1.2.5",
    "uptime": 97,
    "limit": 100,
    "upload": 0,
    "download": 0,
    "disk": 55.57,
    "mem": 55.53,
    "cpu": 6.0000000055879354,
    "uptime_sec": 24410,
    "net_download": 58224,
    "net_upload": 61419,
    "traffic_users": 1205028871166,
    "traffic_node": 7322229619207,
    "users": 8
  },
  {
    "address": "EQB2RQBZGpJocyFl8KAkvuVIkK7JFjnYHX0D6c9ISJk5WAWo",
    "is_active": true,
    "node_registry": "EQDbPc6xGV6-nCmDH8bVXUdQCQ1tXMM062Xah-63HAMAkpq8",
    "owner": "EQA0ltvrkBHmBa0QSTNHcZSUNIvha1F6hTwCCMGPbyVPNpTq",
    "tickets_total": 6365,
    "tickets_30d": 6365,
    "ratings_total": 0,
    "ratings_30d": 0,
    "ratings_avg_stars": 0.0,
    "ratings_avg_stars_30d": 0.0,
    "plan": "time",
    "hostname": "nov.media-cdn.online",
    "country": "RU",
    "region": "Novosibirsk Oblast",
    "city": "Novosibirsk",
    "ip": "194.87.213.185",
    "exit_ip": null,
    "ssl": true,
    "check_port": 443,
    "api_port": 443,
    "api_path": "/api/v1",
    "public_key": "2763286777beb9092b6dd0a65161e3c35e5b058bc61b7177ea4b26e459eae96e",
    "node_id": 19388682128185,
    "scanned": "2026-05-05T03:44:08.134815Z",
    "heartbeat": "2026-05-05T03:44:05.120925Z",
    "health_check": "2026-05-05T03:44:08.784422Z",
    "version": "1.2.5",
    "uptime": 99,
    "limit": 100,
    "upload": 0,
    "download": 0,
    "disk": 38.85,
    "mem": 63.45,
    "cpu": 9.900990087369511,
    "uptime_sec": 406976,
    "net_download": 2563487,
    "net_upload": 2524632,
    "traffic_users": 1571147046584,
    "traffic_node": 7952549151186,
    "users": 9
  },
  {
    "address": "EQB1MZdNK7EazQA5daPCcxtvE44FxQOO9hSlSIg0CMfq6WIW",
    "is_active": true,
    "node_registry": "EQDbPc6xGV6-nCmDH8bVXUdQCQ1tXMM062Xah-63HAMAkpq8",
    "owner": "EQA0ltvrkBHmBa0QSTNHcZSUNIvha1F6hTwCCMGPbyVPNpTq",
    "tickets_total": 8080,
    "tickets_30d": 8080,
    "ratings_total": 0,
    "ratings_30d": 0,
    "ratings_avg_stars": 0.0,
    "ratings_avg_stars_30d": 0.0,
    "plan": "time",
    "hostname": "it.cdn-vk.run",
    "country": "RU",
    "region": "Tatarstan Republic",
    "city": "Kazan",
    "ip": "213.226.112.65",
    "exit_ip": null,
    "ssl": true,
    "check_port": 443,
    "api_port": 443,
    "api_path": "/api/v1",
    "public_key": "bcb46722f795e38503620dd4f470c29a24b66931ceae4d3abc72c4e210a0c7df",
    "node_id": 21282258111865,
    "scanned": "2026-05-05T03:44:08.128697Z",
    "heartbeat": "2026-05-05T03:44:07.724992Z",
    "health_check": "2026-05-05T03:44:07.334805Z",
    "version": "1.2.5",
    "uptime": 100,
    "limit": 100,
    "upload": 0,
    "download": 0,
    "disk": 48.9,
    "mem": 73.49,
    "cpu": 27.18446597201299,
    "uptime_sec": 894093,
    "net_download": 11256540,
    "net_upload": 11727995,
    "traffic_users": 2465143189970,
    "traffic_node": 12345833102317,
    "users": 19
  },
  {
    "address": "EQAn7n9YreZRYLTUcPNHI3hIZU8QuQaVhi5q7IYGHOc9r_V2",
    "is_active": true,
    "node_registry": "EQDbPc6xGV6-nCmDH8bVXUdQCQ1tXMM062Xah-63HAMAkpq8",
    "owner": "EQA0ltvrkBHmBa0QSTNHcZSUNIvha1F6hTwCCMGPbyVPNpTq",
    "tickets_total": 26069,
    "tickets_30d": 26069,
    "ratings_total": 3,
    "ratings_30d": 3,
    "ratings_avg_stars": 4.33,
    "ratings_avg_stars_30d": 4.33,
    "plan": "time",
    "hostname": "se.relay-apple.online",
    "country": "SE",
    "region": "Stockholms l\u00e4n",
    "city": "Stockholm",
    "ip": "138.124.84.49",
    "exit_ip": null,
    "ssl": true,
    "check_port": 443,
    "api_port": 443,
    "api_path": "/api/v1",
    "public_key": "d75a8a6f44f47a99e304d7f878cc94a5fd12b14456d22f18ec427353ec323b34",
    "node_id": 1378123883849,
    "scanned": "2026-05-05T03:44:08.122924Z",
    "heartbeat": "2026-05-05T03:43:56.894590Z",
    "health_check": "2026-05-05T03:44:07.727388Z",
    "version": "1.2.5",
    "uptime": 99,
    "limit": 80,
    "upload": 0,
    "download": 0,
    "disk": 31.71,
    "mem": 27.61,
    "cpu": 9.743589740956814,
    "uptime_sec": 577198,
    "net_download": 4771963,
    "net_upload": 4868534,
    "traffic_users": 8854843308189,
    "traffic_node": 23766323602774,
    "users": 31
  },
  {
    "address": "EQAlr2DsKzSMsO-ADlPqJVOv5GRGb0iKw0nWKpBnym4sz-hS",
    "is_active": true,
    "node_registry": "EQDbPc6xGV6-nCmDH8bVXUdQCQ1tXMM062Xah-63HAMAkpq8",
    "owner": "EQA0ltvrkBHmBa0QSTNHcZSUNIvha1F6hTwCCMGPbyVPNpTq",
    "tickets_total": 29958,
    "tickets_30d": 29958,
    "ratings_total": 0,
    "ratings_30d": 0,
    "ratings_avg_stars": 0.0,
    "ratings_avg_stars_30d": 0.0,
    "plan": "time",
    "hostname": "ee.edge-apple.online",
    "country": "EE",
    "region": "Harjumaa",
    "city": "Tallinn",
    "ip": "23.230.179.233",
    "exit_ip": null,
    "ssl": true,
    "check_port": 443,
    "api_port": 443,
    "api_path": "/api/v1",
    "public_key": "6fb38fe7144ce1efc7086c54769db78be42ab0e5d301065f1c81148c65218159",
    "node_id": 22822981788233,
    "scanned": "2026-05-05T03:44:08.117062Z",
    "heartbeat": "2026-05-05T03:44:16.229803Z",
    "health_check": "2026-05-05T03:44:07.270679Z",
    "version": "1.2.5",
    "uptime": 99,
    "limit": 100,
    "upload": 0,
    "download": 0,
    "disk": 34.27,
    "mem": 39.75,
    "cpu": 43.52331605514418,
    "uptime_sec": 782274,
    "net_download": 9283794,
    "net_upload": 10831194,
    "traffic_users": 10738866316825,
    "traffic_node": 27158658655277,
    "users": 76
  },
  {
    "address": "EQAklR_7ov3Sz7VSYMFs-_83JylG3pdxM1OQAeayohAeuYmy",
    "is_active": true,
    "node_registry": "EQDbPc6xGV6-nCmDH8bVXUdQCQ1tXMM062Xah-63HAMAkpq8",
    "owner": "EQA0ltvrkBHmBa0QSTNHcZSUNIvha1F6hTwCCMGPbyVPNpTq",
    "tickets_total": 5070,
    "tickets_30d": 5070,
    "ratings_total": 0,
    "ratings_30d": 0,
    "ratings_avg_stars": 0.0,
    "ratings_avg_stars_30d": 0.0,
    "plan": "time",
    "hostname": "cloud.cdn-vk.run",
    "country": "RU",
    "region": "Moscow Oblast",
    "city": "Korolev",
    "ip": "195.133.146.74",
    "exit_ip": null,
    "ssl": true,
    "check_port": 443,
    "api_port": 443,
    "api_path": "/api/v1",
    "public_key": "d8e3b8704806ce095628fbf133cbfc37b57b45dad1bc238bb93368dd107d3ce0",
    "node_id": 19481328145874,
    "scanned": "2026-05-05T03:44:08.110510Z",
    "heartbeat": "2026-05-05T03:44:04.584182Z",
    "health_check": "2026-05-05T03:44:08.156487Z",
    "version": "1.2.5",
    "uptime": 100,
    "limit": 100,
    "upload": 0,
    "download": 0,
    "disk": 48.11,
    "mem": 65.69,
    "cpu": 5.154639174206047,
    "uptime_sec": 235103,
    "net_download": 2619541,
    "net_upload": 2522670,
    "traffic_users": 2189702836974,
    "traffic_node": 11279748834678,
    "users": 7
  },
  {
    "address": "EQAiqQCtVfHR1u8FpXMrb_BP5K9W7d8uZhEPGmwG9qd5fEAo",
    "is_active": true,
    "node_registry": "EQDbPc6xGV6-nCmDH8bVXUdQCQ1tXMM062Xah-63HAMAkpq8",
    "owner": "EQA0ltvrkBHmBa0QSTNHcZSUNIvha1F6hTwCCMGPbyVPNpTq",
    "tickets_total": 11311,
    "tickets_30d": 11311,
    "ratings_total": 0,
    "ratings_30d": 0,
    "ratings_avg_stars": 0.0,
    "ratings_avg_stars_30d": 0.0,
    "plan": "time",
    "hostname": "ek.cdn-vk.run",
    "country": "RU",
    "region": "Sverdlovsk Oblast",
    "city": "Yekaterinburg",
    "ip": "45.11.27.93",
    "exit_ip": null,
    "ssl": true,
    "check_port": 443,
    "api_port": 443,
    "api_path": "/api/v1",
    "public_key": "28a814326caec0cea681de85b4ade2a2ac99322ed99f5d171f8023f17916c20b",
    "node_id": 44810826893,
    "scanned": "2026-05-05T03:44:08.104386Z",
    "heartbeat": "2026-05-05T03:44:11.288384Z",
    "health_check": "2026-05-05T03:44:07.240264Z",
    "version": "1.2.5",
    "uptime": 99,
    "limit": 100,
    "upload": 0,
    "download": 0,
    "disk": 42.0,
    "mem": 63.34,
    "cpu": 19.387755096707338,
    "uptime_sec": 33924,
    "net_download": 3458476,
    "net_upload": 3383433,
    "traffic_users": 2853236871236,
    "traffic_node": 14679809022002,
    "users": 20
  },
  {
    "address": "EQAhzt3V7Ng5LZyQdx8LKs3ei5W2yKU5mNlEzOw5KN4PlGt7",
    "is_active": true,
    "node_registry": "EQDbPc6xGV6-nCmDH8bVXUdQCQ1tXMM062Xah-63HAMAkpq8",
    "owner": "EQA0ltvrkBHmBa0QSTNHcZSUNIvha1F6hTwCCMGPbyVPNpTq",
    "tickets_total": 3362,
    "tickets_30d": 3362,
    "ratings_total": 0,
    "ratings_30d": 0,
    "ratings_avg_stars": 0.0,
    "ratings_avg_stars_30d": 0.0,
    "plan": "time",
    "hostname": "ca.yastatic.site",
    "country": "CA",
    "region": "Quebec",
    "city": "Montr\u00e9al",
    "ip": "184.107.179.25",
    "exit_ip": null,
    "ssl": true,
    "check_port": 443,
    "api_port": 443,
    "api_path": "/api/v1",
    "public_key": "b01d259434de07393001ffd7d1b67e3181e191b29eb339f3dea5d660c0e8105b",
    "node_id": 18381068178825,
    "scanned": "2026-05-05T03:44:08.090866Z",
    "heartbeat": "2026-05-05T03:43:56.170871Z",
    "health_check": "2026-05-05T03:44:07.328628Z",
    "version": "1.2.5",
    "uptime": 99,
    "limit": 100,
    "upload": 0,
    "download": 0,
    "disk": 5.09,
    "mem": 7.64,
    "cpu": 1.0025062436682377,
    "uptime_sec": 1214466,
    "net_download": 140258,
    "net_upload": 159624,
    "traffic_users": 1359075337477,
    "traffic_node": 3940284546409,
    "users": 2
  },
  {
    "address": "EQAfwxqts_LkQ-sz-yHPHgZ2hOGIvUUmA9o28M53aaq0Yq54",
    "is_active": true,
    "node_registry": "EQDbPc6xGV6-nCmDH8bVXUdQCQ1tXMM062Xah-63HAMAkpq8",
    "owner": "EQA0ltvrkBHmBa0QSTNHcZSUNIvha1F6hTwCCMGPbyVPNpTq",
    "tickets_total": 2447,
    "tickets_30d": 2447,
    "ratings_total": 1,
    "ratings_30d": 1,
    "ratings_avg_stars": 5.0,
    "ratings_avg_stars_30d": 5.0,
    "plan": "time",
    "hostname": "get.yastatic.site",
    "country": "TH",
    "region": "Bangkok",
    "city": "Bangkok",
    "ip": "165.101.64.91",
    "exit_ip": null,
    "ssl": true,
    "check_port": 443,
    "api_port": 443,
    "api_path": "/api/v1",
    "public_key": "95a655617b2552968eca587046418cd883dc8bad43658d333c8cb5de7b31d324",
    "node_id": 1648100863891,
    "scanned": "2026-05-05T03:44:08.085667Z",
    "heartbeat": "2026-05-05T03:43:41.046975Z",
    "health_check": "2026-05-05T03:44:08.771802Z",
    "version": "1.2.5",
    "uptime": 86,
    "limit": 100,
    "upload": 239,
    "download": 672,
    "disk": 55.25,
    "mem": 45.17,
    "cpu": 0.9999999776482582,
    "uptime_sec": 1208683,
    "net_download": 23289,
    "net_upload": 19009,
    "traffic_users": 606556297220,
    "traffic_node": 1819122398590,
    "users": 3
  },
  {
    "address": "EQAchHEeIMxdV2V3eV5LCgMvIkD626XCsszEcz34XyTdVB3A",
    "is_active": true,
    "node_registry": "EQDbPc6xGV6-nCmDH8bVXUdQCQ1tXMM062Xah-63HAMAkpq8",
    "owner": "EQA0ltvrkBHmBa0QSTNHcZSUNIvha1F6hTwCCMGPbyVPNpTq",
    "tickets_total": 877,
    "tickets_30d": 877,
    "ratings_total": 0,
    "ratings_30d": 0,
    "ratings_avg_stars": 0.0,
    "ratings_avg_stars_30d": 0.0,
    "plan": "time",
    "hostname": "ca.cdn-vk.rest",
    "country": "CA",
    "region": "Quebec",
    "city": "Montr\u00e9al",
    "ip": "68.71.45.152",
    "exit_ip": null,
    "ssl": true,
    "check_port": 443,
    "api_port": 443,
    "api_path": "/api/v1",
    "public_key": "7c465c1ca9dbc6d968694a74fd4ad177077a28506893adf98b8015fd652ec4d5",
    "node_id": 678708448152,
    "scanned": "2026-05-05T03:44:08.080228Z",
    "heartbeat": "2026-05-05T03:44:02.362469Z",
    "health_check": "2026-05-05T03:44:08.809859Z",
    "version": "1.2.5",
    "uptime": 99,
    "limit": 100,
    "upload": 0,
    "download": 0,
    "disk": 73.53,
    "mem": 12.09,
    "cpu": 0.0,
    "uptime_sec": 1211964,
    "net_download": 0,
    "net_upload": 0,
    "traffic_users": 821256622232,
    "traffic_node": 2107538097614,
    "users": 0
  },
  {
    "address": "EQAZdBrzhtrQfAdMdIg1fXUef8j0SSf7oWlcJeAKw1jSxKts",
    "is_active": true,
    "node_registry": "EQDbPc6xGV6-nCmDH8bVXUdQCQ1tXMM062Xah-63HAMAkpq8",
    "owner": "EQA0ltvrkBHmBa0QSTNHcZSUNIvha1F6hTwCCMGPbyVPNpTq",
    "tickets_total": 2687,
    "tickets_30d": 2687,
    "ratings_total": 0,
    "ratings_30d": 0,
    "ratings_avg_stars": 0.0,
    "ratings_avg_stars_30d": 0.0,
    "plan": "time",
    "hostname": "jp.yastatic.site",
    "country": "JP",
    "region": "Tokyo",
    "city": "Tokyo",
    "ip": "142.91.109.126",
    "exit_ip": null,
    "ssl": true,
    "check_port": 443,
    "api_port": 443,
    "api_path": "/api/v1",
    "public_key": "abe7507075772510ce0abefeac25cae4401401c6a8512f6fad72dfbfe8fe3707",
    "node_id": 14189081088126,
    "scanned": "2026-05-05T03:44:08.074630Z",
    "heartbeat": "2026-05-05T03:43:10.343126Z",
    "health_check": "2026-05-05T03:44:10.507945Z",
    "version": "1.2.5",
    "uptime": 99,
    "limit": 100,
    "upload": 0,
    "download": 0,
    "disk": 5.09,
    "mem": 7.02,
    "cpu": 1.2594457703198876,
    "uptime_sec": 1214417,
    "net_download": 367372,
    "net_upload": 370474,
    "traffic_users": 856191827647,
    "traffic_node": 2760438599325,
    "users": 7
  },
  {
    "address": "EQAWdcYsjSA8ZEM1FhvFocz0NNEX_4O3yqiaS7p2oPAi0j4q",
    "is_active": true,
    "node_registry": "EQDbPc6xGV6-nCmDH8bVXUdQCQ1tXMM062Xah-63HAMAkpq8",
    "owner": "EQA0ltvrkBHmBa0QSTNHcZSUNIvha1F6hTwCCMGPbyVPNpTq",
    "tickets_total": 6306,
    "tickets_30d": 6306,
    "ratings_total": 4,
    "ratings_30d": 4,
    "ratings_avg_stars": 4.25,
    "ratings_avg_stars_30d": 4.25,
    "plan": "time",
    "hostname": "eu.yastatic.run",
    "country": "NL",
    "region": "Flevoland",
    "city": "Dronten",
    "ip": "212.87.223.232",
    "exit_ip": null,
    "ssl": true,
    "check_port": 443,
    "api_port": 443,
    "api_path": "/api/v1",
    "public_key": "452814d87e05f130d11c100a328a7ae08db3beb61d0993bdf8c7311a1bc43397",
    "node_id": 21188682228232,
    "scanned": "2026-05-05T03:44:08.068979Z",
    "heartbeat": "2026-05-05T03:44:14.760313Z",
    "health_check": "2026-05-05T03:44:09.843548Z",
    "version": "1.2.5",
    "uptime": 98,
    "limit": 100,
    "upload": 0,
    "download": 0,
    "disk": 29.7,
    "mem": 24.67,
    "cpu": 38.90784982981259,
    "uptime_sec": 225048,
    "net_download": 73835,
    "net_upload": 1024220,
    "traffic_users": 4017932191441,
    "traffic_node": 10441821710148,
    "users": 10
  },
  {
    "address": "EQALo8Rmy6nva0quulLFQzZDKo_SYIrmotQkAtbJWpu8kJVv",
    "is_active": true,
    "node_registry": "EQDbPc6xGV6-nCmDH8bVXUdQCQ1tXMM062Xah-63HAMAkpq8",
    "owner": "EQA0ltvrkBHmBa0QSTNHcZSUNIvha1F6hTwCCMGPbyVPNpTq",
    "tickets_total": 2677,
    "tickets_30d": 2677,
    "ratings_total": 0,
    "ratings_30d": 0,
    "ratings_avg_stars": 0.0,
    "ratings_avg_stars_30d": 0.0,
    "plan": "time",
    "hostname": "m9.cdn-vk.run",
    "country": "RU",
    "region": "Moscow",
    "city": "Moscow",
    "ip": "194.87.207.232",
    "exit_ip": null,
    "ssl": true,
    "check_port": 443,
    "api_port": 443,
    "api_path": "/api/v1",
    "public_key": "ed9dc4e1207d42e75c379d987a3968a747f38f951754aa7d09472e56de837f1a",
    "node_id": 19388682068232,
    "scanned": "2026-05-05T03:44:08.063208Z",
    "heartbeat": "2026-05-05T03:43:48.392659Z",
    "health_check": "2026-05-05T03:44:07.675899Z",
    "version": "1.2.5",
    "uptime": 100,
    "limit": 100,
    "upload": 0,
    "download": 0,
    "disk": 47.25,
    "mem": 59.82,
    "cpu": 1.0000000009313226,
    "uptime_sec": 592004,
    "net_download": 321,
    "net_upload": 883,
    "traffic_users": 986445324250,
    "traffic_node": 5090535956277,
    "users": 2
  },
  {
    "address": "EQAIdINT1SJWqJ4I7ISaeEaYN6dp2q5ORt0VQZlCPlwjYJyz",
    "is_active": true,
    "node_registry": "EQDbPc6xGV6-nCmDH8bVXUdQCQ1tXMM062Xah-63HAMAkpq8",
    "owner": "EQA0ltvrkBHmBa0QSTNHcZSUNIvha1F6hTwCCMGPbyVPNpTq",
    "tickets_total": 5439,
    "tickets_30d": 5439,
    "ratings_total": 0,
    "ratings_30d": 0,
    "ratings_avg_stars": 0.0,
    "ratings_avg_stars_30d": 0.0,
    "plan": "time",
    "hostname": "msk.media-cdn.online",
    "country": "RU",
    "region": "Moscow",
    "city": "Moscow",
    "ip": "150.241.85.124",
    "exit_ip": null,
    "ssl": true,
    "check_port": 443,
    "api_port": 443,
    "api_path": "/api/v1",
    "public_key": "a26d906f82cd4ff5a270dbd3694cd1e5f9485c5636d862ca90b39be4f7f88f12",
    "node_id": 14982408848124,
    "scanned": "2026-05-05T03:44:08.054709Z",
    "heartbeat": "2026-05-05T03:43:11.359941Z",
    "health_check": "2026-05-05T03:44:07.694447Z",
    "version": "1.2.5",
    "uptime": 99,
    "limit": 100,
    "upload": 0,
    "download": 0,
    "disk": 16.4,
    "mem": 26.63,
    "cpu": 6.000000004190952,
    "uptime_sec": 1206800,
    "net_download": 226402,
    "net_upload": 258401,
    "traffic_users": 730254895127,
    "traffic_node": 3183073973635,
    "users": 6
  },
  {
    "address": "EQAAcXmsodmvyT2e8nMcSjKWAXEEuJDkktkm-9ZMtIy0E7E1",
    "is_active": true,
    "node_registry": "EQDbPc6xGV6-nCmDH8bVXUdQCQ1tXMM062Xah-63HAMAkpq8",
    "owner": "EQA0ltvrkBHmBa0QSTNHcZSUNIvha1F6hTwCCMGPbyVPNpTq",
    "tickets_total": 8814,
    "tickets_30d": 8814,
    "ratings_total": 0,
    "ratings_30d": 0,
    "ratings_avg_stars": 0.0,
    "ratings_avg_stars_30d": 0.0,
    "plan": "time",
    "hostname": "nova.cdn-vk.rest",
    "country": "RU",
    "region": "Orenburgskaya oblast'",
    "city": "\u041a\u0438\u0440\u043f\u0438\u0447\u043d\u044b\u0439 \u0417\u0430\u0432\u043e\u0434",
    "ip": "193.233.49.42",
    "exit_ip": null,
    "ssl": true,
    "check_port": 443,
    "api_port": 443,
    "api_path": "/api/v1",
    "public_key": "a94dc7165eff460ce70317691314364b9fc718f5c17df9bcb091937697c3156a",
    "node_id": 1928232848842,
    "scanned": "2026-05-05T03:44:08.047185Z",
    "heartbeat": "2026-05-02T03:59:59.617753Z",
    "health_check": "2026-05-02T04:10:32.087079Z",
    "version": "1.2.5",
    "uptime": 99,
    "limit": 30,
    "upload": 0,
    "download": 0,
    "disk": 50.87,
    "mem": 39.14,
    "cpu": 59.78260868024749,
    "uptime_sec": 940490,
    "net_download": 3080777,
    "net_upload": 3238472,
    "traffic_users": 5576861359390,
    "traffic_node": 21714093016045,
    "users": 24
  },
  {
    "address": "EQA7s3Php7TJS__Y71xns5QSEqt54rtuMC9_Tg50eN4AUFnd",
    "is_active": true,
    "node_registry": "EQDbPc6xGV6-nCmDH8bVXUdQCQ1tXMM062Xah-63HAMAkpq8",
    "owner": "EQA0ltvrkBHmBa0QSTNHcZSUNIvha1F6hTwCCMGPbyVPNpTq",
    "tickets_total": 11233,
    "tickets_30d": 11233,
    "ratings_total": 1,
    "ratings_30d": 1,
    "ratings_avg_stars": 4.0,
    "ratings_avg_stars_30d": 4.0,
    "plan": "time",
    "hostname": "eu.cdn-vk.run",
    "country": "FR",
    "region": "Grand Est",
    "city": "Lauterbourg",
    "ip": "62.169.29.73",
    "exit_ip": null,
    "ssl": true,
    "check_port": 443,
    "api_port": 443,
    "api_path": "/api/v1",
    "public_key": "c7f6b5ef5cc09c29c1befeeeccb4db052a5234a595286584d416ddee69a850b3",
    "node_id": 618168828873,
    "scanned": "2026-05-05T03:44:08.038351Z",
    "heartbeat": "2026-05-05T03:43:51.529171Z",
    "health_check": "2026-05-05T03:44:06.736254Z",
    "version": "1.2.5",
    "uptime": 99,
    "limit": 100,
    "upload": 0,
    "download": 0,
    "disk": 8.02,
    "mem": 6.35,
    "cpu": 2.025316452069999,
    "uptime_sec": 1208696,
    "net_download": 519434,
    "net_upload": 638392,
    "traffic_users": 587386126524,
    "traffic_node": 2706500203579,
    "users": 5
  },
  {
    "address": "EQA-YJB0ILq3Te7Ss9MZW9eKPvVeoPrHAYBOtkQWNuV7q_ae",
    "is_active": true,
    "node_registry": "EQDbPc6xGV6-nCmDH8bVXUdQCQ1tXMM062Xah-63HAMAkpq8",
    "owner": "EQA0ltvrkBHmBa0QSTNHcZSUNIvha1F6hTwCCMGPbyVPNpTq",
    "tickets_total": 1792,
    "tickets_30d": 1792,
    "ratings_total": 30,
    "ratings_30d": 30,
    "ratings_avg_stars": 4.77,
    "ratings_avg_stars_30d": 4.77,
    "plan": "time",
    "hostname": "sg.yastatic.site",
    "country": "SG",
    "region": "Singapore",
    "city": "Singapore",
    "ip": "23.111.14.225",
    "exit_ip": null,
    "ssl": true,
    "check_port": 443,
    "api_port": 443,
    "api_path": "/api/v1",
    "public_key": "234e1731051886541b26642f19afb1d7c78fe6ec0a421076c73177df1a971d41",
    "node_id": 2281108138225,
    "scanned": "2026-05-05T03:44:08.017926Z",
    "heartbeat": "2026-05-05T03:43:41.666344Z",
    "health_check": "2026-05-05T03:44:09.652124Z",
    "version": "1.2.5",
    "uptime": 99,
    "limit": 100,
    "upload": 0,
    "download": 0,
    "disk": 5.07,
    "mem": 7.18,
    "cpu": 1.0025062436682377,
    "uptime_sec": 333195,
    "net_download": 39540,
    "net_upload": 40809,
    "traffic_users": 2659926672608,
    "traffic_node": 7798100658816,
    "users": 8
  }
]